Workbook

Sheet 总表
A1: 商品编码 | B1: PT品牌asin | C1: 平台商品编码 | D1: 发货方式 | E1: 平台SKU状态 | F1: 新/老品 | G1: q2 bcg（asin） | H1: q3 bcg（asin） | I1: q2 bcg（商编维度） | J1: 当前界面list price | K1: 红线价 | L1: 中心价 | M1: 价格下限 | N1: 价格上限 | O1: 4月销量 | P1: 5月销量 | Q1: 6月销量 | R1: 7月销量 | S1: 8月销量 | T1: 9月销量 | U1: 10月销量（截至10.14） | V1: Q2毛利率 | W1: Q3毛利率 | X1: 9月毛利率 | Y1: 9月退款率 | Z1: 9月广告费率 | AA1: 9月促销费率 | AB1: 9月转化率 | AC1: 9月广告转化率 | AD1: FBA可用 | AE1: FBA可售 | AF1: FBA在途 | AG1: 海外仓可用库存 | AH1: 海外仓在途库存 | AI1: Q2市场月均销量 | AJ1: Q3市场月均销量 | AK1: Q2月均销量 | AL1: Q3月均销量 | AM1: PT Q2asin市占 | AN1: PT Q3asin市占
A2: OO2EWP09900 | B2: B0G3LJ7K3X | C2: 3459EWP099NUS | D2: FBA | E2: 维稳 | F2: 老品 | G2: 瘦狗 | H2: 明星 | I2: 潜力 | J2: 29.99 | K2: 22.77 | L2: 34.8 | M2: 31.32 | N2: 38.29 | O2: 0 | P2: 0 | Q2: 0 | R2: 10 | S2: 11 | T2: 17 | U2: 6 | V2: 0 | W2: 0.20017386 | X2: 0.18910482 | Y2: 0.11111111 | Z2: 0.040013338 | AA2: 0.058284152 | AB2: 0.17346939 | AC2: 0.11077784 | AD2: =VLOOKUP(B:B,库存明细报表10.16!L:P,5,0) -> 2 | AE2: =VLOOKUP(B:B,库存明细报表10.16!L:Q,6,0) -> 0 | AF2: =VLOOKUP(B:B,库存明细报表10.16!L:T,9,0) -> 1 | AG2: =VLOOKUP(A:A,进销存报表10.16!A:J,10,0) -> 21 | AH2: =VLOOKUP(A:A,进销存报表10.16!A:K,11,0) -> 37 | AI2: 140.87 | AJ2: 126.03 | AK2: 0 | AL2: 13.333333 | AM2: =AK2/AI2 -> 0 | AN2: =AL2/AJ2 -> 0.10579492
A3: OO2EWP10100 | B3: B0GWQLK91B | C3: 8230EWP101JUS | D3: FBA | E3: 维稳 | F3: 老品 | G3: 瘦狗 | H3: 明星 | I3: 潜力 | J3: 49.99 | K3: 40.12 | L3: 45.58 | M3: 41.02 | N3: 50.14 | O3: 0 | P3: 0 | Q3: 0 | R3: 8 | S3: 1 | T3: 2 | U3: 2 | V3: 0 | W3: 0.21656093 | X3: 0.18368618 | Y3: 0 | Z3: 0.033706741 | AA3: 0.043829522 | AB3: 0.125 | AC3: 0 | AD3: =VLOOKUP(B:B,库存明细报表10.16!L:P,5,0) -> 4 | AE3: =VLOOKUP(B:B,库存明细报表10.16!L:Q,6,0) -> 4 | AF3: =VLOOKUP(B:B,库存明细报表10.16!L:T,9,0) -> 0 | AG3: =VLOOKUP(A:A,进销存报表10.16!A:J,10,0) -> 12 | AH3: =VLOOKUP(A:A,进销存报表10.16!A:K,11,0) -> 6 | AI3: 42.2 | AJ3: 32.83 | AK3: 0 | AL3: 3.6666667 | AM3: =AK3/AI3 -> 0 | AN3: =AL3/AJ3 -> 0.11168647
A4: OO2EWP11800 | B4: B0GWQVWRRZ | C4: 3194EWP118ZUS | D4: FBA | E4: 风险 | F4: 老品 | G4: 瘦狗 | H4: 金牛 | I4: 瘦狗 | J4: 27.99 | K4: 19.63 | L4: 27.66 | M4: 24.89 | N4: 30.42 | O4: 0 | P4: 0 | Q4: 0 | R4: 2 | S4: 10 | T4: 14 | U4: 3 | V4: 0 | W4: 0.162043 | X4: 0.11569841 | Y4: 0.22936356 | Z4: 0.019229719 | AA4: 0.060418107 | AB4: 0.25454545 | AC4: 0.213747 | AD4: =VLOOKUP(B:B,库存明细报表10.16!L:P,5,0) -> 3 | AE4: =VLOOKUP(B:B,库存明细报表10.16!L:Q,6,0) -> 3 | AF4: =VLOOKUP(B:B,库存明细报表10.16!L:T,9,0) -> 0 | AG4: =VLOOKUP(A:A,进销存报表10.16!A:J,10,0) -> 3 | AH4: =VLOOKUP(A:A,进销存报表10.16!A:K,11,0) -> 2 | AI4: 48.68 | AJ4: 40.86 | AK4: 0 | AL4: 9.3333333 | AM4: =AK4/AI4 -> 0 | AN4: =AL4/AJ4 -> 0.22842225
A5: OO2EWP11000 | B5: B0GWZL1L53 | C5: 6164EWP1104US | D5: FBA | E5: 维稳 | F5: 老品 | G5: 瘦狗 | H5: 瘦狗 | I5: 潜力 | J5: 25.99 | K5: 20.54 | L5: 20.32 | M5: 18.29 | N5: 22.35 | O5: 0 | P5: 0 | Q5: 0 | R5: 0 | S5: 5 | T5: 5 | U5: 1 | V5: 0 | W5: 0.11282211 | X5: -0.10904087 | Y5: 0.38983051 | Z5: 0.060071996 | AA5: 0.046719391 | AB5: 0.13513513 | AC5: 0.14244878 | AD5: =VLOOKUP(B:B,库存明细报表10.16!L:P,5,0) -> 15 | AE5: =VLOOKUP(B:B,库存明细报表10.16!L:Q,6,0) -> 15 | AF5: =VLOOKUP(B:B,库存明细报表10.16!L:T,9,0) -> 0 | AG5: =VLOOKUP(A:A,进销存报表10.16!A:J,10,0) -> 8 | AH5: =VLOOKUP(A:A,进销存报表10.16!A:K,11,0) -> 0 | AI5: 176.85 | AJ5: 101.32 | AK5: 0 | AL5: 3.6666667 | AM5: =AK5/AI5 -> 0 | AN5: =AL5/AJ5 -> 0.036188972
A6: OO2EWP05700 | B6: B0GWZGC7Q9 | C6: 5000EWP057FUS | D6: FBA | E6: 维稳 | F6: 老品 | G6: 瘦狗 | H6: 金牛 | I6: 潜力 | J6: 25.99 | K6: 21.94 | L6: 22.79 | M6: 20.51 | N6: 25.07 | O6: 0 | P6: 0 | Q6: 0 | R6: 13 | S6: 10 | T6: 0 | U6: 1 | V6: 0 | W6: 0.10810784 | X6: -0.7383248 | Y6: 0 | Z6: 1.3232558 | AA6: 0.003821135 | AB6: 0 | AC6: 0 | AD6: =VLOOKUP(B:B,库存明细报表10.16!L:P,5,0) -> 23 | AE6: =VLOOKUP(B:B,库存明细报表10.16!L:Q,6,0) -> 3 | AF6: =VLOOKUP(B:B,库存明细报表10.16!L:T,9,0) -> 0 | AG6: =VLOOKUP(A:A,进销存报表10.16!A:J,10,0) -> 3 | AH6: =VLOOKUP(A:A,进销存报表10.16!A:K,11,0) -> 21 | AI6: 122.21 | AJ6: 84.22 | AK6: 0 | AL6: 8.6666667 | AM6: =AK6/AI6 -> 0 | AN6: =AL6/AJ6 -> 0.10290509
A7: OO2EWP07200 | B7: B0GX5FC5K7 | C7: 3824EWP0720US | D7: FBA | E7: 维稳 | F7: 老品 | G7: 瘦狗 | H7: 瘦狗 | I7: 瘦狗 | J7: 22.99 | K7: 18.41 | L7: 19.41 | M7: 17.47 | N7: 21.35 | O7: 0 | P7: 0 | Q7: 0 | R7: 2 | S7: 2 | T7: 4 | U7: 6 | V7: 0 | W7: 0.17344889 | X7: 0.16822218 | Y7: 0 | Z7: 0.10305508 | AA7: 0.083855983 | AB7: 0.13793103 | AC7: 0.1869391 | AD7: =VLOOKUP(B:B,库存明细报表10.16!L:P,5,0) -> 17 | AE7: =VLOOKUP(B:B,库存明细报表10.16!L:Q,6,0) -> 14 | AF7: =VLOOKUP(B:B,库存明细报表10.16!L:T,9,0) -> 0 | AG7: =VLOOKUP(A:A,进销存报表10.16!A:J,10,0) -> 9 | AH7: =VLOOKUP(A:A,进销存报表10.16!A:K,11,0) -> 9 | AI7: 71.28 | AJ7: 47.77 | AK7: 0 | AL7: 2.6666667 | AM7: =AK7/AI7 -> 0 | AN7: =AL7/AJ7 -> 0.055823041
A8: OO2EWP11100 | B8: B0GWZBTZQ1 | C8: 1808EWP111ZUS | D8: FBA | E8: 维稳 | F8: 老品 | G8: 瘦狗 | H8: 瘦狗 | I8: 金牛 | J8: 31.99 | K8: 29.52 | L8: 29.52 | M8: 26.57 | N8: 32.47 | O8: 0 | P8: 0 | Q8: 0 | R8: 3 | S8: 6 | T8: 1 | U8: 2 | V8: 0 | W8: 0.029675854 | X8: 0 | Y8: 0 | Z8: #DIV/0! | AA8: #DIV/0! | AB8: 0.029411765 | AC8: 0.19945807 | AD8: =VLOOKUP(B:B,库存明细报表10.16!L:P,5,0) -> 19 | AE8: =VLOOKUP(B:B,库存明细报表10.16!L:Q,6,0) -> 19 | AF8: =VLOOKUP(B:B,库存明细报表10.16!L:T,9,0) -> 0 | AG8: =VLOOKUP(A:A,进销存报表10.16!A:J,10,0) -> 20 | AH8: =VLOOKUP(A:A,进销存报表10.16!A:K,11,0) -> 15 | AI8: 80.6 | AJ8: 40.8 | AK8: 0 | AL8: 3 | AM8: =AK8/AI8 -> 0 | AN8: =AL8/AJ8 -> 0.073529412
A9: OO2EWP11200 | B9: B0GWQXJ3LD | C9: 8557EWP1125US | D9: FBA | E9: 维稳 | F9: 老品 | G9: 瘦狗 | H9: 瘦狗 | I9: 金牛 | J9: 32.99 | K9: 21.69 | L9: 22.87 | M9: 20.58 | N9: 25.15 | O9: 0 | P9: 0 | Q9: 0 | R9: 0 | S9: 0 | T9: 1 | U9: 0 | V9: 0 | W9: 0.13382195 | X9: 0.19220113 | Y9: 0 | Z9: 0.12640194 | AA9: 0.08384568 | AB9: 0.035714286 | AC9: 0.12467398 | AD9: =VLOOKUP(B:B,库存明细报表10.16!L:P,5,0) -> 8 | AE9: =VLOOKUP(B:B,库存明细报表10.16!L:Q,6,0) -> 8 | AF9: =VLOOKUP(B:B,库存明细报表10.16!L:T,9,0) -> 2 | AG9: =VLOOKUP(A:A,进销存报表10.16!A:J,10,0) -> 18 | AH9: =VLOOKUP(A:A,进销存报表10.16!A:K,11,0) -> 3 | AI9: 27.29 | AJ9: 18.57 | AK9: 0 | AL9: 0.33333333 | AM9: =AK9/AI9 -> 0 | AN9: =AL9/AJ9 -> 0.017950099
A10: OO2EWP04400 | B10: B0GWZBPSDW | C10: 7785EWP044NUS | D10: FBA | E10: 维稳 | F10: 老品 | G10: 瘦狗 | H10: 金牛 | I10: 瘦狗 | J10: 45.99 | K10: 38.41 | L10: 42.24 | M10: 38.01 | N10: 46.46 | O10: 0 | P10: 0 | Q10: 0 | R10: 5 | S10: 2 | T10: 7 | U10: 1 | V10: 0 | W10: 0.072132173 | X10: 0.17543801 | Y10: 0 | Z10: 0.032056893 | AA10: 0.003821543 | AB10: 0.12962963 | AC10: 0.0554199 | AD10: =VLOOKUP(B:B,库存明细报表10.16!L:P,5,0) -> 19 | AE10: =VLOOKUP(B:B,库存明细报表10.16!L:Q,6,0) -> 19 | AF10: =VLOOKUP(B:B,库存明细报表10.16!L:T,9,0) -> 0 | AG10: =VLOOKUP(A:A,进销存报表10.16!A:J,10,0) -> 8 | AH10: =VLOOKUP(A:A,进销存报表10.16!A:K,11,0) -> 24 | AI10: 60.02 | AJ10: 45.02 | AK10: 0 | AL10: 5.3333333 | AM10: =AK10/AI10 -> 0 | AN10: =AL10/AJ10 -> 0.11846587
A11: OO2EWP09800 | B11: B0GWQPPJ13 | C11: 3544EWP0987US | D11: FBA | E11: 风险 | F11: 老品 | G11: 瘦狗 | H11: 潜力 | I11: 潜力 | J11: 27.99 | K11: 18.31 | L11: 20.33 | M11: 18.29 | N11: 22.36 | O11: 0 | P11: 1 | Q11: 0 | R11: 0 | S11: 4 | T11: 0 | U11: 1 | V11: 0 | W11: 0.30875024 | X11: 0 | Y11: 0 | Z11: #DIV/0! | AA11: #DIV/0! | AB11: 0 | AC11: 0 | AD11: =VLOOKUP(B:B,库存明细报表10.16!L:P,5,0) -> 27 | AE11: =VLOOKUP(B:B,库存明细报表10.16!L:Q,6,0) -> 26 | AF11: =VLOOKUP(B:B,库存明细报表10.16!L:T,9,0) -> 0 | AG11: =VLOOKUP(A:A,进销存报表10.16!A:J,10,0) -> 19 | AH11: =VLOOKUP(A:A,进销存报表10.16!A:K,11,0) -> 10 | AI11: 305.39 | AJ11: 160.5 | AK11: 0 | AL11: 1.3333333 | AM11: =AK11/AI11 -> 0 | AN11: =AL11/AJ11 -> 0.0083073728
A12: OO2EWP12200 | B12: B0GWQMTQY9 | C12: 1122EWP122BUS | D12: FBA | E12: 维稳 | F12: 老品 | G12: 瘦狗 | H12: 潜力 | I12: 瘦狗 | J12: 59.99 | K12: 47.22 | L12: 48.64 | M12: 43.77 | N12: 53.5 | O12: 0 | P12: 0 | Q12: 1 | R12: 0 | S12: 4 | T12: 6 | U12: 3 | V12: 0 | W12: 0.20762671 | X12: 0.20674177 | Y12: 0 | Z12: 0.0265322 | AA12: 0.058830725 | AB12: 0.12765957 | AC12: 0.05865822 | AD12: =VLOOKUP(B:B,库存明细报表10.16!L:P,5,0) -> 4 | AE12: =VLOOKUP(B:B,库存明细报表10.16!L:Q,6,0) -> 2 | AF12: =VLOOKUP(B:B,库存明细报表10.16!L:T,9,0) -> 2 | AG12: =VLOOKUP(A:A,进销存报表10.16!A:J,10,0) -> 4 | AH12: =VLOOKUP(A:A,进销存报表10.16!A:K,11,0) -> 26 | AI12: 112.19 | AJ12: 100.12 | AK12: 0 | AL12: 3.6666667 | AM12: =AK12/AI12 -> 0 | AN12: =AL12/AJ12 -> 0.036622719
A13: OO2EWP05600 | B13: B0GWZHYY3T | C13: 5706EWP0564US | D13: FBA | E13: 风险 | F13: 老品 | G13: 瘦狗 | H13: 瘦狗 | I13: 瘦狗 | J13: 35.99 | K13: 31.15 | L13: 38.89 | M13: 35 | N13: 42.78 | O13: 0 | P13: 0 | Q13: 0 | R13: 0 | S13: 0 | T13: 1 | U13: 3 | V13: 0 | W13: 0.017581344 | X13: 0.10736848 | Y13: 0 | Z13: 0.084637086 | AA13: 0.083842075 | AB13: 0.034482759 | AC13: 0.14252045 | AD13: =VLOOKUP(B:B,库存明细报表10.16!L:P,5,0) -> 28 | AE13: =VLOOKUP(B:B,库存明细报表10.16!L:Q,6,0) -> 28 | AF13: =VLOOKUP(B:B,库存明细报表10.16!L:T,9,0) -> 0 | AG13: =VLOOKUP(A:A,进销存报表10.16!A:J,10,0) -> 1 | AH13: =VLOOKUP(A:A,进销存报表10.16!A:K,11,0) -> 7 | AI13: 85.95 | AJ13: 56.52 | AK13: 0 | AL13: 0.33333333 | AM13: =AK13/AI13 -> 0 | AN13: =AL13/AJ13 -> 0.0058976174
A14: OO2EWP12700 | B14: B0GWQXP1D2 | C14: 1432EWP127JUS | D14: FBA | E14: 维稳 | F14: 老品 | G14: 瘦狗 | H14: 瘦狗 | I14: 瘦狗 | J14: 45.99 | K14: 39.85 | L14: 43.92 | M14: 39.53 | N14: 48.32 | O14: 0 | P14: 0 | Q14: 0 | R14: 1 | S14: 1 | T14: 13 | U14: 1 | V14: 0 | W14: 0.0689396 | X14: 0.056724794 | Y14: 0.23076923 | Z14: 0.017662703 | AA14: 0.025364691 | AB14: 0.15853659 | AC14: 0.207875 | AD14: =VLOOKUP(B:B,库存明细报表10.16!L:P,5,0) -> 1 | AE14: =VLOOKUP(B:B,库存明细报表10.16!L:Q,6,0) -> 0 | AF14: =VLOOKUP(B:B,库存明细报表10.16!L:T,9,0) -> 0 | AG14: =VLOOKUP(A:A,进销存报表10.16!A:J,10,0) -> 16 | AH14: =VLOOKUP(A:A,进销存报表10.16!A:K,11,0) -> 14 | AI14: 166.85 | AJ14: 144.26 | AK14: 0 | AL14: 5 | AM14: =AK14/AI14 -> 0 | AN14: =AL14/AJ14 -> 0.034659642
A15: OO2EWP10300 | B15: B0GX52JVGN | C15: 4061EWP103QUS | D15: FBA | E15: 风险 | F15: 老品 | G15: 瘦狗 | H15: 明星 | I15: 明星 | J15: 26.99 | K15: 19.3 | L15: 22.23 | M15: 20.01 | N15: 24.46 | O15: 0 | P15: 0 | Q15: 0 | R15: 0 | S15: 0 | T15: 0 | U15: 0 | V15: 0 | W15: 0.3029256 | X15: 0.38975378 | Y15: 0 | Z15: 0.14338644 | AA15: 0.083851225 | AB15: 0 | AC15: 0 | AD15: =VLOOKUP(B:B,库存明细报表10.16!L:P,5,0) -> 10 | AE15: =VLOOKUP(B:B,库存明细报表10.16!L:Q,6,0) -> 10 | AF15: =VLOOKUP(B:B,库存明细报表10.16!L:T,9,0) -> 3 | AG15: =VLOOKUP(A:A,进销存报表10.16!A:J,10,0) -> 15 | AH15: =VLOOKUP(A:A,进销存报表10.16!A:K,11,0) -> 0 | AI15: 3.41 | AJ15: 2.74 | AK15: 0 | AL15: 0.33333333 | AM15: =AK15/AI15 -> 0 | AN15: =AL15/AJ15 -> 0.1216545
A16: OO2EWP05100 | B16: B0GWZR3D55 | C16: 8759EWP051TUS | D16: FBA | E16: 维稳 | F16: 老品 | G16: 瘦狗 | H16: 潜力 | I16: 瘦狗 | J16: 37.99 | K16: 31.41 | L16: 33.23 | M16: 29.91 | N16: 36.55 | O16: 0 | P16: 0 | Q16: 1 | R16: 2 | S16: 3 | T16: 4 | U16: 1 | V16: 0 | W16: 0.22408861 | X16: 0.22237719 | Y16: 0.25016462 | Z16: 0.044712235 | AA16: 0.063811002 | AB16: 0.11764706 | AC16: 0.076722407 | AD16: =VLOOKUP(B:B,库存明细报表10.16!L:P,5,0) -> 5 | AE16: =VLOOKUP(B:B,库存明细报表10.16!L:Q,6,0) -> 1 | AF16: =VLOOKUP(B:B,库存明细报表10.16!L:T,9,0) -> 0 | AG16: =VLOOKUP(A:A,进销存报表10.16!A:J,10,0) -> 5 | AH16: =VLOOKUP(A:A,进销存报表10.16!A:K,11,0) -> 0 | AI16: 53.38 | AJ16: 39.8 | AK16: 0 | AL16: 3.6666667 | AM16: =AK16/AI16 -> 0 | AN16: =AL16/AJ16 -> 0.092127303
A17: OO2EWP04500 | B17: B0GYRP5X4D | C17: 4601EWP045HUS | D17: FBA | E17: 风险 | F17: 老品 | G17: 瘦狗 | H17: 潜力 | I17: 潜力 | J17: 31.99 | K17: 23.56 | L17: 31.41 | M17: 28.27 | N17: 34.56 | O17: 0 | P17: 0 | Q17: 0 | R17: 0 | S17: 2 | T17: 2 | U17: 1 | V17: 0 | W17: 0.21463789 | X17: 0.17609004 | Y17: 0 | Z17: 0.051161821 | AA17: 0.083846551 | AB17: 0.058823529 | AC17: 0.16632504 | AD17: =VLOOKUP(B:B,库存明细报表10.16!L:P,5,0) -> 13 | AE17: =VLOOKUP(B:B,库存明细报表10.16!L:Q,6,0) -> 13 | AF17: =VLOOKUP(B:B,库存明细报表10.16!L:T,9,0) -> 0 | AG17: =VLOOKUP(A:A,进销存报表10.16!A:J,10,0) -> 46 | AH17: =VLOOKUP(A:A,进销存报表10.16!A:K,11,0) -> 0 | AI17: 78.55 | AJ17: 44.71 | AK17: 0 | AL17: 1.6666667 | AM17: =AK17/AI17 -> 0 | AN17: =AL17/AJ17 -> 0.037277268
A18: OO2EWP07700 | B18: B0GYS61TK1 | C18: 2891EWP077AUS | D18: FBA | E18: 维稳 | F18: 老品 | G18: 瘦狗 | H18: 瘦狗 | I18: 潜力 | J18: 25.99 | K18: 20.78 | L18: 24.67 | M18: 22.2 | N18: 27.13 | O18: 0 | P18: 0 | Q18: 0 | R18: 0 | S18: 0 | T18: 2 | U18: 1 | V18: 0 | W18: 0.12263473 | X18: 0.1645322 | Y18: 0 | Z18: 0.046432616 | AA18: 0.083851748 | AB18: 0.14285714 | AC18: 0 | AD18: =VLOOKUP(B:B,库存明细报表10.16!L:P,5,0) -> 12 | AE18: =VLOOKUP(B:B,库存明细报表10.16!L:Q,6,0) -> 12 | AF18: =VLOOKUP(B:B,库存明细报表10.16!L:T,9,0) -> 0 | AG18: =VLOOKUP(A:A,进销存报表10.16!A:J,10,0) -> 10 | AH18: =VLOOKUP(A:A,进销存报表10.16!A:K,11,0) -> 51 | AI18: 273.16 | AJ18: 229.46 | AK18: 0 | AL18: 0.66666667 | AM18: =AK18/AI18 -> 0 | AN18: =AL18/AJ18 -> 0.002905372
A19: OO2EWP07800 | B19: B0GYRNV2Q2 | C19: 8531EWP078GUS | D19: FBA | E19: 维稳 | F19: 老品 | G19: 瘦狗 | H19: 潜力 | I19: 瘦狗 | J19: 39.99 | K19: 32.08 | L19: 47.1 | M19: 42.39 | N19: 51.81 | O19: 0 | P19: 0 | Q19: 0 | R19: 1 | S19: 0 | T19: 4 | U19: 2 | V19: 0 | W19: 0.22955863 | X19: 0.29320124 | Y19: 0 | Z19: 0.024765004 | AA19: 0.042385051 | AB19: 0.18181818 | AC19: 0.19958913 | AD19: =VLOOKUP(B:B,库存明细报表10.16!L:P,5,0) -> 5 | AE19: =VLOOKUP(B:B,库存明细报表10.16!L:Q,6,0) -> 5 | AF19: =VLOOKUP(B:B,库存明细报表10.16!L:T,9,0) -> 0 | AG19: =VLOOKUP(A:A,进销存报表10.16!A:J,10,0) -> 0 | AH19: =VLOOKUP(A:A,进销存报表10.16!A:K,11,0) -> 50 | AI19: 146.93 | AJ19: 65.38 | AK19: 0 | AL19: 1.6666667 | AM19: =AK19/AI19 -> 0 | AN19: =AL19/AJ19 -> 0.025491996
A20: OO2EWP07300 | B20: B0FZGM1YGD | C20: 7835EWP073GUS | D20: FBA | E20: 维稳 | F20: 老品 | G20: 瘦狗 | H20: 金牛 | I20: 瘦狗 | J20: 85.99 | K20: 63.59 | L20: 71.24 | M20: 64.11 | N20: 78.36 | O20: 0 | P20: 0 | Q20: 0 | R20: 5 | S20: 3 | T20: 1 | U20: 0 | V20: 0 | W20: 0.16375031 | X20: 0 | Y20: 0 | Z20: #DIV/0! | AA20: #DIV/0! | AB20: 0.055555556 | AC20: 0 | AD20: =VLOOKUP(B:B,库存明细报表10.16!L:P,5,0) -> 6 | AE20: =VLOOKUP(B:B,库存明细报表10.16!L:Q,6,0) -> 6 | AF20: =VLOOKUP(B:B,库存明细报表10.16!L:T,9,0) -> 0 | AG20: =VLOOKUP(A:A,进销存报表10.16!A:J,10,0) -> 4 | AH20: =VLOOKUP(A:A,进销存报表10.16!A:K,11,0) -> 8 | AI20: 33.15 | AJ20: 25.37 | AK20: 0 | AL20: 2.6666667 | AM20: =AK20/AI20 -> 0 | AN20: =AL20/AJ20 -> 0.10511102
A21: OO2EWP07600 | B21: B0GWZHV9LG | C21: 8571EWP076LUS | D21: FBA | E21: 风险 | F21: 老品 | G21: 瘦狗 | H21: 潜力 | I21: 潜力 | J21: 33.99 | K21: 25.01 | L21: 31.36 | M21: 28.22 | N21: 34.49 | O21: 0 | P21: 1 | Q21: 1 | R21: 4 | S21: 6 | T21: 6 | U21: 6 | V21: -0.22624968 | W21: 0.22097021 | X21: 0.20495294 | Y21: 0.12658274 | Z21: 0.019137544 | AA21: 0.076175209 | AB21: 0.12244898 | AC21: 0.24944807 | AD21: =VLOOKUP(B:B,库存明细报表10.16!L:P,5,0) -> 26 | AE21: =VLOOKUP(B:B,库存明细报表10.16!L:Q,6,0) -> 26 | AF21: =VLOOKUP(B:B,库存明细报表10.16!L:T,9,0) -> 0 | AG21: =VLOOKUP(A:A,进销存报表10.16!A:J,10,0) -> 11 | AH21: =VLOOKUP(A:A,进销存报表10.16!A:K,11,0) -> 0 | AI21: 327.34 | AJ21: 194.02 | AK21: 0.33 | AL21: 6 | AM21: =AK21/AI21 -> 0.0010081261 | AN21: =AL21/AJ21 -> 0.030924647
A22: OO2EWP03900 | B22: B0GWQRKH9G | C22: 9693EWP0397US | D22: FBA | E22: 维稳 | F22: 老品 | G22: 瘦狗 | H22: 瘦狗 | I22: 瘦狗 | J22: 27.99 | K22: 24.31 | L22: 23.74 | M22: 21.37 | N22: 26.11 | O22: 0 | P22: 0 | Q22: 2 | R22: 6 | S22: 3 | T22: 0 | U22: 2 | V22: 0.081142765 | W22: 0.096450859 | X22: 0 | Y22: 0 | Z22: #DIV/0! | AA22: #DIV/0! | AB22: 0 | AC22: 0 | AD22: =VLOOKUP(B:B,库存明细报表10.16!L:P,5,0) -> 7 | AE22: =VLOOKUP(B:B,库存明细报表10.16!L:Q,6,0) -> 7 | AF22: =VLOOKUP(B:B,库存明细报表10.16!L:T,9,0) -> 0 | AG22: =VLOOKUP(A:A,进销存报表10.16!A:J,10,0) -> 29 | AH22: =VLOOKUP(A:A,进销存报表10.16!A:K,11,0) -> 27 | AI22: 347.13 | AJ22: 242.79 | AK22: 0.67 | AL22: 3.3333333 | AM22: =AK22/AI22 -> 0.0019301126 | AN22: =AL22/AJ22 -> 0.013729286
A23: OO2EWP02600 | B23: B0GWZ8Q8L2 | C23: 4673EWP026JUS | D23: FBA | E23: 维稳 | F23: 老品 | G23: 瘦狗 | H23: 潜力 | I23: 瘦狗 | J23: 22.99 | K23: 16.52 | L23: 18.84 | M23: 16.96 | N23: 20.73 | O23: 0 | P23: 0 | Q23: 2 | R23: 9 | S23: 5 | T23: 7 | U23: 4 | V23: 0.13278429 | W23: 0.20965005 | X23: 0.19286386 | Y23: 0 | Z23: 0.075979472 | AA23: 0.072353274 | AB23: 0.11111111 | AC23: 0 | AD23: =VLOOKUP(B:B,库存明细报表10.16!L:P,5,0) -> 27 | AE23: =VLOOKUP(B:B,库存明细报表10.16!L:Q,6,0) -> 26 | AF23: =VLOOKUP(B:B,库存明细报表10.16!L:T,9,0) -> 0 | AG23: =VLOOKUP(A:A,进销存报表10.16!A:J,10,0) -> 3 | AH23: =VLOOKUP(A:A,进销存报表10.16!A:K,11,0) -> 28 | AI23: 318 | AJ23: 232.58 | AK23: 0.67 | AL23: 7 | AM23: =AK23/AI23 -> 0.0021069182 | AN23: =AL23/AJ23 -> 0.030097171
A24: OO2EWP03100 | B24: B0GWZNCP7S | C24: 6070EWP0315US | D24: FBA | E24: 维稳 | F24: 老品 | G24: 潜力 | H24: 瘦狗 | I24: 潜力 | J24: 38.99 | K24: 32.05 | L24: 37.99 | M24: 34.19 | N24: 41.79 | O24: 0 | P24: 0 | Q24: 1 | R24: 7 | S24: 2 | T24: 0 | U24: 1 | V24: 0.23143232 | W24: 0.16010831 | X24: 0 | Y24: 0 | Z24: #DIV/0! | AA24: #DIV/0! | AB24: 0 | AC24: 0 | AD24: =VLOOKUP(B:B,库存明细报表10.16!L:P,5,0) -> 9 | AE24: =VLOOKUP(B:B,库存明细报表10.16!L:Q,6,0) -> 0 | AF24: =VLOOKUP(B:B,库存明细报表10.16!L:T,9,0) -> 0 | AG24: =VLOOKUP(A:A,进销存报表10.16!A:J,10,0) -> 8 | AH24: =VLOOKUP(A:A,进销存报表10.16!A:K,11,0) -> 26 | AI24: 155.92 | AJ24: 123.99 | AK24: 0.33 | AL24: 3.3333333 | AM24: =AK24/AI24 -> 0.00211647 | AN24: =AL24/AJ24 -> 0.026883888
A25: OO2EWP08900 | B25: B0GWQNW9QC | C25: 3328EWP089HUS | D25: FBA | E25: 维稳 | F25: 老品 | G25: 潜力 | H25: 瘦狗 | I25: 潜力 | J25: 24.99 | K25: 19.05 | L25: 23.99 | M25: 21.59 | N25: 26.39 | O25: 0 | P25: 0 | Q25: 1 | R25: 1 | S25: 1 | T25: 2 | U25: 1 | V25: 0.30960216 | W25: 0.088390617 | X25: 0.062125706 | Y25: 0 | Z25: 0.084433774 | AA25: 0.083853506 | AB25: 0.095238095 | AC25: 0.036980607 | AD25: =VLOOKUP(B:B,库存明细报表10.16!L:P,5,0) -> 11 | AE25: =VLOOKUP(B:B,库存明细报表10.16!L:Q,6,0) -> 10 | AF25: =VLOOKUP(B:B,库存明细报表10.16!L:T,9,0) -> 2 | AG25: =VLOOKUP(A:A,进销存报表10.16!A:J,10,0) -> 21 | AH25: =VLOOKUP(A:A,进销存报表10.16!A:K,11,0) -> 1 | AI25: 153.58 | AJ25: 115.22 | AK25: 0.33 | AL25: 1.3333333 | AM25: =AK25/AI25 -> 0.0021487173 | AN25: =AL25/AJ25 -> 0.011572065
A26: ZC2CLK04900 | B26: B0GWQVBRBB | C26: 6936CLK0491US | D26: FBA | E26: 维稳 | F26: 老品 | G26: 潜力 | H26: 潜力 | I26: 潜力 | J26: 38.99 | K26: 22.2 | L26: 38.95 | M26: 35.05 | N26: 42.84 | O26: 0 | P26: 0 | Q26: 1 | R26: 1 | S26: 1 | T26: 4 | U26: 0 | V26: 0.38353171 | W26: 0.30951289 | X26: 0.31383031 | Y26: 0 | Z26: 0.065070493 | AA26: 0.083824903 | AB26: 0.11764706 | AC26: 0.10696505 | AD26: =VLOOKUP(B:B,库存明细报表10.16!L:P,5,0) -> 15 | AE26: =VLOOKUP(B:B,库存明细报表10.16!L:Q,6,0) -> 14 | AF26: =VLOOKUP(B:B,库存明细报表10.16!L:T,9,0) -> 0 | AG26: =VLOOKUP(A:A,进销存报表10.16!A:J,10,0) -> 19 | AH26: =VLOOKUP(A:A,进销存报表10.16!A:K,11,0) -> 12 | AI26: 131.47 | AJ26: 90.4 | AK26: 0.33 | AL26: 1.6666667 | AM26: =AK26/AI26 -> 0.0025100783 | AN26: =AL26/AJ26 -> 0.018436578
A27: OO2EWP08000 | B27: B0G3LJ3LGP | C27: 3150EWP080GUS | D27: FBA | E27: 维稳 | F27: 老品 | G27: 瘦狗 | H27: 瘦狗 | I27: 瘦狗 | J27: 37.99 | K27: 29.95 | L27: 35.19 | M27: 31.67 | N27: 38.71 | O27: 0 | P27: 1 | Q27: 4 | R27: 6 | S27: 5 | T27: 4 | U27: 1 | V27: 0.18804262 | W27: 0.176674 | X27: 0.47464876 | Y27: 0 | Z27: 0.047349961 | AA27: 0.083842339 | AB27: 0.070175439 | AC27: 0.19951349 | AD27: =VLOOKUP(B:B,库存明细报表10.16!L:P,5,0) -> 29 | AE27: =VLOOKUP(B:B,库存明细报表10.16!L:Q,6,0) -> 29 | AF27: =VLOOKUP(B:B,库存明细报表10.16!L:T,9,0) -> 0 | AG27: =VLOOKUP(A:A,进销存报表10.16!A:J,10,0) -> 0 | AH27: =VLOOKUP(A:A,进销存报表10.16!A:K,11,0) -> 83 | AI27: 634.05 | AJ27: 472.58 | AK27: 1.67 | AL27: 5 | AM27: =AK27/AI27 -> 0.0026338617 | AN27: =AL27/AJ27 -> 0.010580219
A28: OO2EWP08600 | B28: B0GWQTZDGZ | C28: 4633EWP0866US | D28: FBA | E28: 维稳 | F28: 老品 | G28: 潜力 | H28: 瘦狗 | I28: 瘦狗 | J28: 53.99 | K28: 45.43 | L28: 46.54 | M28: 41.88 | N28: 51.19 | O28: 0 | P28: 1 | Q28: 0 | R28: 6 | S28: 6 | T28: 8 | U28: 6 | V28: 0.27483858 | W28: 0.19843972 | X28: 0.18035891 | Y28: 0.25225266 | Z28: 0.023269959 | AA28: 0.051037269 | AB28: 0.15384615 | AC28: 0.15349244 | AD28: =VLOOKUP(B:B,库存明细报表10.16!L:P,5,0) -> 17 | AE28: =VLOOKUP(B:B,库存明细报表10.16!L:Q,6,0) -> 6 | AF28: =VLOOKUP(B:B,库存明细报表10.16!L:T,9,0) -> 2 | AG28: =VLOOKUP(A:A,进销存报表10.16!A:J,10,0) -> 21 | AH28: =VLOOKUP(A:A,进销存报表10.16!A:K,11,0) -> 10 | AI28: 107.6 | AJ28: 85.99 | AK28: 0.33 | AL28: 6.6666667 | AM28: =AK28/AI28 -> 0.0030669145 | AN28: =AL28/AJ28 -> 0.077528395
A29: OO2EWP07900 | B29: B0DSW8XVPB | C29: 7900EWP0795US | D29: FBA | E29: 维稳 | F29: 老品 | G29: 瘦狗 | H29: 潜力 | I29: 潜力 | J29: 59.99 | K29: 40.31 | L29: 47.49 | M29: 42.74 | N29: 52.24 | O29: 0 | P29: 0 | Q29: 3 | R29: 2 | S29: 5 | T29: 9 | U29: 6 | V29: 0.19749434 | W29: 0.28267932 | X29: 0.29774235 | Y29: 0 | Z29: 0.001364657 | AA29: 0.041133697 | AB29: 0.25 | AC29: 0 | AD29: =VLOOKUP(B:B,库存明细报表10.16!L:P,5,0) -> 32 | AE29: =VLOOKUP(B:B,库存明细报表10.16!L:Q,6,0) -> 31 | AF29: =VLOOKUP(B:B,库存明细报表10.16!L:T,9,0) -> 0 | AG29: =VLOOKUP(A:A,进销存报表10.16!A:J,10,0) -> 42 | AH29: =VLOOKUP(A:A,进销存报表10.16!A:K,11,0) -> 2 | AI29: 396.21 | AJ29: 333.63 | AK29: 1.33 | AL29: 5.3333333 | AM29: =AK29/AI29 -> 0.0033568057 | AN29: =AL29/AJ29 -> 0.015985773
A30: OO2EWP02100 | B30: B0GWQY9RW4 | C30: 9087EWP021RUS | D30: FBA | E30: 风险 | F30: 老品 | G30: 潜力 | H30: 瘦狗 | I30: 潜力 | J30: 25.99 | K30: 22.59 | L30: 18.58 | M30: 16.72 | N30: 20.44 | O30: 0 | P30: 0 | Q30: 2 | R30: 1 | S30: 10 | T30: 2 | U30: 0 | V30: 0.28375521 | W30: 0.049795808 | X30: 0.24754104 | Y30: 0 | Z30: 0.04546355 | AA30: 0.024383773 | AB30: 0.05 | AC30: 0.1246411 | AD30: =VLOOKUP(B:B,库存明细报表10.16!L:P,5,0) -> 5 | AE30: =VLOOKUP(B:B,库存明细报表10.16!L:Q,6,0) -> 1 | AF30: =VLOOKUP(B:B,库存明细报表10.16!L:T,9,0) -> 0 | AG30: =VLOOKUP(A:A,进销存报表10.16!A:J,10,0) -> 18 | AH30: =VLOOKUP(A:A,进销存报表10.16!A:K,11,0) -> 8 | AI30: 189.31 | AJ30: 164.27 | AK30: 0.67 | AL30: 4.6666667 | AM30: =AK30/AI30 -> 0.0035391686 | AN30: =AL30/AJ30 -> 0.028408514
A31: OO2EWP10700 | B31: B0GWZHZJXQ | C31: 4417EWP107SUS | D31: FBA | E31: 维稳 | F31: 老品 | G31: 瘦狗 | H31: 瘦狗 | I31: 潜力 | J31: 27.99 | K31: 19.85 | L31: 19.27 | M31: 17.34 | N31: 21.2 | O31: 0 | P31: 0 | Q31: 1 | R31: 4 | S31: 4 | T31: 9 | U31: 5 | V31: 0.01795781 | W31: 0.19576777 | X31: 0.26137279 | Y31: 0 | Z31: 0.053352388 | AA31: 0.074958072 | AB31: 0.13846154 | AC31: 0.16629319 | AD31: =VLOOKUP(B:B,库存明细报表10.16!L:P,5,0) -> 8 | AE31: =VLOOKUP(B:B,库存明细报表10.16!L:Q,6,0) -> 8 | AF31: =VLOOKUP(B:B,库存明细报表10.16!L:T,9,0) -> 0 | AG31: =VLOOKUP(A:A,进销存报表10.16!A:J,10,0) -> 5 | AH31: =VLOOKUP(A:A,进销存报表10.16!A:K,11,0) -> 16 | AI31: 91.06 | AJ31: 61.56 | AK31: 0.33 | AL31: 6 | AM31: =AK31/AI31 -> 0.0036239842 | AN31: =AL31/AJ31 -> 0.097465887
A32: OO2EWP05000 | B32: B0GWZKWRT4 | C32: 6571EWP050XUS | D32: FBA | E32: 维稳 | F32: 老品 | G32: 潜力 | H32: 瘦狗 | I32: 潜力 | J32: 21.99 | K32: 20.85 | L32: 17.57 | M32: 15.81 | N32: 19.33 | O32: 0 | P32: 0 | Q32: 1 | R32: 0 | S32: 5 | T32: 8 | U32: 9 | V32: 0.34725141 | W32: 0.088299283 | X32: 0.004619175 | Y32: 0.12622019 | Z32: 0.071438978 | AA32: 0.073755017 | AB32: 0.1038961 | AC32: 0.083134443 | AD32: =VLOOKUP(B:B,库存明细报表10.16!L:P,5,0) -> 4 | AE32: =VLOOKUP(B:B,库存明细报表10.16!L:Q,6,0) -> 4 | AF32: =VLOOKUP(B:B,库存明细报表10.16!L:T,9,0) -> 0 | AG32: =VLOOKUP(A:A,进销存报表10.16!A:J,10,0) -> 0 | AH32: =VLOOKUP(A:A,进销存报表10.16!A:K,11,0) -> 0 | AI32: 89.74 | AJ32: 62.2 | AK32: 0.33 | AL32: 4.6666667 | AM32: =AK32/AI32 -> 0.0036772899 | AN32: =AL32/AJ32 -> 0.075026795
A33: OO2EWP03000 | B33: B0GWZPSHM2 | C33: 8131EWP0300US | D33: FBA | E33: 风险 | F33: 老品 | G33: 瘦狗 | H33: 瘦狗 | I33: 瘦狗 | J33: 69.99 | K33: 66.66 | L33: 60.79 | M33: 54.71 | N33: 66.87 | O33: 0 | P33: 5 | Q33: 5 | R33: 1 | S33: 1 | T33: 2 | U33: 0 | V33: -0.050532872 | W33: 0.090402945 | X33: 0.085295012 | Y33: 0 | Z33: 0.05971304 | AA33: 0.088784262 | AB33: 0.068965517 | AC33: 0.049893831 | AD33: =VLOOKUP(B:B,库存明细报表10.16!L:P,5,0) -> 19 | AE33: =VLOOKUP(B:B,库存明细报表10.16!L:Q,6,0) -> 18 | AF33: =VLOOKUP(B:B,库存明细报表10.16!L:T,9,0) -> 0 | AG33: =VLOOKUP(A:A,进销存报表10.16!A:J,10,0) -> 37 | AH33: =VLOOKUP(A:A,进销存报表10.16!A:K,11,0) -> 12 | AI33: 753.52 | AJ33: 522.41 | AK33: 3 | AL33: 1.6666667 | AM33: =AK33/AI33 -> 0.0039813144 | AN33: =AL33/AJ33 -> 0.0031903422
A34: OO2EWP10800 | B34: B0GX5DMQLL | C34: 4030EWP108VUS | D34: FBA | E34: 维稳 | F34: 老品 | G34: 瘦狗 | H34: 瘦狗 | I34: 潜力 | J34: 25.99 | K34: 18.67 | L34: 22.79 | M34: 20.51 | N34: 25.06 | O34: 0 | P34: 0 | Q34: 1 | R34: 4 | S34: 4 | T34: 3 | U34: 0 | V34: 0.18498106 | W34: 0.11711769 | X34: -0.013370955 | Y34: 0.31587263 | Z34: 0.090544482 | AA34: 0.054380623 | AB34: 0.125 | AC34: 0.24922416 | AD34: =VLOOKUP(B:B,库存明细报表10.16!L:P,5,0) -> 15 | AE34: =VLOOKUP(B:B,库存明细报表10.16!L:Q,6,0) -> 15 | AF34: =VLOOKUP(B:B,库存明细报表10.16!L:T,9,0) -> 0 | AG34: =VLOOKUP(A:A,进销存报表10.16!A:J,10,0) -> 15 | AH34: =VLOOKUP(A:A,进销存报表10.16!A:K,11,0) -> 22 | AI34: 79.27 | AJ34: 46.94 | AK34: 0.33 | AL34: 4.3333333 | AM34: =AK34/AI34 -> 0.0041629873 | AN34: =AL34/AJ34 -> 0.092316432
A35: OO2EWP11300 | B35: B0GWQXQT6R | C35: 7505EWP1139US | D35: FBA | E35: 维稳 | F35: 老品 | G35: 瘦狗 | H35: 金牛 | I35: 瘦狗 | J35: 45.99 | K35: 36.44 | L35: 34.49 | M35: 31.04 | N35: 37.94 | O35: 0 | P35: 0 | Q35: 2 | R35: 7 | S35: 14 | T35: 2 | U35: 3 | V35: 0.18125014 | W35: 0.077713561 | X35: 0.078995459 | Y35: 0.44224909 | Z35: 0.003637079 | AA35: -0.040413238 | AB35: 0.5 | AC35: 0.99820025 | AD35: =VLOOKUP(B:B,库存明细报表10.16!L:P,5,0) -> 2 | AE35: =VLOOKUP(B:B,库存明细报表10.16!L:Q,6,0) -> 2 | AF35: =VLOOKUP(B:B,库存明细报表10.16!L:T,9,0) -> 11 | AG35: =VLOOKUP(A:A,进销存报表10.16!A:J,10,0) -> 0 | AH35: =VLOOKUP(A:A,进销存报表10.16!A:K,11,0) -> 8 | AI35: 149.96 | AJ35: 82.85 | AK35: 0.67 | AL35: 9.3333333 | AM35: =AK35/AI35 -> 0.0044678581 | AN35: =AL35/AJ35 -> 0.11265339
A36: OO2EWP11900 | B36: B0GWZH2JVV | C36: 1189EWP119BUS | D36: FBA | E36: 维稳 | F36: 老品 | G36: 潜力 | H36: 金牛 | I36: 瘦狗 | J36: 66.99 | K36: 54.13 | L36: 54.78 | M36: 49.3 | N36: 60.25 | O36: 0 | P36: 0 | Q36: 1 | R36: 2 | S36: 4 | T36: 6 | U36: 1 | V36: 0.2347088 | W36: 0.17234422 | X36: 0.092458435 | Y36: 0 | Z36: 0.007135393 | AA36: 0.093834993 | AB36: 0.24 | AC36: 0 | AD36: =VLOOKUP(B:B,库存明细报表10.16!L:P,5,0) -> 6 | AE36: =VLOOKUP(B:B,库存明细报表10.16!L:Q,6,0) -> 5 | AF36: =VLOOKUP(B:B,库存明细报表10.16!L:T,9,0) -> 0 | AG36: =VLOOKUP(A:A,进销存报表10.16!A:J,10,0) -> 1 | AH36: =VLOOKUP(A:A,进销存报表10.16!A:K,11,0) -> 23 | AI36: 55.14 | AJ36: 39.25 | AK36: 0.33 | AL36: 4 | AM36: =AK36/AI36 -> 0.0059847661 | AN36: =AL36/AJ36 -> 0.10191083
... A40: OO2EWP12000 | B40: B0GWQSPYL6 | C40: 8948EWP1204US | D40: FBA | E40: 维稳 | F40: 老品 | G40: 潜力 | H40: 瘦狗 | I40: 明星 | J40: 29.99 | K40: 22.42 | L40: 28.36 | M40: 25.52 | N40: 31.19 | O40: 0 | P40: 1 | Q40: 0 | R40: 3 | S40: 2 | T40: 1 | U40: 1 | V40: 0.25492005 | W40: 0.12104269 | X40: -0.059893165 | Y40: 0 | Z40: 0.2354118 | AA40: 0.083848185 | AB40: 0.034482759 | AC40: 0 | AD40: =VLOOKUP(B:B,库存明细报表10.16!L:P,5,0) -> 21 | AE40: =VLOOKUP(B:B,库存明细报表10.16!L:Q,6,0) -> 14 | AF40: =VLOOKUP(B:B,库存明细报表10.16!L:T,9,0) -> 17 | AG40: =VLOOKUP(A:A,进销存报表10.16!A:J,10,0) -> 15 | AH40: =VLOOKUP(A:A,进销存报表10.16!A:K,11,0) -> 13 | AI40: 42.26 | AJ40: 27.83 | AK40: 0.33 | AL40: 2 | AM40: =AK40/AI40 -> 0.0078088027 | AN40: =AL40/AJ40 -> 0.071864894
A41: OO2EWP09700 | B41: B0FLK4C864 | C41: 9920EWP097BUS | D41: FBA | E41: 维稳 | F41: 老品 | G41: 瘦狗 | H41: 瘦狗 | I41: 潜力 | J41: 25.99 | K41: 16.51 | L41: 21.96 | M41: 19.76 | N41: 24.16 | O41: 2 | P41: 3 | Q41: 2 | R41: 2 | S41: 2 | T41: 1 | U41: 2 | V41: 0.19787915 | W41: 0.18670803 | X41: 0 | Y41: 0 | Z41: #DIV/0! | AA41: #DIV/0! | AB41: 0.05 | AC41: 0 | AD41: =VLOOKUP(B:B,库存明细报表10.16!L:P,5,0) -> 0 | AE41: =VLOOKUP(B:B,库存明细报表10.16!L:Q,6,0) -> 0 | AF41: =VLOOKUP(B:B,库存明细报表10.16!L:T,9,0) -> 15 | AG41: =VLOOKUP(A:A,进销存报表10.16!A:J,10,0) -> 34 | AH41: =VLOOKUP(A:A,进销存报表10.16!A:K,11,0) -> 0 | AI41: 238.06 | AJ41: 209.54 | AK41: 2 | AL41: 1.6666667 | AM41: =AK41/AI41 -> 0.0084012434 | AN41: =AL41/AJ41 -> 0.0079539308
A42: OO2EWP05900 | B42: B0GWQLN3LT | C42: 2193EWP059HUS | D42: FBA | E42: 维稳 | F42: 老品 | G42: 潜力 | H42: 明星 | I42: 潜力 | J42: 42.99 | K42: 31.01 | L42: 34.28 | M42: 30.86 | N42: 37.71 | O42: 0 | P42: 1 | Q42: 1 | R42: 7 | S42: 15 | T42: 6 | U42: 1 | V42: 0.33141245 | W42: 0.23030727 | X42: 0.28549064 | Y42: 0.1639088 | Z42: 0.018758579 | AA42: 0.043168824 | AB42: 0.11111111 | AC42: 0.14260555 | AD42: =VLOOKUP(B:B,库存明细报表10.16!L:P,5,0) -> 0 | AE42: =VLOOKUP(B:B,库存明细报表10.16!L:Q,6,0) -> 0 | AF42: =VLOOKUP(B:B,库存明细报表10.16!L:T,9,0) -> 40 | AG42: =VLOOKUP(A:A,进销存报表10.16!A:J,10,0) -> 1 | AH42: =VLOOKUP(A:A,进销存报表10.16!A:K,11,0) -> 36 | AI42: 72.93 | AJ42: 60.29 | AK42: 0.67 | AL42: 9.6666667 | AM42: =AK42/AI42 -> 0.0091868915 | AN42: =AL42/AJ42 -> 0.16033615
A43: OO2EWP06600 | B43: B0GWQY1VKB | C43: 8525EWP0665US | D43: FBA | E43: 维稳 | F43: 老品 | G43: 潜力 | H43: 潜力 | I43: 瘦狗 | J43: 26.99 | K43: 21.08 | L43: 24.54 | M43: 22.08 | N43: 26.99 | O43: 0 | P43: 4 | Q43: 0 | R43: 3 | S43: 1 | T43: 9 | U43: 2 | V43: 0.20781505 | W43: 0.21657343 | X43: 0.23684707 | Y43: 0 | Z43: 0.028860527 | AA43: 0.070511208 | AB43: 0.20930233 | AC43: 0.23026062 | AD43: =VLOOKUP(B:B,库存明细报表10.16!L:P,5,0) -> 11 | AE43: =VLOOKUP(B:B,库存明细报表10.16!L:Q,6,0) -> 11 | AF43: =VLOOKUP(B:B,库存明细报表10.16!L:T,9,0) -> 0 | AG43: =VLOOKUP(A:A,进销存报表10.16!A:J,10,0) -> 23 | AH43: =VLOOKUP(A:A,进销存报表10.16!A:K,11,0) -> 9 | AI43: 127.73 | AJ43: 97.31 | AK43: 1.33 | AL43: 4.3333333 | AM43: =AK43/AI43 -> 0.010412589 | AN43: =AL43/AJ43 -> 0.044531223
A44: OO2EWP08300 | B44: B0G3LGYZX4 | C44: 7263EWP083CUS | D44: FBA | E44: 维稳 | F44: 老品 | G44: 瘦狗 | H44: 明星 | I44: 瘦狗 | J44: 33.99 | K44: 26.03 | L44: 30.39 | M44: 27.35 | N44: 33.43 | O44: 1 | P44: 0 | Q44: 2 | R44: 12 | S44: 18 | T44: 7 | U44: 1 | V44: -0.37138431 | W44: 0.21188197 | X44: 0.21552026 | Y44: 0 | Z44: 0.038330601 | AA44: 0.072413145 | AB44: 0.095890411 | AC44: 0.15751567 | AD44: =VLOOKUP(B:B,库存明细报表10.16!L:P,5,0) -> 6 | AE44: =VLOOKUP(B:B,库存明细报表10.16!L:Q,6,0) -> 1 | AF44: =VLOOKUP(B:B,库存明细报表10.16!L:T,9,0) -> 7 | AG44: =VLOOKUP(A:A,进销存报表10.16!A:J,10,0) -> 13 | AH44: =VLOOKUP(A:A,进销存报表10.16!A:K,11,0) -> 74 | AI44: 121.51 | AJ44: 98.01 | AK44: 1.33 | AL44: 12.333333 | AM44: =AK44/AI44 -> 0.010945601 | AN44: =AL44/AJ44 -> 0.1258375
A45: OO2EWP01600 | B45: B0CKX9959W | C45: 8703EWP016ZUS | D45: FBA | E45: 维稳 | F45: 老品 | G45: 潜力 | H45: 潜力 | I45: 潜力 | J45: 25.99 | K45: 19.39 | L45: 21.84 | M45: 19.66 | N45: 24.03 | O45: 3 | P45: 4 | Q45: 3 | R45: 22 | S45: 21 | T45: 16 | U45: 5 | V45: 0.29692302 | W45: 0.2197321 | X45: 0.23201475 | Y45: 0 | Z45: 0.046243748 | AA45: 0.083852331 | AB45: 0.12121212 | AC45: 0.10231112 | AD45: =VLOOKUP(B:B,库存明细报表10.16!L:P,5,0) -> 44 | AE45: =VLOOKUP(B:B,库存明细报表10.16!L:Q,6,0) -> 17 | AF45: =VLOOKUP(B:B,库存明细报表10.16!L:T,9,0) -> 20 | AG45: =VLOOKUP(A:A,进销存报表10.16!A:J,10,0) -> 52 | AH45: =VLOOKUP(A:A,进销存报表10.16!A:K,11,0) -> 23 | AI45: 320.08 | AJ45: 239.53 | AK45: 3.67 | AL45: 19.666667 | AM45: =AK45/AI45 -> 0.011465884 | AN45: =AL45/AJ45 -> 0.082105234
A46: OO2EWP02800 | B46: B0DTSQSBS7 | C46: 3866EWP0286US | D46: FBA | E46: 风险 | F46: 老品 | G46: 瘦狗 | H46: 瘦狗 | I46: 瘦狗 | J46: 41.99 | K46: 34.22 | L46: 31.4 | M46: 28.26 | N46: 34.55 | O46: 0 | P46: 4 | Q46: 3 | R46: 6 | S46: 4 | T46: 13 | U46: 8 | V46: 0.18482293 | W46: 0.13762372 | X46: 0.10139644 | Y46: 0.21420136 | Z46: 0.01948512 | AA46: 0.06091042 | AB46: 0.13 | AC46: 0.039907514 | AD46: =VLOOKUP(B:B,库存明细报表10.16!L:P,5,0) -> 19 | AE46: =VLOOKUP(B:B,库存明细报表10.16!L:Q,6,0) -> 17 | AF46: =VLOOKUP(B:B,库存明细报表10.16!L:T,9,0) -> 8 | AG46: =VLOOKUP(A:A,进销存报表10.16!A:J,10,0) -> 25 | AH46: =VLOOKUP(A:A,进销存报表10.16!A:K,11,0) -> 15 | AI46: 203.09 | AJ46: 152.19 | AK46: 2.33 | AL46: 8 | AM46: =AK46/AI46 -> 0.011472746 | AN46: =AL46/AJ46 -> 0.052565872
A47: OO2EWP00400 | B47: B0CKX9SK3Y | C47: 8753EWP0043US | D47: FBA | E47: 维稳 | F47: 老品 | G47: 潜力 | H47: 瘦狗 | I47: 潜力 | J47: 24.99 | K47: 21.21 | L47: 20.15 | M47: 18.14 | N47: 22.17 | O47: 16 | P47: 10 | Q47: 10 | R47: 21 | S47: 8 | T47: 10 | U47: 7 | V47: 0.23523266 | W47: 0.1891784 | X47: 0.074141481 | Y47: 0.10980346 | Z47: 0.11878702 | AA47: 0.068156981 | AB47: 0.029761905 | AC47: 0.065627557 | AD47: =VLOOKUP(B:B,库存明细报表10.16!L:P,5,0) -> 47 | AE47: =VLOOKUP(B:B,库存明细报表10.16!L:Q,6,0) -> 46 | AF47: =VLOOKUP(B:B,库存明细报表10.16!L:T,9,0) -> 60 | AG47: =VLOOKUP(A:A,进销存报表10.16!A:J,10,0) -> 8 | AH47: =VLOOKUP(A:A,进销存报表10.16!A:K,11,0) -> 27 | AI47: 947.59 | AJ47: 838.05 | AK47: 11.67 | AL47: 13.333333 | AM47: =AK47/AI47 -> 0.012315453 | AN47: =AL47/AJ47 -> 0.01590995
A48: OO2EWP06700 | B48: B0GWQWCMPT | C48: 5900EWP0675US | D48: FBA | E48: 维稳 | F48: 老品 | G48: 潜力 | H48: 明星 | I48: 潜力 | J48: 26.99 | K48: 20.24 | L48: 24.61 | M48: 22.15 | N48: 27.07 | O48: 0 | P48: 1 | Q48: 3 | R48: 14 | S48: 14 | T48: 11 | U48: 2 | V48: 0.30284607 | W48: 0.20537964 | X48: 0.19110717 | Y48: 0.090909091 | Z48: 0.041799993 | AA48: 0.071119216 | AB48: 0.18644068 | AC48: 0.13008279 | AD48: =VLOOKUP(B:B,库存明细报表10.16!L:P,5,0) -> 5 | AE48: =VLOOKUP(B:B,库存明细报表10.16!L:Q,6,0) -> 3 | AF48: =VLOOKUP(B:B,库存明细报表10.16!L:T,9,0) -> 23 | AG48: =VLOOKUP(A:A,进销存报表10.16!A:J,10,0) -> 35 | AH48: =VLOOKUP(A:A,进销存报表10.16!A:K,11,0) -> 14 | AI48: 107.84 | AJ48: 82.77 | AK48: 1.33 | AL48: 13 | AM48: =AK48/AI48 -> 0.012333086 | AN48: =AL48/AJ48 -> 0.15706174
A49: OO2EWP07500 | B49: B0DSW7XBDY | C49: 8814EWP075NUS | D49: FBA | E49: 维稳 | F49: 老品 | G49: 瘦狗 | H49: 明星 | I49: 潜力 | J49: 42.99 | K49: 32.18 | L49: 36.74 | M49: 33.07 | N49: 40.41 | O49: 0 | P49: 2 | Q49: 0 | R49: 5 | S49: 2 | T49: 4 | U49: 0 | V49: 0.10140621 | W49: 0.29067468 | X49: 0.26084399 | Y49: 0 | Z49: 0.018477574 | AA49: 0.083838387 | AB49: 0.15384615 | AC49: 0 | AD49: =VLOOKUP(B:B,库存明细报表10.16!L:P,5,0) -> 25 | AE49: =VLOOKUP(B:B,库存明细报表10.16!L:Q,6,0) -> 24 | AF49: =VLOOKUP(B:B,库存明细报表10.16!L:T,9,0) -> 0 | AG49: =VLOOKUP(A:A,进销存报表10.16!A:J,10,0) -> 40 | AH49: =VLOOKUP(A:A,进销存报表10.16!A:K,11,0) -> 8 | AI49: 54.14 | AJ49: 36.31 | AK49: 0.67 | AL49: 3.6666667 | AM49: =AK49/AI49 -> 0.012375323 | AN49: =AL49/AJ49 -> 0.10098228
A50: OO2EWP08200 | B50: B0GWQRW5DS | C50: 8050EWP082GUS | D50: FBA | E50: 维稳 | F50: 老品 | G50: 潜力 | H50: 潜力 | I50: 明星 | J50: 33.99 | K50: 20.32 | L50: 33.24 | M50: 29.91 | N50: 36.56 | O50: 0 | P50: 1 | Q50: 2 | R50: 5 | S50: 5 | T50: 2 | U50: 2 | V50: 0.20414803 | W50: 0.31508666 | X50: 0.34515489 | Y50: 0 | Z50: 0 | AA50: 0 | AB50: 0.11111111 | AC50: #DIV/0! | AD50: =VLOOKUP(B:B,库存明细报表10.16!L:P,5,0) -> 0 | AE50: =VLOOKUP(B:B,库存明细报表10.16!L:Q,6,0) -> 0 | AF50: =VLOOKUP(B:B,库存明细报表10.16!L:T,9,0) -> 20 | AG50: =VLOOKUP(A:A,进销存报表10.16!A:J,10,0) -> 14 | AH50: =VLOOKUP(A:A,进销存报表10.16!A:K,11,0) -> 83 | AI50: 78.55 | AJ50: 51.24 | AK50: 1 | AL50: 3.3333333 | AM50: =AK50/AI50 -> 0.012730745 | AN50: =AL50/AJ50 -> 0.065053344
A51: OO2EWP07000 | B51: B0G3LHFPHD | C51: 7009EWP070JUS | D51: FBA | E51: 维稳 | F51: 老品 | G51: 潜力 | H51: 瘦狗 | I51: 潜力 | J51: 23.99 | K51: 18.44 | L51: 22.79 | M51: 20.51 | N51: 25.07 | O51: 0 | P51: 4 | Q51: 4 | R51: 18 | S51: 11 | T51: 2 | U51: 3 | V51: 0.21616592 | W51: 0.14171206 | X51: -0.18193169 | Y51: 0.32199459 | Z51: 0.17575055 | AA51: 0.056392115 | AB51: 0.035714286 | AC51: 0.10234494 | AD51: =VLOOKUP(B:B,库存明细报表10.16!L:P,5,0) -> 31 | AE51: =VLOOKUP(B:B,库存明细报表10.16!L:Q,6,0) -> 14 | AF51: =VLOOKUP(B:B,库存明细报表10.16!L:T,9,0) -> 0 | AG51: =VLOOKUP(A:A,进销存报表10.16!A:J,10,0) -> 5 | AH51: =VLOOKUP(A:A,进销存报表10.16!A:K,11,0) -> 13 | AI51: 201.99 | AJ51: 119.35 | AK51: 2.67 | AL51: 11 | AM51: =AK51/AI51 -> 0.013218476 | AN51: =AL51/AJ51 -> 0.092165899
A52: OO2EWP10400 | B52: B0GWQKHTNJ | C52: 4702EWP104MUS | D52: FBA | E52: 维稳 | F52: 老品 | G52: 潜力 | H52: 瘦狗 | I52: 潜力 | J52: 36.99 | K52: 26.05 | L52: 36.91 | M52: 33.22 | N52: 40.6 | O52: 0 | P52: 0 | Q52: 5 | R52: 12 | S52: 4 | T52: 8 | U52: 6 | V52: 0.27455072 | W52: 0.1003237 | X52: 0.15880766 | Y52: 0.25539724 | Z52: 0.071747265 | AA52: 0.04660364 | AB52: 0.16 | AC52: 0.080834751 | AD52: =VLOOKUP(B:B,库存明细报表10.16!L:P,5,0) -> 9 | AE52: =VLOOKUP(B:B,库存明细报表10.16!L:Q,6,0) -> 9 | AF52: =VLOOKUP(B:B,库存明细报表10.16!L:T,9,0) -> 0 | AG52: =VLOOKUP(A:A,进销存报表10.16!A:J,10,0) -> 0 | AH52: =VLOOKUP(A:A,进销存报表10.16!A:K,11,0) -> 59 | AI52: 125.64 | AJ52: 120.76 | AK52: 1.67 | AL52: 8 | AM52: =AK52/AI52 -> 0.013291945 | AN52: =AL52/AJ52 -> 0.066247102
A53: OO2EWP06000 | B53: B0GWQFSGVJ | C53: 3666EWP0603US | D53: FBA | E53: 维稳 | F53: 老品 | G53: 潜力 | H53: 明星 | I53: 潜力 | J53: 27.99 | K53: 18.98 | L53: 22.49 | M53: 20.24 | N53: 24.74 | O53: 0 | P53: 2 | Q53: 3 | R53: 3 | S53: 14 | T53: 5 | U53: 1 | V53: 0.2897914 | W53: 0.29609919 | X53: 0.33211584 | Y53: 0 | Z53: 0.03214543 | AA53: 0.07964042 | AB53: 0.047619048 | AC53: 0.099710023 | AD53: =VLOOKUP(B:B,库存明细报表10.16!L:P,5,0) -> 23 | AE53: =VLOOKUP(B:B,库存明细报表10.16!L:Q,6,0) -> 3 | AF53: =VLOOKUP(B:B,库存明细报表10.16!L:T,9,0) -> 20 | AG53: =VLOOKUP(A:A,进销存报表10.16!A:J,10,0) -> 23 | AH53: =VLOOKUP(A:A,进销存报表10.16!A:K,11,0) -> 5 | AI53: 99.86 | AJ53: 64.92 | AK53: 1.33 | AL53: 7.6666667 | AM53: =AK53/AI53 -> 0.013318646 | AN53: =AL53/AJ53 -> 0.11809406
A54: OO2EWP08700 | B54: B0GWZLNVH8 | C54: 5409EWP087HUS | D54: FBA | E54: 风险 | F54: 老品 | G54: 潜力 | H54: 金牛 | I54: 明星 | J54: 25.99 | K54: 20.13 | L54: 25.8 | M54: 23.22 | N54: 28.38 | O54: 0 | P54: 0 | Q54: 1 | R54: 0 | S54: 4 | T54: 5 | U54: 1 | V54: 0.34488991 | W54: 0.12526249 | X54: 0.080482841 | Y54: 0.18749511 | Z54: 0.031731145 | AA54: 0.068846975 | AB54: 0.22727273 | AC54: 0.22167585 | AD54: =VLOOKUP(B:B,库存明细报表10.16!L:P,5,0) -> 10 | AE54: =VLOOKUP(B:B,库存明细报表10.16!L:Q,6,0) -> 9 | AF54: =VLOOKUP(B:B,库存明细报表10.16!L:T,9,0) -> 0 | AG54: =VLOOKUP(A:A,进销存报表10.16!A:J,10,0) -> 4 | AH54: =VLOOKUP(A:A,进销存报表10.16!A:K,11,0) -> 2 | AI54: 23.45 | AJ54: 14.07 | AK54: 0.33 | AL54: 3 | AM54: =AK54/AI54 -> 0.014072495 | AN54: =AL54/AJ54 -> 0.21321962
A55: OO2EWP09500 | B55: B0FZGM76JK | C55: 7188EWP0952US | D55: VC | E55: 维稳 | F55: 老品 | G55: 瘦狗 | H55: 瘦狗 | I55: 瘦狗 | J55: 42.66 | K55: 26.34 | L55: 31.35 | M55: 28.21 | N55: 34.48 | O55: 1 | P55: 0 | Q55: 2 | R55: 0 | S55: 1 | T55: 4 | U55: 0 | V55: -0.028998766 | W55: 0.12061612 | X55: 0.12834301 | Y55: 0.2 | Z55: 0.024770352 | AA55: 0.089705417 | AB55: 0.21052632 | AC55: 0.22220129 | AD55: =VLOOKUP(B:B,库存明细报表10.16!L:P,5,0) -> #N/A | AE55: =VLOOKUP(B:B,库存明细报表10.16!L:Q,6,0) -> #N/A | AF55: =VLOOKUP(B:B,库存明细报表10.16!L:T,9,0) -> #N/A | AG55: =VLOOKUP(A:A,进销存报表10.16!A:J,10,0) -> 9 | AH55: =VLOOKUP(A:A,进销存报表10.16!A:K,11,0) -> 1 | AI55: 46.94 | AJ55: 22.94 | AK55: 0.67 | AL55: 2 | AM55: =AK55/AI55 -> 0.014273541 | AN55: =AL55/AJ55 -> 0.087183958
A56: OO2EWP01300 | B56: B0CKX85NSB | C56: 1002EWP0137US | D56: FBA | E56: 维稳 | F56: 老品 | G56: 潜力 | H56: 瘦狗 | I56: 潜力 | J56: 77.99 | K56: 54.74 | L56: 58.29 | M56: 52.46 | N56: 64.11 | O56: 6 | P56: 3 | Q56: 3 | R56: 10 | S56: 12 | T56: 0 | U56: 0 | V56: 0.21257981 | W56: 0.14881248 | X56: 0.12051237 | Y56: 2 | Z56: 0.058985492 | AA56: 0.05 | AB56: 0 | AC56: 0 | AD56: =VLOOKUP(B:B,库存明细报表10.16!L:P,5,0) -> 0 | AE56: =VLOOKUP(B:B,库存明细报表10.16!L:Q,6,0) -> 0 | AF56: =VLOOKUP(B:B,库存明细报表10.16!L:T,9,0) -> 35 | AG56: =VLOOKUP(A:A,进销存报表10.16!A:J,10,0) -> 15 | AH56: =VLOOKUP(A:A,进销存报表10.16!A:K,11,0) -> 64 | AI56: 199.78 | AJ56: 149.23 | AK56: 3 | AL56: 8.3333333 | AM56: =AK56/AI56 -> 0.015016518 | AN56: =AL56/AJ56 -> 0.055842212
A57: ZC2CLK05300 | B57: B0GWR5G1FG | C57: 9951CLK053VUS | D57: FBA | E57: 维稳 | F57: 老品 | G57: 潜力 | H57: 金牛 | I57: 潜力 | J57: 49.99 | K57: 36.03 | L57: 36.89 | M57: 33.2 | N57: 40.58 | O57: 0 | P57: 2 | Q57: 5 | R57: 4 | S57: 9 | T57: 12 | U57: 0 | V57: 0.31694419 | W57: 0.14774242 | X57: 0.12256968 | Y57: 0.24589277 | Z57: 0.00703394 | AA57: 0.056272771 | AB57: 0.087591241 | AC57: 0.39914232 | AD57: =VLOOKUP(B:B,库存明细报表10.16!L:P,5,0) -> 22 | AE57: =VLOOKUP(B:B,库存明细报表10.16!L:Q,6,0) -> 22 | AF57: =VLOOKUP(B:B,库存明细报表10.16!L:T,9,0) -> 18 | AG57: =VLOOKUP(A:A,进销存报表10.16!A:J,10,0) -> 36 | AH57: =VLOOKUP(A:A,进销存报表10.16!A:K,11,0) -> 7 | AI57: 129.61 | AJ57: 88.24 | AK57: 2 | AL57: 9.3333333 | AM57: =AK57/AI57 -> 0.015430908 | AN57: =AL57/AJ57 -> 0.10577214
A58: OO2EWP07100 | B58: B0GWR1GG26 | C58: 8850EWP0710US | D58: FBA | E58: 维稳 | F58: 老品 | G58: 瘦狗 | H58: 明星 | I58: 潜力 | J58: 25.99 | K58: 19.07 | L58: 21.13 | M58: 19.02 | N58: 23.25 | O58: 0 | P58: 7 | Q58: 3 | R58: 26 | S58: 18 | T58: 20 | U58: 3 | V58: 0.1947953 | W58: 0.20186343 | X58: 0.25912251 | Y58: 0.049330929 | Z58: 0.024618013 | AA58: 0.078833408 | AB58: 0.21505376 | AC58: 0.25863668 | AD58: =VLOOKUP(B:B,库存明细报表10.16!L:P,5,0) -> 18 | AE58: =VLOOKUP(B:B,库存明细报表10.16!L:Q,6,0) -> 2 | AF58: =VLOOKUP(B:B,库存明细报表10.16!L:T,9,0) -> 0 | AG58: =VLOOKUP(A:A,进销存报表10.16!A:J,10,0) -> 3 | AH58: =VLOOKUP(A:A,进销存报表10.16!A:K,11,0) -> 47 | AI58: 185.34 | AJ58: 154 | AK58: 3 | AL58: 23.666667 | AM58: =AK58/AI58 -> 0.016186468 | AN58: =AL58/AJ58 -> 0.15367965
A59: ZC2CLK04700 | B59: B0GWQS55JD | C59: 9206CLK0476US | D59: FBA | E59: 维稳 | F59: 老品 | G59: 瘦狗 | H59: 潜力 | I59: 潜力 | J59: 29.99 | K59: 19.99 | L59: 20.68 | M59: 18.61 | N59: 22.75 | O59: 0 | P59: 3 | Q59: 7 | R59: 5 | S59: 12 | T59: 12 | U59: 5 | V59: -0.016661704 | W59: 0.2772388 | X59: 0.35135209 | Y59: 0.051287168 | Z59: 0.021324515 | AA59: 0.078831525 | AB59: 0.18181818 | AC59: 0.42742608 | AD59: =VLOOKUP(B:B,库存明细报表10.16!L:P,5,0) -> 5 | AE59: =VLOOKUP(B:B,库存明细报表10.16!L:Q,6,0) -> 2 | AF59: =VLOOKUP(B:B,库存明细报表10.16!L:T,9,0) -> 0 | AG59: =VLOOKUP(A:A,进销存报表10.16!A:J,10,0) -> 13 | AH59: =VLOOKUP(A:A,进销存报表10.16!A:K,11,0) -> 0 | AI59: 176.82 | AJ59: 160.22 | AK59: 3.33 | AL59: 10 | AM59: =AK59/AI59 -> 0.018832711 | AN59: =AL59/AJ59 -> 0.062414181
A60: OO2EWP06400 | B60: B0GWQK6RXF | C60: 5397EWP064VUS | D60: FBA | E60: 维稳 | F60: 老品 | G60: 瘦狗 | H60: 金牛 | I60: 金牛 | J60: 26.99 | K60: 20.74 | L60: 27.89 | M60: 25.1 | N60: 30.68 | O60: 0 | P60: 0 | Q60: 3 | R60: 8 | S60: 11 | T60: 8 | U60: 1 | V60: 0.081571162 | W60: 0.1776455 | X60: 0.28068478 | Y60: 0 | Z60: 0.014614466 | AA60: 0.057174659 | AB60: 0.14285714 | AC60: 0 | AD60: =VLOOKUP(B:B,库存明细报表10.16!L:P,5,0) -> 0 | AE60: =VLOOKUP(B:B,库存明细报表10.16!L:Q,6,0) -> 0 | AF60: =VLOOKUP(B:B,库存明细报表10.16!L:T,9,0) -> 20 | AG60: =VLOOKUP(A:A,进销存报表10.16!A:J,10,0) -> 19 | AH60: =VLOOKUP(A:A,进销存报表10.16!A:K,11,0) -> 13 | AI60: 52.64 | AJ60: 47.43 | AK60: 1 | AL60: 9.3333333 | AM60: =AK60/AI60 -> 0.01899696 | AN60: =AL60/AJ60 -> 0.19678122
A61: OO2EWP08500 | B61: B0GWQX2NTR | C61: 9973EWP085JUS | D61: FBA | E61: 维稳 | F61: 老品 | G61: 潜力 | H61: 明星 | I61: 潜力 | J61: 28.99 | K61: 21.48 | L61: 28.14 | M61: 25.32 | N61: 30.95 | O61: 0 | P61: 2 | Q61: 2 | R61: 10 | S61: 8 | T61: 4 | U61: 4 | V61: 0.35815424 | W61: 0.27017427 | X61: 0.3290419 | Y61: 0 | Z61: 0.053588441 | AA61: 0.083846994 | AB61: 0.11111111 | AC61: 0 | AD61: =VLOOKUP(B:B,库存明细报表10.16!L:P,5,0) -> 8 | AE61: =VLOOKUP(B:B,库存明细报表10.16!L:Q,6,0) -> 8 | AF61: =VLOOKUP(B:B,库存明细报表10.16!L:T,9,0) -> 1 | AG61: =VLOOKUP(A:A,进销存报表10.16!A:J,10,0) -> 18 | AH61: =VLOOKUP(A:A,进销存报表10.16!A:K,11,0) -> 0 | AI61: 67.58 | AJ61: 51.7 | AK61: 1.33 | AL61: 7.3333333 | AM61: =AK61/AI61 -> 0.019680379 | AN61: =AL61/AJ61 -> 0.14184397
A62: OO2EWP02000 | B62: B0CKX8PSXX | C62: 2100EWP020ZUS | D62: FBA | E62: 维稳 | F62: 老品 | G62: 潜力 | H62: 瘦狗 | I62: 潜力 | J62: 22.99 | K62: 18.42 | L62: 22.83 | M62: 20.54 | N62: 25.11 | O62: 10 | P62: 6 | Q62: 21 | R62: 19 | S62: 7 | T62: 19 | U62: 8 | V62: 0.2545421 | W62: 0.057603836 | X62: -0.03076376 | Y62: 0.15626385 | Z62: 0.071610239 | AA62: 0.071021779 | AB62: 0.048969072 | AC62: 0.085500004 | AD62: =VLOOKUP(B:B,库存明细报表10.16!L:P,5,0) -> 26 | AE62: =VLOOKUP(B:B,库存明细报表10.16!L:Q,6,0) -> 22 | AF62: =VLOOKUP(B:B,库存明细报表10.16!L:T,9,0) -> 20 | AG62: =VLOOKUP(A:A,进销存报表10.16!A:J,10,0) -> 83 | AH62: =VLOOKUP(A:A,进销存报表10.16!A:K,11,0) -> 59 | AI62: 452.27 | AJ62: 324.08 | AK62: 9.67 | AL62: 18 | AM62: =AK62/AI62 -> 0.021381033 | AN62: =AL62/AJ62 -> 0.055541842
A63: OO2EWP08100 | B63: B0DSW8VBT5 | C63: 1753EWP081HUS | D63: FBA | E63: 维稳 | F63: 老品 | G63: 潜力 | H63: 明星 | I63: 潜力 | J63: 31.99 | K63: 23.39 | L63: 25.64 | M63: 23.08 | N63: 28.2 | O63: 0 | P63: 1 | Q63: 7 | R63: 7 | S63: 9 | T63: 17 | U63: 8 | V63: 0.32115829 | W63: 0.21564095 | X63: 0.20614158 | Y63: 0 | Z63: 0.078417363 | AA63: 0.083846562 | AB63: 0.14049587 | AC63: 0.1187757 | AD63: =VLOOKUP(B:B,库存明细报表10.16!L:P,5,0) -> 10 | AE63: =VLOOKUP(B:B,库存明细报表10.16!L:Q,6,0) -> 9 | AF63: =VLOOKUP(B:B,库存明细报表10.16!L:T,9,0) -> 7 | AG63: =VLOOKUP(A:A,进销存报表10.16!A:J,10,0) -> 53 | AH63: =VLOOKUP(A:A,进销存报表10.16!A:K,11,0) -> 28 | AI63: 110.96 | AJ63: 52.31 | AK63: 2.67 | AL63: 10.333333 | AM63: =AK63/AI63 -> 0.024062725 | AN63: =AL63/AJ63 -> 0.1975403
A64: ZC2CLK02000 | B64: B0DG2D424T | C64: 1683CLK020HUS | D64: FBA | E64: 维稳 | F64: 老品 | G64: 潜力 | H64: 潜力 | I64: 潜力 | J64: 29.99 | K64: 21.64 | L64: 20.18 | M64: 18.16 | N64: 22.2 | O64: 1 | P64: 3 | Q64: 2 | R64: 3 | S64: 0 | T64: 0 | U64: 1 | V64: 0.30272608 | W64: 0.29207241 | X64: #N/A | Y64: #N/A | Z64: #N/A | AA64: #N/A | AB64: 0 | AC64: #DIV/0! | AD64: =VLOOKUP(B:B,库存明细报表10.16!L:P,5,0) -> 0 | AE64: =VLOOKUP(B:B,库存明细报表10.16!L:Q,6,0) -> 0 | AF64: =VLOOKUP(B:B,库存明细报表10.16!L:T,9,0) -> 1 | AG64: =VLOOKUP(A:A,进销存报表10.16!A:J,10,0) -> 14 | AH64: =VLOOKUP(A:A,进销存报表10.16!A:K,11,0) -> 10 | AI64: 80.46 | AJ64: 63.56 | AK64: 2 | AL64: 1 | AM64: =AK64/AI64 -> 0.024857072 | AN64: =AL64/AJ64 -> 0.015733166
A65: OO2EWP05500 | B65: B0FZGMW6VL | C65: 2427EWP0558US | D65: FBA | E65: 维稳 | F65: 老品 | G65: 瘦狗 | H65: 金牛 | I65: 潜力 | J65: 39.99 | K65: 30.14 | L65: 32.29 | M65: 29.06 | N65: 35.52 | O65: 12 | P65: 5 | Q65: 0 | R65: 24 | S65: 27 | T65: 7 | U65: 10 | V65: 0.18102113 | W65: 0.18513897 | X65: -0.003707593 | Y65: 0.52463116 | Z65: 0.01658748 | AA65: 0.003821553 | AB65: 0.027237354 | AC65: 0.083126045 | AD65: =VLOOKUP(B:B,库存明细报表10.16!L:P,5,0) -> 6 | AE65: =VLOOKUP(B:B,库存明细报表10.16!L:Q,6,0) -> 0 | AF65: =VLOOKUP(B:B,库存明细报表10.16!L:T,9,0) -> 8 | AG65: =VLOOKUP(A:A,进销存报表10.16!A:J,10,0) -> 10 | AH65: =VLOOKUP(A:A,进销存报表10.16!A:K,11,0) -> 6 | AI65: 225.33 | AJ65: 168.61 | AK65: 5.67 | AL65: 20.666667 | AM65: =AK65/AI65 -> 0.025163094 | AN65: =AL65/AJ65 -> 0.12257082
A66: OO2EWP09000 | B66: B0G3LJNL1N | C66: 6741EWP090DUS | D66: FBA | E66: 维稳 | F66: 老品 | G66: 瘦狗 | H66: 瘦狗 | I66: 潜力 | J66: 28.99 | K66: 22.73 | L66: 24.61 | M66: 22.15 | N66: 27.07 | O66: 1 | P66: 5 | Q66: 3 | R66: 8 | S66: 2 | T66: 4 | U66: 1 | V66: 0.14711785 | W66: 0.12487112 | X66: 0.2353255 | Y66: 0 | Z66: 0.047074647 | AA66: 0.083848441 | AB66: 0.16 | AC66: 0 | AD66: =VLOOKUP(B:B,库存明细报表10.16!L:P,5,0) -> 7 | AE66: =VLOOKUP(B:B,库存明细报表10.16!L:Q,6,0) -> 5 | AF66: =VLOOKUP(B:B,库存明细报表10.16!L:T,9,0) -> 3 | AG66: =VLOOKUP(A:A,进销存报表10.16!A:J,10,0) -> 20 | AH66: =VLOOKUP(A:A,进销存报表10.16!A:K,11,0) -> 13 | AI66: 114.08 | AJ66: 66.33 | AK66: 3.33 | AL66: 5.3333333 | AM66: =AK66/AI66 -> 0.029190042 | AN66: =AL66/AJ66 -> 0.080406051
A67: OO2EWP01400 | B67: B0DG22S4LY | C67: 5683EWP014UUS | D67: FBA | E67: 维稳 | F67: 老品 | G67: 瘦狗 | H67: 潜力 | I67: 瘦狗 | J67: 55.99 | K67: 45.74 | L67: 35.84 | M67: 32.26 | N67: 39.43 | O67: 5 | P67: 2 | Q67: 10 | R67: 9 | S67: 15 | T67: 13 | U67: 0 | V67: 0.14015096 | W67: 0.21466579 | X67: 0.15892798 | Y67: 0.16366559 | Z67: 0.051210443 | AA67: 0.076561813 | AB67: 0.030444965 | AC67: 0.086807312 | AD67: =VLOOKUP(B:B,库存明细报表10.16!L:P,5,0) -> 22 | AE67: =VLOOKUP(B:B,库存明细报表10.16!L:Q,6,0) -> 9 | AF67: =VLOOKUP(B:B,库存明细报表10.16!L:T,9,0) -> 21 | AG67: =VLOOKUP(A:A,进销存报表10.16!A:J,10,0) -> 47 | AH67: =VLOOKUP(A:A,进销存报表10.16!A:K,11,0) -> 36 | AI67: 174.08 | AJ67: 163.63 | AK67: 5.33 | AL67: 12 | AM67: =AK67/AI67 -> 0.030618107 | AN67: =AL67/AJ67 -> 0.073336185
A68: OO2EWP04700 | B68: B0GWZLNY3H | C68: 9699EWP047ZUS | D68: FBA | E68: 风险 | F68: 老品 | G68: 潜力 | H68: 明星 | I68: 金牛 | J68: 46.99 | K68: 35.67 | L68: 45.28 | M68: 40.76 | N68: 49.81 | O68: 0 | P68: 1 | Q68: 2 | R68: 9 | S68: 2 | T68: 7 | U68: 1 | V68: 0.33177471 | W68: 0.23484554 | X68: 0.17640463 | Y68: 0.13956188 | Z68: 0.013482945 | AA68: 0.059747497 | AB68: 0.08974359 | AC68: 0.076789009 | AD68: =VLOOKUP(B:B,库存明细报表10.16!L:P,5,0) -> #N/A | AE68: =VLOOKUP(B:B,库存明细报表10.16!L:Q,6,0) -> #N/A | AF68: =VLOOKUP(B:B,库存明细报表10.16!L:T,9,0) -> #N/A | AG68: =VLOOKUP(A:A,进销存报表10.16!A:J,10,0) -> 5 | AH68: =VLOOKUP(A:A,进销存报表10.16!A:K,11,0) -> 24 | AI68: 30.74 | AJ68: 33.76 | AK68: 1 | AL68: 7 | AM68: =AK68/AI68 -> 0.032530904 | AN68: =AL68/AJ68 -> 0.20734597
A69: OO2EWP06100 | B69: B0GWZG6T4W | C69: 4365EWP061CUS | D69: FBA | E69: 维稳 | F69: 老品 | G69: 潜力 | H69: 金牛 | I69: 明星 | J69: 31.99 | K69: 23.41 | L69: 54.96 | M69: 49.46 | N69: 60.46 | O69: 0 | P69: 1 | Q69: 0 | R69: 6 | S69: 5 | T69: 6 | U69: 2 | V69: 0.22546553 | W69: 0.10375858 | X69: 0.2754715 | Y69: 0.13477452 | Z69: 0.042677824 | AA69: 0.045244127 | AB69: 0.18181818 | AC69: 0.24928278 | AD69: =VLOOKUP(B:B,库存明细报表10.16!L:P,5,0) -> 2 | AE69: =VLOOKUP(B:B,库存明细报表10.16!L:Q,6,0) -> 2 | AF69: =VLOOKUP(B:B,库存明细报表10.16!L:T,9,0) -> 2 | AG69: =VLOOKUP(A:A,进销存报表10.16!A:J,10,0) -> 5 | AH69: =VLOOKUP(A:A,进销存报表10.16!A:K,11,0) -> 16 | AI69: 9.34 | AJ69: 12.92 | AK69: 0.33 | AL69: 6.3333333 | AM69: =AK69/AI69 -> 0.035331906 | AN69: =AL69/AJ69 -> 0.49019608
A70: OO2EWP11500 | B70: B0GWZLHQS3 | C70: 2577EWP115BUS | D70: FBA | E70: 维稳 | F70: 老品 | G70: 瘦狗 | H70: 金牛 | I70: 瘦狗 | J70: 29.99 | K70: 21.51 | L70: 25.64 | M70: 23.07 | N70: 28.2 | O70: 0 | P70: 0 | Q70: 2 | R70: 5 | S70: 5 | T70: 3 | U70: 0 | V70: -0.92640615 | W70: 0.14856018 | X70: 0.2465355 | Y70: 0 | Z70: 0.034023503 | AA70: 0.07903137 | AB70: 0.33333333 | AC70: 0.3324887 | AD70: =VLOOKUP(B:B,库存明细报表10.16!L:P,5,0) -> 2 | AE70: =VLOOKUP(B:B,库存明细报表10.16!L:Q,6,0) -> 2 | AF70: =VLOOKUP(B:B,库存明细报表10.16!L:T,9,0) -> 0 | AG70: =VLOOKUP(A:A,进销存报表10.16!A:J,10,0) -> 7 | AH70: =VLOOKUP(A:A,进销存报表10.16!A:K,11,0) -> 10 | AI70: 18 | AJ70: 18.92 | AK70: 0.67 | AL70: 6 | AM70: =AK70/AI70 -> 0.037222222 | AN70: =AL70/AJ70 -> 0.31712474
A71: OO2EWP06300 | B71: B0FZGQ8YH9 | C71: 6783EWP063DUS | D71: FBA | E71: 维稳 | F71: 老品 | G71: 瘦狗 | H71: 金牛 | I71: 明星 | J71: 31.99 | K71: 23.99 | O71: 2 | P71: 2 | Q71: 1 | R71: 6 | S71: 13 | T71: 9 | U71: 1 | V71: 0.15194789 | W71: 0.19544607 | X71: 0.19697315 | Y71: 0.09920918 | Z71: 0.027725229 | AA71: 0.067335264 | AB71: 0.20454545 | AC71: 0.18697613 | AD71: =VLOOKUP(B:B,库存明细报表10.16!L:P,5,0) -> 2 | AE71: =VLOOKUP(B:B,库存明细报表10.16!L:Q,6,0) -> 1 | AF71: =VLOOKUP(B:B,库存明细报表10.16!L:T,9,0) -> 21 | AG71: =VLOOKUP(A:A,进销存报表10.16!A:J,10,0) -> 5 | AH71: =VLOOKUP(A:A,进销存报表10.16!A:K,11,0) -> 23 | AI71: 40.95 | AJ71: 17.54 | AK71: 1.67 | AL71: 10 | AM71: =AK71/AI71 -> 0.040781441 | AN71: =AL71/AJ71 -> 0.57012543
A72: OO2EWP12500 | B72: B0FC5MCKB1 | C72: 8957EWP125VUS | D72: VC | E72: 维稳 | F72: 老品 | G72: 潜力 | H72: 潜力 | I72: 明星 | J72: 36.99 | K72: 16.23 | O72: 1 | P72: 1 | Q72: 0 | R72: 1 | S72: 0 | T72: 0 | U72: 0 | V72: 0.38166358 | W72: 0.41870425 | X72: #N/A | Y72: #N/A | Z72: #N/A | AA72: #N/A | AB72: 0 | AC72: #DIV/0! | AD72: =VLOOKUP(B:B,库存明细报表10.16!L:P,5,0) -> #N/A | AE72: =VLOOKUP(B:B,库存明细报表10.16!L:Q,6,0) -> #N/A | AF72: =VLOOKUP(B:B,库存明细报表10.16!L:T,9,0) -> #N/A | AG72: =VLOOKUP(A:A,进销存报表10.16!A:J,10,0) -> 11 | AH72: =VLOOKUP(A:A,进销存报表10.16!A:K,11,0) -> 2 | AI72: 16.39 | AJ72: 7.84 | AK72: 0.67 | AL72: 0.33333333 | AM72: =AK72/AI72 -> 0.040878585 | AN72: =AL72/AJ72 -> 0.042517007
A73: OO2EWP04800 | B73: B0GWZR1KQ6 | C73: 1211EWP048CUS | D73: FBA | E73: 维稳 | F73: 老品 | G73: 瘦狗 | H73: 明星 | I73: 明星 | J73: 44.99 | K73: 30.36 | L73: 46.72 | M73: 42.05 | N73: 51.39 | O73: 0 | P73: 5 | Q73: 6 | R73: 4 | S73: 6 | T73: 5 | U73: 4 | V73: 0.17516128 | W73: 0.24814905 | X73: 0.32642962 | Y73: 0 | Z73: 0.008084037 | AA73: 0.003821565 | AB73: 0.10204082 | AC73: 0 | AD73: =VLOOKUP(B:B,库存明细报表10.16!L:P,5,0) -> 2 | AE73: =VLOOKUP(B:B,库存明细报表10.16!L:Q,6,0) -> 1 | AF73: =VLOOKUP(B:B,库存明细报表10.16!L:T,9,0) -> 0 | AG73: =VLOOKUP(A:A,进销存报表10.16!A:J,10,0) -> 7 | AH73: =VLOOKUP(A:A,进销存报表10.16!A:K,11,0) -> 28 | AI73: 67.91 | AJ73: 52.74 | AK73: 3.33 | AL73: 5.3333333 | AM73: =AK73/AI73 -> 0.049035488 | AN73: =AL73/AJ73 -> 0.10112502
A74: OO2EWP09400 | B74: B0FZGPWVJ6 | C74: 5790EWP0943US | D74: FBA | E74: 维稳 | F74: 老品 | G74: 瘦狗 | H74: 金牛 | I74: 明星 | J74: 35.99 | K74: 32.62 | L74: 30.62 | M74: 27.55 | N74: 33.68 | O74: 0 | P74: 1 | Q74: 1 | R74: 5 | S74: 1 | T74: 0 | U74: 0 | V74: 0.19524753 | W74: 0.16913661 | X74: 0 | Y74: 0 | Z74: #DIV/0! | AA74: #DIV/0! | AB74: 0 | AC74: 0 | AD74: =VLOOKUP(B:B,库存明细报表10.16!L:P,5,0) -> 19 | AE74: =VLOOKUP(B:B,库存明细报表10.16!L:Q,6,0) -> 19 | AF74: =VLOOKUP(B:B,库存明细报表10.16!L:T,9,0) -> 0 | AG74: =VLOOKUP(A:A,进销存报表10.16!A:J,10,0) -> 17 | AH74: =VLOOKUP(A:A,进销存报表10.16!A:K,11,0) -> 1 | AI74: 5.73 | AJ74: 6.25 | AK74: 0.33 | AL74: 2.3333333 | AM74: =AK74/AI74 -> 0.057591623 | AN74: =AL74/AJ74 -> 0.37333333
A75: OO2EWP11400 | B75: B0G3LFCLSW | C75: 8369EWP114UUS | D75: FBA | E75: 维稳 | F75: 老品 | G75: 瘦狗 | H75: 明星 | I75: 明星 | J75: 38.99 | K75: 32.06 | L75: 43.77 | M75: 39.4 | N75: 48.15 | O75: 1 | P75: 7 | Q75: 8 | R75: 9 | S75: 16 | T75: 5 | U75: 5 | V75: 0.13072654 | W75: 0.21455747 | X75: 0.13063959 | Y75: 0 | Z75: 0.040616317 | AA75: 0.083841754 | AB75: 0.16666667 | AC75: 0.21367074 | AD75: =VLOOKUP(B:B,库存明细报表10.16!L:P,5,0) -> 24 | AE75: =VLOOKUP(B:B,库存明细报表10.16!L:Q,6,0) -> 23 | AF75: =VLOOKUP(B:B,库存明细报表10.16!L:T,9,0) -> 0 | AG75: =VLOOKUP(A:A,进销存报表10.16!A:J,10,0) -> 22 | AH75: =VLOOKUP(A:A,进销存报表10.16!A:K,11,0) -> 48 | AI75: 91.42 | AJ75: 86.02 | AK75: 6 | AL75: 10 | AM75: =AK75/AI75 -> 0.065631153 | AN75: =AL75/AJ75 -> 0.11625203
A76: OO2EWP05800 | B76: B0G3LJYFZX | C76: 6114EWP058CUS | D76: FBA | E76: 维稳 | F76: 老品 | G76: 潜力 | H76: 明星 | I76: 明星 | J76: 51.99 | K76: 43.65 | L76: 51.08 | M76: 45.97 | N76: 56.19 | O76: 0 | P76: 3 | Q76: 12 | R76: 15 | S76: 3 | T76: 10 | U76: 4 | V76: 0.24254717 | W76: 0.20699482 | X76: 0.39243854 | Y76: 0.10731844 | Z76: 0.021167429 | AA76: 0.040896758 | AB76: 0.14492754 | AC76: 0.11741438 | AD76: =VLOOKUP(B:B,库存明细报表10.16!L:P,5,0) -> 46 | AE76: =VLOOKUP(B:B,库存明细报表10.16!L:Q,6,0) -> 38 | AF76: =VLOOKUP(B:B,库存明细报表10.16!L:T,9,0) -> 4 | AG76: =VLOOKUP(A:A,进销存报表10.16!A:J,10,0) -> 44 | AH76: =VLOOKUP(A:A,进销存报表10.16!A:K,11,0) -> 24 | AI76: 68.51 | AJ76: 42.92 | AK76: 5.33 | AL76: 9 | AM76: =AK76/AI76 -> 0.077798861 | AN76: =AL76/AJ76 -> 0.20969245
A77: OO2EWP06200 | B77: B0G3LG85VS | C77: 4146EWP062FUS | D77: FBA | E77: 维稳 | F77: 老品 | G77: 瘦狗 | H77: 明星 | I77: 金牛 | J77: 28.99 | K77: 20.43 | L77: 41.28 | M77: 37.15 | N77: 45.41 | O77: 5 | P77: 13 | Q77: 3 | R77: 14 | S77: 11 | T77: 14 | U77: 3 | V77: 0.024451522 | W77: 0.20477128 | X77: 0.089931218 | Y77: 0.28220046 | Z77: 0.026879741 | AA77: 0.032296899 | AB77: 0.068627451 | AC77: 0.094989778 | AD77: =VLOOKUP(B:B,库存明细报表10.16!L:P,5,0) -> 21 | AE77: =VLOOKUP(B:B,库存明细报表10.16!L:Q,6,0) -> 18 | AF77: =VLOOKUP(B:B,库存明细报表10.16!L:T,9,0) -> 0 | AG77: =VLOOKUP(A:A,进销存报表10.16!A:J,10,0) -> 39 | AH77: =VLOOKUP(A:A,进销存报表10.16!A:K,11,0) -> 31 | AI77: 81.06 | AJ77: 74.65 | AK77: 7.33 | AL77: 14 | AM77: =AK77/AI77 -> 0.090426844 | AN77: =AL77/AJ77 -> 0.18754186
A78: OO2EWP05400 | B78: B0FLJW7Y8P | C78: 7229EWP054RUS | D78: FBA | E78: 维稳 | F78: 老品 | G78: 明星 | H78: 金牛 | I78: 明星 | J78: 25.99 | K78: 19.48 | L78: 28.73 | M78: 25.85 | N78: 31.6 | O78: 3 | P78: 10 | Q78: 2 | R78: 0 | S78: 4 | T78: 3 | U78: 0 | V78: 0.27161969 | W78: 0.031096479 | X78: -0.26631541 | Y78: 0.86448363 | Z78: 0.029974811 | AA78: 0.023468934 | AB78: 0.027522936 | AC78: 0 | AD78: =VLOOKUP(B:B,库存明细报表10.16!L:P,5,0) -> 14 | AE78: =VLOOKUP(B:B,库存明细报表10.16!L:Q,6,0) -> 14 | AF78: =VLOOKUP(B:B,库存明细报表10.16!L:T,9,0) -> 0 | AG78: =VLOOKUP(A:A,进销存报表10.16!A:J,10,0) -> 7 | AH78: =VLOOKUP(A:A,进销存报表10.16!A:K,11,0) -> 9 | AI78: 34.14 | AJ78: 21.88 | AK78: 5.33 | AL78: 2.6666667 | AM78: =AK78/AI78 -> 0.15612185 | AN78: =AL78/AJ78 -> 0.1218769
A79: OO2EWP01000 | B79: B0GWZNXH6Z | C79: 3060EWP0101US | D79: FBA | E79: 风险 | F79: 老品 | G79: 明星 | H79: 明星 | I79: 明星 | J79: 59.99 | K79: 42.4 | O79: 3 | P79: 4 | Q79: 2 | R79: 4 | S79: 6 | T79: 8 | U79: 2 | V79: 0.32057046 | W79: 0.27240791 | X79: 0.28433822 | Y79: 0.12311197 | Z79: 0.023682482 | AA79: 0.050611897 | AB79: 0.093023256 | AC79: 0.058723535 | AD79: =VLOOKUP(B:B,库存明细报表10.16!L:P,5,0) -> 3 | AE79: =VLOOKUP(B:B,库存明细报表10.16!L:Q,6,0) -> 0 | AF79: =VLOOKUP(B:B,库存明细报表10.16!L:T,9,0) -> 9 | AG79: =VLOOKUP(A:A,进销存报表10.16!A:J,10,0) -> 13 | AH79: =VLOOKUP(A:A,进销存报表10.16!A:K,11,0) -> 12 | AI79: 8.25 | AJ79: 7.37 | AK79: 3 | AL79: 6 | AM79: =AK79/AI79 -> 0.36363636 | AN79: =AL79/AJ79 -> 0.81411126
A80: OO2EWP10600 | B80: B0G3LLJK2D | C80: 9909EWP106UUS | D80: FBA | E80: 维稳 | F80: 老品 | G80: 瘦狗 | H80: 未分层 | I80: #N/A | J80: 51.99 | K80: 39.2 | L80: #N/A | M80: #N/A | N80: #N/A | O80: 0 | P80: 0 | Q80: 9 | R80: 16 | S80: 14 | T80: 2 | U80: 0 | V80: 0.1481617 | W80: 0.21145175 | X80: 1.3152219 | Y80: 0 | Z80: 0.010802179 | AA80: 0.003821582 | AB80: 0.043478261 | AC80: 0 | AD80: =VLOOKUP(B:B,库存明细报表10.16!L:P,5,0) -> 0 | AE80: =VLOOKUP(B:B,库存明细报表10.16!L:Q,6,0) -> 0 | AF80: =VLOOKUP(B:B,库存明细报表10.16!L:T,9,0) -> 24 | AG80: =VLOOKUP(A:A,进销存报表10.16!A:J,10,0) -> 13 | AH80: =VLOOKUP(A:A,进销存报表10.16!A:K,11,0) -> 42 | AI80: #N/A | AJ80: 0 | AK80: 3 | AL80: 12 | AM80: =AK80/AI80 -> #VALUE! | AN80: =AL80/AJ80 -> #DIV/0!
A81: OO2EWP04000 | B81: B0GWR7MW7T | C81: 7827EWP0401US | D81: FBA | E81: 风险 | F81: 老品 | G81: 瘦狗 | H81: 未分层 | I81: #N/A | J81: 52.99 | K81: 41.84 | L81: #N/A | M81: #N/A | N81: #N/A | O81: 0 | P81: 2 | Q81: 2 | R81: 1 | S81: 1 | T81: 4 | U81: 2 | V81: 0.10306221 | W81: 0.016300264 | X81: -0.032533966 | Y81: 0.31034269 | Z81: 0.053948349 | AA81: 0.05646621 | AB81: 0.10526316 | AC81: 0.090729348 | AD81: =VLOOKUP(B:B,库存明细报表10.16!L:P,5,0) -> 19 | AE81: =VLOOKUP(B:B,库存明细报表10.16!L:Q,6,0) -> 8 | AF81: =VLOOKUP(B:B,库存明细报表10.16!L:T,9,0) -> 0 | AG81: =VLOOKUP(A:A,进销存报表10.16!A:J,10,0) -> 18 | AH81: =VLOOKUP(A:A,进销存报表10.16!A:K,11,0) -> 2 | AI81: #N/A | AJ81: 0 | AK81: 1.33 | AL81: 2 | AM81: =AK81/AI81 -> #VALUE! | AN81: =AL81/AJ81 -> #DIV/0!
A82: OO2EWP02700 | B82: B0GWQNXB9R | C82: 6490EWP027NUS | D82: FBA | E82: 风险 | F82: 老品 | G82: #N/A | H82: 潜力 | I82: 潜力 | J82: 29.99 | K82: 22.57 | L82: 25.64 | M82: 23.07 | N82: 28.2 | O82: 0 | P82: 0 | Q82: 0 | R82: 1 | S82: 1 | T82: 0 | U82: 2 | V82: 0 | W82: 0.60386116 | X82: 0 | Y82: 0 | Z82: #DIV/0! | AA82: #DIV/0! | AB82: 0 | AC82: 0 | AD82: =VLOOKUP(B:B,库存明细报表10.16!L:P,5,0) -> 16 | AE82: =VLOOKUP(B:B,库存明细报表10.16!L:Q,6,0) -> 16 | AF82: =VLOOKUP(B:B,库存明细报表10.16!L:T,9,0) -> 0 | AG82: =VLOOKUP(A:A,进销存报表10.16!A:J,10,0) -> 26 | AH82: =VLOOKUP(A:A,进销存报表10.16!A:K,11,0) -> 10 | AI82: 207.47 | AJ82: 137.19 | AK82: #N/A | AL82: 0.66666667 | AM82: =AK82/AI82 -> #VALUE! | AN82: =AL82/AJ82 -> 0.0048594407
A83: OO2EWP12400 | B83: B0GWR2PWNH | C83: 2549EWP1241US | D83: FBA | E83: 维稳 | F83: 老品 | G83: 瘦狗 | H83: 未分层 | I83: #N/A | J83: 47.99 | K83: 36.13 | L83: #N/A | M83: #N/A | N83: #N/A | O83: 0 | P83: 0 | Q83: 1 | R83: 1 | S83: 3 | T83: 8 | U83: 2 | V83: 0.26635987 | W83: 0.18052932 | X83: 0.14846169 | Y83: 0.14139242 | Z83: 0.026339825 | AA83: 0.048958694 | AB83: 0.20512821 | AC83: 0.15752307 | AD83: =VLOOKUP(B:B,库存明细报表10.16!L:P,5,0) -> 28 | AE83: =VLOOKUP(B:B,库存明细报表10.16!L:Q,6,0) -> 28 | AF83: =VLOOKUP(B:B,库存明细报表10.16!L:T,9,0) -> 0 | AG83: =VLOOKUP(A:A,进销存报表10.16!A:J,10,0) -> 13 | AH83: =VLOOKUP(A:A,进销存报表10.16!A:K,11,0) -> 24 | AI83: #N/A | AJ83: 0 | AK83: 0.33 | AL83: 4 | AM83: =AK83/AI83 -> #VALUE! | AN83: =AL83/AJ83 -> #DIV/0!
A84: ZC2CLK04100 | B84: B0GWQXWG5D | C84: 9147CLK041TUS | D84: FBA | E84: 维稳 | F84: 老品 | G84: #N/A | H84: 瘦狗 | I84: 潜力 | J84: 29.99 | K84: 21.84 | L84: 32.17 | M84: 28.95 | N84: 35.39 | O84: 0 | P84: 0 | Q84: 1 | R84: 1 | S84: 0 | T84: 3 | U84: 4 | V84: 0 | W84: 0.12464349 | X84: 0.052059714 | Y84: 0.33370424 | Z84: 0.077000111 | AA84: 0.05712083 | AB84: 0.13043478 | AC84: 0.15343669 | AD84: =VLOOKUP(B:B,库存明细报表10.16!L:P,5,0) -> 14 | AE84: =VLOOKUP(B:B,库存明细报表10.16!L:Q,6,0) -> 13 | AF84: =VLOOKUP(B:B,库存明细报表10.16!L:T,9,0) -> 3 | AG84: =VLOOKUP(A:A,进销存报表10.16!A:J,10,0) -> 9 | AH84: =VLOOKUP(A:A,进销存报表10.16!A:K,11,0) -> 12 | AI84: 274.4 | AJ84: 204.01 | AK84: #N/A | AL84: 1.6666667 | AM84: =AK84/AI84 -> #VALUE! | AN84: =AL84/AJ84 -> 0.0081695342
A85: OO2EWP09600 | B85: B0GWR6Q3XR | C85: 9445EWP096LUS | D85: FBA | E85: 维稳 | F85: 老品 | G85: #N/A | H85: 明星 | I85: 明星 | J85: 24.99 | K85: 17.04 | L85: 23.43 | M85: 21.09 | N85: 25.77 | O85: 0 | P85: 0 | Q85: 0 | R85: 1 | S85: 3 | T85: 5 | U85: 5 | V85: 0 | W85: 0.27209156 | X85: 0.23073198 | Y85: 0 | Z85: 0.077904687 | AA85: 0.083853099 | AB85: 0.11904762 | AC85: 0 | AD85: =VLOOKUP(B:B,库存明细报表10.16!L:P,5,0) -> 2 | AE85: =VLOOKUP(B:B,库存明细报表10.16!L:Q,6,0) -> 2 | AF85: =VLOOKUP(B:B,库存明细报表10.16!L:T,9,0) -> 2 | AG85: =VLOOKUP(A:A,进销存报表10.16!A:J,10,0) -> 12 | AH85: =VLOOKUP(A:A,进销存报表10.16!A:K,11,0) -> 6 | AI85: 24.01 | AJ85: 12.54 | AK85: #N/A | AL85: 3 | AM85: =AK85/AI85 -> #VALUE! | AN85: =AL85/AJ85 -> 0.23923445
A86: OO2EWP12100 | B86: B0GWR42KD9 | C86: 1623EWP1217US | D86: FBA | E86: 维稳 | F86: 老品 | G86: #N/A | H86: 金牛 | I86: 潜力 | J86: 29.99 | K86: 27.94 | L86: 19 | M86: 17.1 | N86: 20.9 | O86: 0 | P86: 0 | Q86: 0 | R86: 0 | S86: 6 | T86: 1 | U86: 1 | V86: 0 | W86: 0.11952999 | X86: -0.42656365 | Y86: 1 | Z86: 0.15286027 | AA86: 0.003821456 | AB86: 0.04 | AC86: 0 | AD86: =VLOOKUP(B:B,库存明细报表10.16!L:P,5,0) -> 4 | AE86: =VLOOKUP(B:B,库存明细报表10.16!L:Q,6,0) -> 4 | AF86: =VLOOKUP(B:B,库存明细报表10.16!L:T,9,0) -> 0 | AG86: =VLOOKUP(A:A,进销存报表10.16!A:J,10,0) -> 14 | AH86: =VLOOKUP(A:A,进销存报表10.16!A:K,11,0) -> 0 | AI86: 59.07 | AJ86: 22.2 | AK86: #N/A | AL86: 2.3333333 | AM86: =AK86/AI86 -> #VALUE! | AN86: =AL86/AJ86 -> 0.10510511
A87: OO2EWP05300 | B87: B0GWQJRJ41 | C87: 3062EWP053SUS | D87: FBA | E87: 风险 | F87: 老品 | G87: #N/A | H87: 瘦狗 | I87: 潜力 | J87: 31.99 | K87: 25.5 | L87: 27.54 | M87: 24.78 | N87: 30.29 | O87: 0 | P87: 0 | Q87: 1 | R87: 2 | S87: 7 | T87: 0 | U87: 3 | V87: 0 | W87: 0.066169115 | X87: 0.23505912 | Y87: 3.9651442 | Z87: 0.38581731 | AA87: -0.31348593 | AB87: 0 | AC87: 0 | AD87: =VLOOKUP(B:B,库存明细报表10.16!L:P,5,0) -> 5 | AE87: =VLOOKUP(B:B,库存明细报表10.16!L:Q,6,0) -> 3 | AF87: =VLOOKUP(B:B,库存明细报表10.16!L:T,9,0) -> 0 | AG87: =VLOOKUP(A:A,进销存报表10.16!A:J,10,0) -> 12 | AH87: =VLOOKUP(A:A,进销存报表10.16!A:K,11,0) -> 2 | AI87: 157.34 | AJ87: 104.2 | AK87: #N/A | AL87: 4 | AM87: =AK87/AI87 -> #VALUE! | AN87: =AL87/AJ87 -> 0.038387716
A88: OO2EWP09100 | B88: B0GWZBW3C4 | C88: 9006EWP091YUS | D88: FBA | E88: 维稳 | F88: 老品 | G88: #N/A | H88: 潜力 | I88: 潜力 | J88: 24.99 | K88: 18.46 | L88: 20.89 | M88: 18.8 | N88: 22.98 | O88: 0 | P88: 0 | Q88: 0 | R88: 7 | S88: 6 | T88: 6 | U88: 4 | V88: 0 | W88: 0.22917389 | X88: 0.2401587 | Y88: 0 | Z88: 0.047504716 | AA88: 0.049554137 | AB88: 0.14285714 | AC88: 0.10503282 | AD88: =VLOOKUP(B:B,库存明细报表10.16!L:P,5,0) -> 20 | AE88: =VLOOKUP(B:B,库存明细报表10.16!L:Q,6,0) -> 17 | AF88: =VLOOKUP(B:B,库存明细报表10.16!L:T,9,0) -> 5 | AG88: =VLOOKUP(A:A,进销存报表10.16!A:J,10,0) -> 10 | AH88: =VLOOKUP(A:A,进销存报表10.16!A:K,11,0) -> 11 | AI88: 126.29 | AJ88: 87.07 | AK88: #N/A | AL88: 6.3333333 | AM88: =AK88/AI88 -> #VALUE! | AN88: =AL88/AJ88 -> 0.07273841
A89: OO2EWP12300 | B89: B0GWR6FG91 | C89: 5536EWP123HUS | D89: FBA | E89: 维稳 | F89: 老品 | G89: 瘦狗 | H89: 未分层 | I89: #N/A | J89: 33.99 | K89: 26.21 | L89: #N/A | M89: #N/A | N89: #N/A | O89: 0 | P89: 0 | Q89: 0 | R89: 4 | S89: 11 | T89: 2 | U89: 4 | V89: 0 | W89: 0.13691252 | X89: 0.12005186 | Y89: 0.32439397 | Z89: 0.085417064 | AA89: 0.049250046 | AB89: 0.071428571 | AC89: 0.11733723 | AD89: =VLOOKUP(B:B,库存明细报表10.16!L:P,5,0) -> 10 | AE89: =VLOOKUP(B:B,库存明细报表10.16!L:Q,6,0) -> 10 | AF89: =VLOOKUP(B:B,库存明细报表10.16!L:T,9,0) -> 0 | AG89: =VLOOKUP(A:A,进销存报表10.16!A:J,10,0) -> 1 | AH89: =VLOOKUP(A:A,进销存报表10.16!A:K,11,0) -> 6 | AI89: #N/A | AJ89: 0 | AK89: 0 | AL89: 6.3333333 | AM89: =AK89/AI89 -> #VALUE! | AN89: =AL89/AJ89 -> #DIV/0!
A90: OO2EWP10900 | B90: B0GWQQCTFC | C90: 1772EWP109KUS | D90: FBA | E90: 维稳 | F90: 老品 | G90: #N/A | H90: 未分层 | I90: 潜力 | J90: 25.99 | K90: 20.34 | L90: 21.84 | M90: 19.65 | N90: 24.02 | O90: 0 | P90: 0 | Q90: 0 | R90: 0 | S90: 0 | T90: 0 | U90: 0 | V90: 0 | W90: 0 | X90: 0 | Y90: 0 | Z90: #DIV/0! | AA90: #DIV/0! | AB90: 0 | AC90: #DIV/0! | AD90: =VLOOKUP(B:B,库存明细报表10.16!L:P,5,0) -> 16 | AE90: =VLOOKUP(B:B,库存明细报表10.16!L:Q,6,0) -> 16 | AF90: =VLOOKUP(B:B,库存明细报表10.16!L:T,9,0) -> 0 | AG90: =VLOOKUP(A:A,进销存报表10.16!A:J,10,0) -> 26 | AH90: =VLOOKUP(A:A,进销存报表10.16!A:K,11,0) -> 5 | AI90: 36.42 | AJ90: 17.02 | AK90: #N/A | AL90: 0 | AM90: =AK90/AI90 -> #VALUE! | AN90: =AL90/AJ90 -> 0
A91: OO2EWP09300 | B91: B0GWZDQ8Q1 | C91: 6131EWP0939US | D91: FBA | E91: 维稳 | F91: 老品 | G91: #N/A | H91: 潜力 | I91: 明星 | J91: 27.99 | K91: 17.32 | L91: 30.35 | M91: 27.32 | N91: 33.39 | O91: 0 | P91: 0 | Q91: 0 | R91: 1 | S91: 0 | T91: 2 | U91: 3 | V91: 0 | W91: 0.26839691 | X91: 0.38286388 | Y91: 0 | Z91: 0.10203401 | AA91: 0.083848221 | AB91: 0.125 | AC91: 0.14254473 | AD91: =VLOOKUP(B:B,库存明细报表10.16!L:P,5,0) -> 9 | AE91: =VLOOKUP(B:B,库存明细报表10.16!L:Q,6,0) -> 9 | AF91: =VLOOKUP(B:B,库存明细报表10.16!L:T,9,0) -> 0 | AG91: =VLOOKUP(A:A,进销存报表10.16!A:J,10,0) -> 12 | AH91: =VLOOKUP(A:A,进销存报表10.16!A:K,11,0) -> 7 | AI91: 12.89 | AJ91: 10.8 | AK91: #N/A | AL91: 1 | AM91: =AK91/AI91 -> #VALUE! | AN91: =AL91/AJ91 -> 0.092592593
A92: OO2EWP03400 | B92: B0GWQT6CY9 | C92: 8556EWP034YUS | D92: FBA | E92: 风险 | F92: 老品 | G92: #N/A | H92: 潜力 | I92: 潜力 | J92: 29.99 | K92: 19.15 | L92: 19.3 | M92: 17.37 | N92: 21.23 | O92: 0 | P92: 0 | Q92: 1 | R92: 1 | S92: 0 | T92: 4 | U92: 4 | V92: 0 | W92: 0.31334825 | X92: 0.33273232 | Y92: 0 | Z92: 0.043014338 | AA92: 0.083848235 | AB92: 0.16 | AC92: 0.39896871 | AD92: =VLOOKUP(B:B,库存明细报表10.16!L:P,5,0) -> 9 | AE92: =VLOOKUP(B:B,库存明细报表10.16!L:Q,6,0) -> 9 | AF92: =VLOOKUP(B:B,库存明细报表10.16!L:T,9,0) -> 1 | AG92: =VLOOKUP(A:A,进销存报表10.16!A:J,10,0) -> 22 | AH92: =VLOOKUP(A:A,进销存报表10.16!A:K,11,0) -> 3 | AI92: 164.48 | AJ92: 125.66 | AK92: #N/A | AL92: 2 | AM92: =AK92/AI92 -> #VALUE! | AN92: =AL92/AJ92 -> 0.015915964
A93: OO2EWP00500 | B93: B0GYRV9MW3 | C93: 7466EWP0052US | D93: FBA | E93: 维稳 | F93: 老品 | G93: 瘦狗 | H93: 未分层 | I93: #N/A | J93: 37.99 | K93: 26.47 | L93: #N/A | M93: #N/A | N93: #N/A | O93: 0 | P93: 0 | Q93: 0 | R93: 3 | S93: 7 | T93: 1 | U93: 1 | V93: 0 | W93: 0.26111758 | X93: 0.24758847 | Y93: 0 | Z93: 0.079099763 | AA93: 0.043832067 | AB93: 0.016949153 | AC93: 0 | AD93: =VLOOKUP(B:B,库存明细报表10.16!L:P,5,0) -> 13 | AE93: =VLOOKUP(B:B,库存明细报表10.16!L:Q,6,0) -> 13 | AF93: =VLOOKUP(B:B,库存明细报表10.16!L:T,9,0) -> 0 | AG93: =VLOOKUP(A:A,进销存报表10.16!A:J,10,0) -> 0 | AH93: =VLOOKUP(A:A,进销存报表10.16!A:K,11,0) -> 11 | AI93: #N/A | AJ93: 0 | AK93: 0 | AL93: 4 | AM93: =AK93/AI93 -> #VALUE! | AN93: =AL93/AJ93 -> #DIV/0!
A94: OO2EWP01900 | B94: B0GYRF41VB | C94: 2990EWP019NUS | D94: FBA | E94: 风险 | F94: 老品 | G94: #N/A | H94: 瘦狗 | I94: 瘦狗 | J94: 62.99 | K94: 47.2 | L94: 41.48 | M94: 37.33 | N94: 45.63 | O94: 0 | P94: 0 | Q94: 0 | R94: 0 | S94: 1 | T94: 0 | U94: 1 | V94: 0 | W94: 0.030056489 | X94: 0 | Y94: 0 | Z94: #DIV/0! | AA94: #DIV/0! | AB94: 0 | AC94: 0 | AD94: =VLOOKUP(B:B,库存明细报表10.16!L:P,5,0) -> 10 | AE94: =VLOOKUP(B:B,库存明细报表10.16!L:Q,6,0) -> 7 | AF94: =VLOOKUP(B:B,库存明细报表10.16!L:T,9,0) -> 0 | AG94: =VLOOKUP(A:A,进销存报表10.16!A:J,10,0) -> 3 | AH94: =VLOOKUP(A:A,进销存报表10.16!A:K,11,0) -> 10 | AI94: 74.39 | AJ94: 46.89 | AK94: #N/A | AL94: 0.33333333 | AM94: =AK94/AI94 -> #VALUE! | AN94: =AL94/AJ94 -> 0.0071088363
A95: OO2EWP02400 | B95: B0GYS648HC | C95: 2487EWP024ZUS | D95: FBA | E95: 维稳 | F95: 老品 | G95: #N/A | H95: 潜力 | I95: 潜力 | J95: 48.99 | K95: 34.17 | L95: 44.99 | M95: 40.49 | N95: 49.49 | O95: 0 | P95: 0 | Q95: 0 | R95: 0 | S95: 4 | T95: 8 | U95: 4 | V95: 0 | W95: 0.26699747 | X95: 0.28544254 | Y95: 0 | Z95: 0.00806287 | AA95: 0.043829715 | AB95: 0.17021277 | AC95: 0.28506954 | AD95: =VLOOKUP(B:B,库存明细报表10.16!L:P,5,0) -> 25 | AE95: =VLOOKUP(B:B,库存明细报表10.16!L:Q,6,0) -> 19 | AF95: =VLOOKUP(B:B,库存明细报表10.16!L:T,9,0) -> 0 | AG95: =VLOOKUP(A:A,进销存报表10.16!A:J,10,0) -> 0 | AH95: =VLOOKUP(A:A,进销存报表10.16!A:K,11,0) -> 66 | AI95: 195.89 | AJ95: 153.74 | AK95: #N/A | AL95: 4 | AM95: =AK95/AI95 -> #VALUE! | AN95: =AL95/AJ95 -> 0.026017952
A96: ZC2CLK05000 | B96: B0HD5FB81R | C96: 6505CLK050KUS | D96: FBA | E96: 维稳 | F96: 老品 | G96: #N/A | H96: 未分层 | I96: 瘦狗 | J96: 79.99 | K96: 51.18 | L96: 46.73 | M96: 42.06 | N96: 51.4 | O96: #N/A | P96: #N/A | Q96: #N/A | R96: #N/A | S96: 0 | T96: 0 | U96: 0 | V96: 0 | W96: 0 | X96: #N/A | Y96: #N/A | Z96: #N/A | AA96: #N/A | AB96: 0 | AC96: #DIV/0! | AD96: =VLOOKUP(B:B,库存明细报表10.16!L:P,5,0) -> 12 | AE96: =VLOOKUP(B:B,库存明细报表10.16!L:Q,6,0) -> 3 | AF96: =VLOOKUP(B:B,库存明细报表10.16!L:T,9,0) -> 6 | AG96: =VLOOKUP(A:A,进销存报表10.16!A:J,10,0) -> 29 | AH96: =VLOOKUP(A:A,进销存报表10.16!A:K,11,0) -> 25 | AI96: 452.32 | AJ96: 307.15 | AK96: #N/A | AL96: 0 | AM96: =AK96/AI96 -> #VALUE! | AN96: =AL96/AJ96 -> 0
A97: OO2EWP02900 | B97: B0HD5Q89RG | C97: 5867EWP029MUS | D97: FBA | E97: 维稳 | F97: 老品 | G97: #N/A | H97: 潜力 | I97: 潜力 | J97: 36.99 | K97: 21.19 | L97: 24.28 | M97: 21.85 | N97: 26.71 | O97: #N/A | P97: #N/A | Q97: #N/A | R97: #N/A | S97: 1 | T97: 1 | U97: 0 | V97: 0 | W97: 0.28291686 | X97: #N/A | Y97: #N/A | Z97: #N/A | AA97: #N/A | AB97: 0.11111111 | AC97: #DIV/0! | AD97: =VLOOKUP(B:B,库存明细报表10.16!L:P,5,0) -> 0 | AE97: =VLOOKUP(B:B,库存明细报表10.16!L:Q,6,0) -> 0 | AF97: =VLOOKUP(B:B,库存明细报表10.16!L:T,9,0) -> 0 | AG97: =VLOOKUP(A:A,进销存报表10.16!A:J,10,0) -> 14 | AH97: =VLOOKUP(A:A,进销存报表10.16!A:K,11,0) -> 38 | AI97: 486.18 | AJ97: 408.33 | AK97: #N/A | AL97: 0.33333333 | AM97: =AK97/AI97 -> #VALUE! | AN97: =AL97/AJ97 -> 0.00081633319
A98: KC2EWP25500 | B98: B0HD6KL2ZX | C98: 3443EWP2554US | D98: FBA | E98: 推新 | F98: 新品 | G98: #N/A | H98: 未分层 | I98: 新品待观察 | J98: 59.99 | K98: 44.26 | O98: #N/A | P98: #N/A | Q98: #N/A | R98: #N/A | S98: 0 | T98: 0 | U98: 0 | V98: 0 | W98: 0 | X98: #N/A | Y98: #N/A | Z98: #N/A | AA98: #N/A | AB98: 0 | AC98: #DIV/0! | AD98: =VLOOKUP(B:B,库存明细报表10.16!L:P,5,0) -> #N/A | AE98: =VLOOKUP(B:B,库存明细报表10.16!L:Q,6,0) -> #N/A | AF98: =VLOOKUP(B:B,库存明细报表10.16!L:T,9,0) -> #N/A | AG98: =VLOOKUP(A:A,进销存报表10.16!A:J,10,0) -> 41 | AH98: =VLOOKUP(A:A,进销存报表10.16!A:K,11,0) -> 30 | AI98: 56.99 | AJ98: 41.42 | AK98: #N/A | AL98: 0 | AM98: =AK98/AI98 -> #VALUE! | AN98: =AL98/AJ98 -> 0
A99: OO2EWP02500 | B99: B0HD68B8BL | C99: 9417EWP0256US | D99: FBA | E99: 维稳 | F99: 老品 | G99: #N/A | H99: 未分层 | I99: 瘦狗 | J99: 49.99 | K99: 38.09 | L99: 35.88 | M99: 32.3 | N99: 39.47 | O99: #N/A | P99: #N/A | Q99: #N/A | R99: #N/A | S99: 0 | T99: 0 | U99: 0 | V99: 0 | W99: 0 | X99: #N/A | Y99: #N/A | Z99: #N/A | AA99: #N/A | AB99: 0 | AC99: #DIV/0! | AD99: =VLOOKUP(B:B,库存明细报表10.16!L:P,5,0) -> 6 | AE99: =VLOOKUP(B:B,库存明细报表10.16!L:Q,6,0) -> 0 | AF99: =VLOOKUP(B:B,库存明细报表10.16!L:T,9,0) -> 0 | AG99: =VLOOKUP(A:A,进销存报表10.16!A:J,10,0) -> 10 | AH99: =VLOOKUP(A:A,进销存报表10.16!A:K,11,0) -> 2 | AI99: 372.38 | AJ99: 247.87 | AK99: #N/A | AL99: 0 | AM99: =AK99/AI99 -> #VALUE! | AN99: =AL99/AJ99 -> 0
A100: ZC2CLK02900 | B100: B0HD68W4G6 | C100: 2515CLK0299US | D100: FBA | E100: 风险 | F100: 老品 | G100: #N/A | H100: 未分层 | I100: #N/A | J100: 59.99 | K100: 47.74 | L100: #N/A | M100: #N/A | N100: #N/A | O100: #N/A | P100: #N/A | Q100: #N/A | R100: #N/A | S100: 0 | T100: 2 | U100: 1 | V100: 0 | W100: 0.12667136 | X100: 0.12667136 | Y100: 0 | Z100: 0 | AA100: 0.19337125 | AB100: 0.017857143 | AC100: #DIV/0! | AD100: =VLOOKUP(B:B,库存明细报表10.16!L:P,5,0) -> 11 | AE100: =VLOOKUP(B:B,库存明细报表10.16!L:Q,6,0) -> 6 | AF100: =VLOOKUP(B:B,库存明细报表10.16!L:T,9,0) -> 21 | AG100: =VLOOKUP(A:A,进销存报表10.16!A:J,10,0) -> 11 | AH100: =VLOOKUP(A:A,进销存报表10.16!A:K,11,0) -> 6 | AI100: #N/A | AJ100: 0 | AK100: #N/A | AL100: 0.33333333 | AM100: =AK100/AI100 -> #VALUE! | AN100: =AL100/AJ100 -> #DIV/0!
A101: KC2EWP16700 | B101: B0HD5ZTHD1 | C101: 9111EWP167VUS | D101: FBA | E101: 交付中 | F101: 新品 | G101: #N/A | H101: 潜力 | I101: 新品待观察 | J101: 34.99 | K101: 23.6 | O101: #N/A | P101: #N/A | Q101: #N/A | R101: #N/A | S101: 0 | T101: 4 | U101: 0 | V101: 0 | W101: 0.20553042 | X101: 0.20552841 | Y101: 0 | Z101: 0.052631579 | AA101: 0.060243584 | AB101: 0.22222222 | AC101: 0 | AD101: =VLOOKUP(B:B,库存明细报表10.16!L:P,5,0) -> 0 | AE101: =VLOOKUP(B:B,库存明细报表10.16!L:Q,6,0) -> 0 | AF101: =VLOOKUP(B:B,库存明细报表10.16!L:T,9,0) -> 16 | AG101: =VLOOKUP(A:A,进销存报表10.16!A:J,10,0) -> 8 | AH101: =VLOOKUP(A:A,进销存报表10.16!A:K,11,0) -> 7 | AI101: 98.68 | AJ101: 69.8 | AK101: #N/A | AL101: 0.66666667 | AM101: =AK101/AI101 -> #VALUE! | AN101: =AL101/AJ101 -> 0.0095510984
A102: KC2EWP26400 | B102: B0HD684QKG | C102: 7973EWP264YUS | D102: FBA | E102: 推新 | F102: 新品 | G102: #N/A | H102: 瘦狗 | I102: 新品待观察 | J102: 29.99 | K102: 21.09 | O102: #N/A | P102: #N/A | Q102: #N/A | R102: #N/A | S102: 0 | T102: 1 | U102: 0 | V102: 0 | W102: -0.005952373 | X102: 0.015053733 | Y102: 0 | Z102: 0.17008504 | AA102: 0.12656328 | AB102: 0.029411765 | AC102: 0.14284212 | AD102: =VLOOKUP(B:B,库存明细报表10.16!L:P,5,0) -> 0 | AE102: =VLOOKUP(B:B,库存明细报表10.16!L:Q,6,0) -> 0 | AF102: =VLOOKUP(B:B,库存明细报表10.16!L:T,9,0) -> 15 | AG102: =VLOOKUP(A:A,进销存报表10.16!A:J,10,0) -> 14 | AH102: =VLOOKUP(A:A,进销存报表10.16!A:K,11,0) -> 14 | AI102: 54.89 | AJ102: 38.12 | AK102: #N/A | AL102: 0.33333333 | AM102: =AK102/AI102 -> #VALUE! | AN102: =AL102/AJ102 -> 0.0087443162
A103: KC2EWP27200 | B103: B0HD63SR81 | C103: 9377EWP2729US | D103: FBA | E103: 交付中 | F103: 新品 | G103: #N/A | H103: 未分层 | I103: 新品待观察 | J103: 35.99 | K103: 24.74 | O103: #N/A | P103: #N/A | Q103: #N/A | R103: #N/A | S103: 0 | T103: 0 | U103: 0 | V103: 0 | W103: 0 | X103: 0 | Y103: 0 | Z103: #DIV/0! | AA103: #DIV/0! | AB103: 0 | AC103: 0 | AD103: =VLOOKUP(B:B,库存明细报表10.16!L:P,5,0) -> 0 | AE103: =VLOOKUP(B:B,库存明细报表10.16!L:Q,6,0) -> 0 | AF103: =VLOOKUP(B:B,库存明细报表10.16!L:T,9,0) -> 18 | AG103: =VLOOKUP(A:A,进销存报表10.16!A:J,10,0) -> 15 | AH103: =VLOOKUP(A:A,进销存报表10.16!A:K,11,0) -> 7 | AI103: 65.62 | AJ103: 56.97 | AK103: #N/A | AL103: 0 | AM103: =AK103/AI103 -> #VALUE! | AN103: =AL103/AJ103 -> 0
...

Sheet 日更监控
A1: 更新时间 | B1: 商编 | C1: ASIN | D1: 分组 | E1: 开始推广月份 | F1: 状态 | G1: 近7日 | H1: 前7日 | I1: 环比% | J1: 日均 | K1: FBA可用 | L1: FBA在途 | M1: 海外仓可用 | N1: 海外仓在途 | O1: 本地仓可用 | P1: 采购在途 | Q1: 全链路库存 | R1: 库销比(月)※ | S1: FBA可售天数 | T1: 9月累计 | U1: 月目标 | V1: 达成率% | W1: 目标进度% | X1: 10%市占月目标 | Y1: 近30日销量(FBA) | Z1: 近30日销量(全渠道) | AA1: 10%目标达成% | AB1: 是否已完成10% | AC1: 上月销量 | AD1: 成交价$(折算) | AE1: 界面LP$ | AF1: 红线价$ | AG1: 价格下限$ | AH1: 价格上限$ | AI1: 可降幅度% | AJ1: 降到底毛利率% | AK1: 毛利率%(近30d FBA) | AL1: 促销费率% | AM1: 近30日PV | AN1: 转化率% | AO1: 前28日日均 | AP1: 诊断类型 | AQ1: 等级 | AR1: 改善动作 | AS1: DRI | AT1: 预警
A2: 2026-10-16 | B2: ⚠️ 本页由脚本每日自动覆盖刷新｜销量=FBA口径(该商编下发货模式=FBA的链接出库销量)｜库存=BI日终快照全渠道｜毛利率/成交价=BI损益明细(finance) ASIN级｜成交价=出库销售单价(￥)÷结算汇率6.70，已含coupon/促销｜库销比(月)※=全链路库存÷近30日销量(全渠道)
A3: 2026-10-16 | B3: OO2EWP00400 | C3: B0CKX9SK3Y | D3: 大组 | E3: 9月 | F3: 正常 | G3: 3.0 | H3: 4.0 | I3: -25.0 | J3: 0.43 | K3: 87 | L3: 60 | M3: 8 | N3: 27 | O3: 24 | P3: 120 | Q3: 326 | R3: 9.06 | S3: 203.0 | T3: 7.0 | U3: 15 | V3: 46.7 | W3: 53.3 | X3: 95 | Y3: 13.0 | Z3: 36.0 | AA3: 13.7 | AB3: 未完成 | AC3: 9.0 | AD3: 25.13 | AE3: 22.99 | AF3: 21.21 | AG3: 18.14 | AH3: 22.17 | AI3: 27.8 | AJ3: -10.9 | AK3: 19.9 | AL3: 8.0 | AM3: 581 | AN3: 2.24 | AO3: 0.39 | AP3: 高浏览低转化 | AQ3: P3 | AR3: 产品端：竞对与市场价格核查；运营端：看页面承接与评价 | AS3: 林心园
A4: 2026-10-16 | B4: OO2EWP01300 | C4: B0CKX85NSB | D4: 小组 | E4: — | F4: A-零销量 | G4: 0.0 | H4: 0.0 | J4: 0.0 | K4: 2 | L4: 35 | M4: 15 | N4: 64 | O4: 12 | P4: 128 | Q4: 256 | T4: 0.0 | U4: 12 | V4: 0.0 | W4: 53.3 | X4: 20 | Y4: 0.0 | Z4: 0.0 | AA4: 0.0 | AB4: 未完成 | AC4: 0.0 | AE4: 71.7 | AF4: 54.74 | AG4: 52.46 | AH4: 64.11 | AM4: 82 | AN4: 0.0 | AO4: 0.0 | AT4: ⚫近7日0销量 / 🎯进度落后(0%/53%)
A5: 2026-10-16 | B5: OO2EWP01600 | C5: B0CKX9959W | D5: 大组 | E5: — | F5: D-掉量 | G5: 1.0 | H5: 4.0 | I5: -75.0 | J5: 0.14 | K5: 44 | L5: 20 | M5: 52 | N5: 23 | O5: 29 | P5: 120 | Q5: 288 | R5: 19.2 | S5: 308.0 | T5: 6.0 | U5: 15 | V5: 40.0 | W5: 53.3 | X5: 33 | Y5: 12.0 | Z5: 15.0 | AA5: 36.4 | AB5: 未完成 | AC5: 16.0 | AD5: 25.91 | AE5: 22.07 | AF5: 19.39 | AG5: 19.66 | AH5: 24.03 | AI5: 24.1 | AJ5: 4.2 | AK5: 27.3 | AL5: 8.0 | AM5: 127 | AN5: 9.45 | AO5: 0.46 | AP5: 销量明显下降 | AQ5: P2 | AR5: 运营：查转化与价格、竞对；广告端：查投放是否缩减 | AS5: 林心园 | AT5: 🟡掉量-75%
A6: 2026-10-16 | B6: OO2EWP01800 | C6: B0HJ4NTDXG | D6: 大组 | E6: 9月 | F6: D-掉量 | G6: 1.0 | H6: 3.0 | I6: -66.7 | J6: 0.14 | K6: 4 | L6: 0 | M6: 8 | N6: 11 | O6: 16 | P6: 18 | Q6: 57 | R6: 8.14 | S6: 28.0 | T6: 4.0 | U6: 2 | V6: 200.0 | W6: 53.3 | X6: 26 | Y6: 7.0 | Z6: 7.0 | AA6: 26.9 | AB6: 未完成 | AC6: 4.0 | AD6: 48.01 | AE6: 42.31 | AF6: 42.15 | AG6: 34.59 | AH6: 42.28 | AI6: 28.0 | AJ6: -18.3 | AK6: 14.8 | AL6: 8.0 | AM6: 100 | AN6: 7.0 | AO6: 0.21 | AP6: 断货中风险 | AQ6: P1 | AR6: 运营：确认调价与节奏；供应链：确认最近一批到货时间与数量 | AS6: 林心园 | AT6: 🟡掉量-67%
A7: 2026-10-16 | B7: OO2EWP02000 | C7: B0CKX8PSXX | D7: 大组 | E7: 9月 | F7: D-掉量 | G7: 2.0 | H7: 5.0 | I7: -60.0 | J7: 0.29 | K7: 46 | L7: 20 | M7: 83 | N7: 59 | O7: 82 | P7: 240 | Q7: 530 | R7: 20.38 | S7: 161.0 | T7: 7.0 | U7: 7 | V7: 100.0 | W7: 53.3 | X7: 46 | Y7: 19.0 | Z7: 26.0 | AA7: 41.3 | AB7: 未完成 | AC7: 20.0 | AD7: 22.14 | AE7: 22.07 | AF7: 18.42 | AG7: 20.54 | AH7: 25.11 | AI7: 7.2 | AJ7: 7.7 | AK7: 14.4 | AL7: 7.6 | AM7: 525 | AN7: 3.62 | AO7: 0.71 | AP7: 销量明显下降 | AQ7: P2 | AR7: 运营：查转化与价格、竞对；广告端：查投放是否缩减 | AS7: 林心园 | AT7: 🟡掉量-60%
A8: 2026-10-16 | B8: OO2EWP02100 | C8: B0GWQY9RW4 | D8: 小组 | E8: — | F8: A-零销量 | G8: 0.0 | H8: 1.0 | I8: -100.0 | J8: 0.0 | K8: 5 | L8: 0 | M8: 18 | N8: 8 | O8: 35 | P8: 0 | Q8: 66 | R8: 16.5 | T8: 1.0 | U8: 3 | V8: 33.3 | W8: 53.3 | X8: 19 | Y8: 3.0 | Z8: 4.0 | AA8: 15.8 | AB8: 未完成 | AC8: 3.0 | AD8: 18.08 | AE8: 24.43 | AF8: 22.59 | AG8: 16.72 | AH8: 20.44 | AI8: 7.5 | AJ8: 24.5 | AK8: 30.2 | AL8: 0.0 | AM8: 47 | AN8: 6.38 | AO8: 0.11 | AP8: 低浏览高转化 | AQ8: P3 | AR8: 广告端：放量（加大投放/拓词） | AS8: 林心园 | AT8: ⚫近7日0销量 / 🟡掉量-100% / 🎯进度落后(33%/53%)
A9: 2026-10-16 | B9: OO2EWP03100 | C9: B0GWZNCP7S | D9: 小组 | E9: — | F9: A-零销量 | G9: 0.0 | H9: 0.0 | J9: 0.0 | K9: 9 | L9: 0 | M9: 8 | N9: 26 | O9: 12 | P9: 120 | Q9: 175 | R9: 43.75 | T9: 0.0 | U9: 4 | V9: 0.0 | W9: 53.3 | X9: 16 | Y9: 0.0 | Z9: 4.0 | AA9: 0.0 | AB9: 未完成 | AC9: 0.0 | AE9: 35.87 | AF9: 32.05 | AG9: 34.19 | AH9: 41.79 | AM9: 51 | AN9: 0.0 | AO9: 0.0 | AP9: 滞销风险 | AQ9: P1 | AR9: 运营+推广：促销/降价换量；供应链：缩减海外仓发货计划 | AS9: 林心园 | AT9: ⚫近7日0销量 / 🎯进度落后(0%/53%)
A10: 2026-10-16 | B10: OO2EWP04700 | C10: B0GWZLNY3H | D10: 小组 | E10: 9月 | F10: B-断货风险 | G10: 1.0 | H10: 0.0 | J10: 0.14 | K10: 0 | L10: 0 | M10: 5 | N10: 24 | O10: 56 | P10: 96 | Q10: 181 | R10: 36.2 | S10: 0.0 | T10: 1.0 | U10: 2 | V10: 50.0 | W10: 53.3 | X10: 4 | Y10: 5.0 | Z10: 5.0 | AA10: 125.0 | AB10: ✅ 已完成 | AC10: 10.0 | AD10: 20.39 | AE10: 46.99 | AF10: 35.67 | AG10: 40.76 | AH10: 49.81 | AI10: -99.9 | AK10: 33.2 | AL10: 0.0 | AM10: 126 | AN10: 3.97 | AO10: 0.21 | AP10: 断货高风险 | AQ10: P0 | AR10: 运营：调价控销；供应链：海外仓发货加倍 + 同步最近一批到货时间 | AS10: 林心园 | AT10: 🔴断货风险(0.0天)
A11: 2026-10-16 | B11: OO2EWP05000 | C11: B0GWZKWRT4 | D11: 小组 | E11: 9月 | F11: B-断货风险 | G11: 6.0 | H11: 2.0 | I11: 200.0 | J11: 0.86 | K11: 4 | L11: 0 | M11: 0 | N11: 0 | O11: 14 | P11: 40 | Q11: 58 | R11: 3.41 | S11: 4.7 | T11: 9.0 | U11: 3 | V11: 300.0 | W11: 53.3 | X11: 9 | Y11: 17.0 | Z11: 17.0 | AA11: 188.9 | AB11: ✅ 已完成 | AC11: 9.0 | AD11: 22.88 | AE11: 21.15 | AF11: 20.85 | AG11: 15.81 | AH11: 19.33 | AI11: 30.9 | AJ11: -43.4 | AK11: 0.9 | AL11: 6.7 | AM11: 82 | AN11: 20.73 | AO11: 0.46 | AP11: 断货高风险 | AQ11: P0 | AR11: 运营：控销节奏、暂停加码；供应链：确认在途批量与到货时间 | AS11: 林心园 | AT11: 🔴断货风险(4.7天)
A12: 2026-10-16 | B12: OO2EWP05800 | C12: B0G3LJYFZX | D12: 小组 | E12: 9月 | F12: 正常 | G12: 2.0 | H12: 2.0 | I12: 0.0 | J12: 0.29 | K12: 46 | L12: 4 | M12: 44 | N12: 24 | O12: 98 | P12: 0 | Q12: 216 | R12: 14.4 | S12: 161.0 | T12: 5.0 | U12: 4 | V12: 125.0 | W12: 53.3 | X12: 7 | Y12: 10.0 | Z12: 15.0 | AA12: 142.9 | AB12: ✅ 已完成 | AC12: 9.0 | AD12: 52.91 | AE12: 45.99 | AF12: 43.65 | AG12: 45.97 | AH12: 56.19 | AI12: 13.1 | AJ12: 14.2 | AK12: 25.5 | AL12: 7.2 | AM12: 166 | AN12: 6.02 | AO12: 0.32
A13: 2026-10-16 | B13: OO2EWP05900 | C13: B0GWQLN3LT | D13: 小组 | E13: — | F13: A-零销量 | G13: 0.0 | H13: 0.0 | J13: 0.0 | K13: 24 | L13: 40 | M13: 1 | N13: 36 | O13: 34 | P13: 0 | Q13: 135 | R13: 45.0 | T13: 0.0 | U13: 8 | V13: 0.0 | W13: 53.3 | X13: 8 | Y13: 1.0 | Z13: 3.0 | AA13: 12.5 | AB13: 未完成 | AC13: 7.0 | AD13: 43.63 | AE13: 42.99 | AF13: 31.01 | AG13: 30.86 | AH13: 37.71 | AI13: 29.3 | AJ13: 14.0 | AK13: 39.2 | AL13: 0.0 | AM13: 91 | AN13: 1.1 | AO13: 0.07 | AP13: 滞销风险 | AQ13: P1 | AR13: 运营+推广：促销/降价换量；供应链：缩减海外仓发货计划 | AS13: 林心园 | AT13: ⚫近7日0销量 / 🎯进度落后(0%/53%)
A14: 2026-10-16 | B14: OO2EWP06000 | C14: B0GWQFSGVJ | D14: 小组 | E14: — | F14: F-进度落后 | G14: 2.0 | H14: 0.0 | J14: 0.29 | K14: 43 | L14: 20 | M14: 23 | N14: 5 | O14: 0 | P14: 100 | Q14: 191 | R14: 63.67 | S14: 150.5 | T14: 2.0 | U14: 12 | V14: 16.7 | W14: 53.3 | X14: 10 | Y14: 3.0 | Z14: 3.0 | AA14: 30.0 | AB14: 未完成 | AC14: 7.0 | AD14: 20.03 | AE14: 24.43 | AF14: 18.98 | AG14: 20.24 | AH14: 24.74 | AI14: -1.1 | AK14: 37.8 | AL14: 5.6 | AM14: 67 | AN14: 4.48 | AO14: 0.07 | AT14: 🎯进度落后(17%/53%)
A15: 2026-10-16 | B15: OO2EWP06100 | C15: B0GWZG6T4W | D15: 小组 | E15: — | F15: F-进度落后 | G15: 1.0 | H15: 0.0 | J15: 0.14 | K15: 4 | L15: 2 | M15: 5 | N15: 16 | O15: 52 | P15: 0 | Q15: 79 | R15: 7.9 | S15: 28.0 | T15: 1.0 | U15: 5 | V15: 20.0 | W15: 53.3 | X15: 1 | Y15: 6.0 | Z15: 10.0 | AA15: 600.0 | AB15: ✅ 已完成 | AC15: 8.0 | AD15: 27.06 | AE15: 31.99 | AF15: 23.41 | AG15: 49.46 | AH15: 60.46 | AI15: -82.8 | AK15: 23.2 | AL15: 2.8 | AM15: 87 | AN15: 6.9 | AO15: 0.21 | AP15: 断货中风险 | AQ15: P1 | AR15: 运营：确认调价与节奏；供应链：确认最近一批到货时间与数量 | AS15: 林心园 | AT15: 🎯进度落后(20%/53%)
A16: 2026-10-16 | B16: OO2EWP06600 | C16: B0GWQY1VKB | D16: 小组 | E16: 9月 | F16: 正常 | G16: 2.0 | H16: 0.0 | J16: 0.29 | K16: 11 | L16: 0 | M16: 23 | N16: 9 | O16: 45 | P16: 80 | Q16: 168 | R16: 33.6 | S16: 38.5 | T16: 2.0 | U16: 3 | V16: 66.7 | W16: 53.3 | X16: 13 | Y16: 5.0 | Z16: 5.0 | AA16: 38.5 | AB16: 未完成 | AC16: 9.0 | AD16: 28.45 | AE16: 26.67 | AF16: 21.08 | AG16: 22.08 | AH16: 26.99 | AI16: 22.4 | AJ16: 4.2 | AK16: 25.6 | AL16: 7.3 | AM16: 61 | AN16: 8.2 | AO16: 0.14
A17: 2026-10-16 | B17: OO2EWP06700 | C17: B0GWQWCMPT | D17: 小组 | E17: — | F17: F-进度落后 | G17: 2.0 | H17: 1.0 | I17: 100.0 | J17: 0.29 | K17: 28 | L17: 23 | M17: 35 | N17: 14 | O17: 76 | P17: 60 | Q17: 236 | R17: 33.71 | S17: 98.0 | T17: 3.0 | U17: 15 | V17: 20.0 | W17: 53.3 | X17: 11 | Y17: 6.0 | Z17: 7.0 | AA17: 54.5 | AB17: 未完成 | AC17: 11.0 | AD17: 23.16 | AE17: 25.37 | AF17: 20.24 | AG17: 22.15 | AH17: 27.07 | AI17: 4.4 | AJ17: 14.8 | AK17: 18.5 | AL17: 3.1 | AM17: 67 | AN17: 8.96 | AO17: 0.29 | AT17: 🎯进度落后(20%/53%)
A18: 2026-10-16 | B18: OO2EWP07000 | C18: B0G3LHFPHD | D18: 大组 | E18: 9月 | F18: D-掉量 | G18: 1.0 | H18: 2.0 | I18: -50.0 | J18: 0.14 | K18: 31 | L18: 0 | M18: 5 | N18: 13 | O18: 27 | P18: 100 | Q18: 176 | R18: 14.67 | S18: 217.0 | T18: 3.0 | U18: 12 | V18: 25.0 | W18: 53.3 | X18: 21 | Y18: 4.0 | Z18: 12.0 | AA18: 19.0 | AB18: 未完成 | AC18: 4.0 | AD18: 24.08 | AE18: 22.07 | AF18: 18.44 | AG18: 20.51 | AH18: 25.07 | AI18: 14.8 | AJ18: 9.2 | AK18: 22.6 | AL18: 8.0 | AM18: 143 | AN18: 2.8 | AO18: 0.14 | AP18: 高浏览低转化 | AQ18: P3 | AR18: 产品端：竞对与市场价格核查；运营端：看页面承接与评价 | AS18: 林心园 | AT18: 🟡掉量-50% / 🎯进度落后(25%/53%)
A19: 2026-10-16 | B19: OO2EWP08100 | C19: B0DSW8VBT5 | D19: 小组 | E19: 9月 | F19: 正常 | G19: 4.0 | H19: 5.0 | I19: -20.0 | J19: 0.57 | K19: 12 | L19: 7 | M19: 53 | N19: 28 | O19: 54 | P19: 140 | Q19: 294 | R19: 11.76 | S19: 21.0 | T19: 13.0 | U19: 4 | V19: 325.0 | W19: 53.3 | X19: 12 | Y19: 20.0 | Z19: 25.0 | AA19: 166.7 | AB19: ✅ 已完成 | AC19: 14.0 | AD19: 29.09 | AE19: 29.43 | AF19: 23.39 | AG19: 23.08 | AH19: 28.2 | AI19: 20.7 | AJ19: -2.1 | AK19: 19.0 | AL19: 7.5 | AM19: 195 | AN19: 10.26 | AO19: 0.61 | AP19: 断货中风险 | AQ19: P1 | AR19: 运营：确认调价与节奏；供应链：确认最近一批到货时间与数量 | AS19: 林心园
A20: 2026-10-16 | B20: OO2EWP08200 | C20: B0GWQRW5DS | D20: 小组 | E20: — | F20: A-零销量 | G20: 0.0 | H20: 0.0 | J20: 0.0 | K20: 20 | L20: 20 | M20: 14 | N20: 83 | O20: 1 | P20: 0 | Q20: 138 | R20: 69.0 | T20: 0.0 | U20: 5 | V20: 0.0 | W20: 53.3 | X20: 8 | Y20: 0.0 | Z20: 2.0 | AA20: 0.0 | AB20: 未完成 | AC20: 0.0 | AE20: 32.16 | AF20: 20.32 | AG20: 29.91 | AH20: 36.56 | AM20: 59 | AN20: 0.0 | AO20: 0.0 | AP20: 滞销风险 | AQ20: P1 | AR20: 运营+推广：促销/降价换量；供应链：缩减海外仓发货计划 | AS20: 林心园 | AT20: ⚫近7日0销量 / 🎯进度落后(0%/53%)
A21: 2026-10-16 | B21: OO2EWP08400 | C21: B0GWZRG6FQ | D21: 小组 | E21: — | F21: F-进度落后 | G21: 1.0 | H21: 0.0 | J21: 0.14 | K21: 35 | L21: 20 | M21: 11 | N21: 28 | O21: 23 | P21: 120 | Q21: 237 | R21: 11.85 | S21: 245.0 | T21: 2.0 | U21: 11 | V21: 18.2 | W21: 53.3 | X21: 18 | Y21: 8.0 | Z21: 20.0 | AA21: 44.4 | AB21: 未完成 | AC21: 11.0 | AD21: 25.96 | AE21: 22.99 | AF21: 20.43 | AG21: 19.12 | AH21: 23.37 | AI21: 26.4 | AJ21: 2.3 | AK21: 28.0 | AL21: 7.5 | AM21: 147 | AN21: 5.44 | AO21: 0.36 | AP21: 销量明显下降 | AQ21: P2 | AR21: 运营：查转化与价格、竞对；广告端：查投放是否缩减 | AS21: 林心园 | AT21: 🎯进度落后(18%/53%)
A22: 2026-10-16 | B22: OO2EWP08500 | C22: B0GWQX2NTR | D22: 小组 | E22: — | F22: F-进度落后 | G22: 3.0 | H22: 1.0 | I22: 200.0 | J22: 0.43 | K22: 21 | L22: 1 | M22: 18 | N22: 0 | O22: 33 | P22: 32 | Q22: 105 | R22: 17.5 | S22: 49.0 | T22: 4.0 | U22: 11 | V22: 36.4 | W22: 53.3 | X22: 7 | Y22: 5.0 | Z22: 6.0 | AA22: 71.4 | AB22: 未完成 | AC22: 4.0 | AD22: 29.73 | AE22: 26.67 | AF22: 21.48 | AG22: 25.32 | AH22: 30.95 | AI22: 14.8 | AJ22: 15.0 | AK22: 27.6 | AL22: 8.0 | AM22: 80 | AN22: 6.25 | AO22: 0.14 | AT22: 🎯进度落后(36%/53%)
A23: 2026-10-16 | B23: OO2EWP08600 | C23: B0GWQTZDGZ | D23: 小组 | E23: 9月 | F23: D-掉量 | G23: 1.0 | H23: 4.0 | I23: -75.0 | J23: 0.14 | K23: 19 | L23: 2 | M23: 21 | N23: 10 | O23: 22 | P23: 84 | Q23: 158 | R23: 14.36 | S23: 133.0 | T23: 5.0 | U23: 6 | V23: 83.3 | W23: 53.3 | X23: 11 | Y23: 7.0 | Z23: 11.0 | AA23: 63.6 | AB23: 未完成 | AC23: 8.0 | AD23: 54.21 | AE23: 49.67 | AF23: 45.43 | AG23: 41.88 | AH23: 51.19 | AI23: 22.7 | AJ23: 3.3 | AK23: 25.3 | AL23: 8.0 | AM23: 120 | AN23: 5.83 | AO23: 0.25 | AT23: 🟡掉量-75%
A24: 2026-10-16 | B24: OO2EWP08700 | C24: B0GWZLNVH8 | D24: 小组 | E24: 9月 | F24: F-进度落后 | G24: 1.0 | H24: 0.0 | J24: 0.14 | K24: 10 | L24: 0 | M24: 4 | N24: 2 | O24: 17 | P24: 35 | Q24: 68 | R24: 11.33 | S24: 70.0 | T24: 1.0 | U24: 3 | V24: 33.3 | W24: 53.3 | X24: 3 | Y24: 5.0 | Z24: 6.0 | AA24: 166.7 | AB24: ✅ 已完成 | AC24: 5.0 | AD24: 26.3 | AE24: 23.91 | AF24: 20.13 | AG24: 23.22 | AH24: 28.38 | AI24: 11.7 | AJ24: 34.0 | AK24: 41.7 | AL24: 8.0 | AM24: 49 | AN24: 10.2 | AO24: 0.14 | AP24: 低浏览高转化 | AQ24: P3 | AR24: 广告端：放量（加大投放/拓词） | AS24: 林心园 | AT24: 🎯进度落后(33%/53%)
A25: 2026-10-16 | B25: OO2EWP08900 | C25: B0GWQNW9QC | D25: 小组 | E25: 9月 | F25: A-零销量 | G25: 0.0 | H25: 0.0 | J25: 0.0 | K25: 11 | L25: 2 | M25: 21 | N25: 1 | O25: 29 | P25: 20 | Q25: 84 | R25: 42.0 | T25: 1.0 | U25: 3 | V25: 33.3 | W25: 53.3 | X25: 16 | Y25: 1.0 | Z25: 2.0 | AA25: 6.2 | AB25: 未完成 | AC25: 2.0 | AD25: 24.99 | AE25: 22.99 | AF25: 19.05 | AG25: 21.59 | AH25: 26.39 | AI25: 13.6 | AJ25: 7.8 | AK25: 20.3 | AL25: 8.0 | AM25: 46 | AN25: 2.17 | AO25: 0.04 | AP25: 滞销风险 | AQ25: P1 | AR25: 运营+推广：促销/降价换量；供应链：缩减海外仓发货计划 | AS25: 林心园 | AT25: ⚫近7日0销量 / 🎯进度落后(33%/53%)
A26: 2026-10-16 | B26: OO2EWP10400 | C26: B0GWQKHTNJ | D26: 小组 | E26: 9月 | F26: 正常 | G26: 3.0 | H26: 4.0 | I26: -25.0 | J26: 0.43 | K26: 9 | L26: 0 | M26: 0 | N26: 59 | O26: 21 | P26: 156 | Q26: 245 | R26: 15.31 | S26: 21.0 | T26: 8.0 | U26: 3 | V26: 266.7 | W26: 53.3 | X26: 13 | Y26: 11.0 | Z26: 16.0 | AA26: 84.6 | AB26: 未完成 | AC26: 8.0 | AD26: 33.76 | AE26: 34.03 | AF26: 26.05 | AG26: 33.22 | AH26: 40.6 | AI26: 1.6 | AJ26: 31.5 | AK26: 32.6 | AL26: 7.4 | AM26: 100 | AN26: 11.0 | AO26: 0.29 | AP26: 断货中风险 | AQ26: P1 | AR26: 运营：确认调价与节奏；供应链：确认最近一批到货时间与数量 | AS26: 林心园
A27: 2026-10-16 | B27: OO2EWP11900 | C27: B0GWZH2JVV | D27: 小组 | E27: — | F27: 正常 | G27: 2.0 | H27: 0.0 | J27: 0.29 | K27: 6 | L27: 0 | M27: 1 | N27: 23 | O27: 21 | P27: 18 | Q27: 69 | R27: 7.67 | S27: 21.0 | T27: 2.0 | U27: 4 | V27: 50.0 | W27: 53.3 | X27: 6 | Y27: 8.0 | Z27: 9.0 | AA27: 133.3 | AB27: ✅ 已完成 | AC27: 6.0 | AD27: 58.74 | AE27: 59.79 | AF27: 54.13 | AG27: 49.3 | AH27: 60.25 | AI27: 16.1 | AJ27: -3.7 | AK27: 12.9 | AL27: 9.0 | AM27: 60 | AN27: 13.33 | AO27: 0.21 | AP27: 断货中风险 | AQ27: P1 | AR27: 运营：确认调价与节奏；供应链：确认最近一批到货时间与数量 | AS27: 林心园
A28: 2026-10-16 | B28: OO2EWP12000 | C28: B0GWQSPYL6 | D28: 小组 | E28: 9月 | F28: A-零销量 | G28: 0.0 | H28: 1.0 | I28: -100.0 | J28: 0.0 | K28: 31 | L28: 17 | M28: 15 | N28: 13 | O28: 35 | P28: 0 | Q28: 111 | R28: 22.2 | T28: 1.0 | U28: 2 | V28: 50.0 | W28: 53.3 | X28: 5 | Y28: 1.0 | Z28: 5.0 | AA28: 20.0 | AB28: 未完成 | AC28: 1.0 | AD28: 29.99 | AE28: 26.67 | AF28: 22.42 | AG28: 25.52 | AH28: 31.19 | AI28: 14.9 | AJ28: 5.8 | AK28: 19.8 | AL28: 8.0 | AM28: 87 | AN28: 1.15 | AO28: 0.04 | AP28: 滞销风险 | AQ28: P1 | AR28: 运营+推广：促销/降价换量；供应链：缩减海外仓发货计划 | AS28: 林心园 | AT28: ⚫近7日0销量 / 🟡掉量-100%
A29: 2026-10-16 | B29: OO2EWP12500 | C29: B0FC5MCKB1 | D29: 小组 | E29: — | F29: A-零销量 | G29: 0.0 | H29: 0.0 | J29: 0.0 | K29: 0 | L29: 0 | M29: 11 | N29: 2 | O29: 1 | P29: 24 | Q29: 38 | R29: 7.6 | T29: 0.0 | U29: 1 | V29: 0.0 | W29: 53.3 | X29: 2 | Y29: 0.0 | Z29: 5.0 | AA29: 0.0 | AB29: 未完成 | AC29: 0.0 | AE29: 33.29 | AF29: 16.23 | AM29: 24 | AN29: 0.0 | AO29: 0.0 | AT29: ⚫近7日0销量 / 🎯进度落后(0%/53%)
A30: 2026-10-16 | B30: ZC2CLK02000 | C30: B0DG2D424T | D30: 小组 | E30: — | F30: A-零销量 | G30: 0.0 | H30: 0.0 | J30: 0.0 | K30: 1 | L30: 1 | M30: 14 | N30: 10 | O30: 31 | P30: 20 | Q30: 77 | R30: 77.0 | T30: 0.0 | U30: 2 | V30: 0.0 | W30: 53.3 | X30: 9 | Y30: 0.0 | Z30: 1.0 | AA30: 0.0 | AB30: 未完成 | AC30: 0.0 | AE30: 29.99 | AF30: 21.64 | AG30: 18.16 | AH30: 22.2 | AM30: 13 | AN30: 0.0 | AO30: 0.0 | AP30: 滞销风险 | AQ30: P1 | AR30: 运营+推广：促销/降价换量；供应链：缩减海外仓发货计划 | AS30: 林心园 | AT30: ⚫近7日0销量 / 🎯进度落后(0%/53%)
A31: 2026-10-16 | B31: ZC2CLK04900 | C31: B0GWQVBRBB | D31: 小组 | E31: 9月 | F31: A-零销量 | G31: 0.0 | H31: 0.0 | J31: 0.0 | K31: 15 | L31: 0 | M31: 19 | N31: 12 | O31: 67 | P31: 20 | Q31: 133 | R31: 22.17 | T31: 1.0 | U31: 3 | V31: 33.3 | W31: 53.3 | X31: 14 | Y31: 1.0 | Z31: 6.0 | AA31: 7.1 | AB31: 未完成 | AC31: 3.0 | AD31: 38.99 | AE31: 35.87 | AF31: 22.2 | AG31: 35.05 | AH31: 42.84 | AI31: 10.1 | AJ31: 31.4 | AK31: 38.3 | AL31: 8.0 | AM31: 113 | AN31: 0.88 | AO31: 0.04 | AP31: 滞销风险 | AQ31: P1 | AR31: 运营+推广：促销/降价换量；供应链：缩减海外仓发货计划 | AS31: 林心园 | AT31: ⚫近7日0销量 / 🎯进度落后(33%/53%)
A32: 2026-10-16 | B32: ZC2CLK05300 | C32: B0GWR5G1FG | D32: 小组 | E32: — | F32: A-零销量 | G32: 0.0 | H32: 0.0 | J32: 0.0 | K32: 34 | L32: 18 | M32: 36 | N32: 7 | O32: 60 | P32: 60 | Q32: 215 | R32: 23.89 | T32: 0.0 | U32: 10 | V32: 0.0 | W32: 53.3 | X32: 13 | Y32: 3.0 | Z32: 9.0 | AA32: 23.1 | AB32: 未完成 | AC32: 14.0 | AD32: 35.9 | AE32: 44.15 | AF32: 36.03 | AG32: 33.2 | AH32: 40.58 | AI32: 7.5 | AJ32: -42.5 | AK32: -31.8 | AL32: 7.5 | AM32: 161 | AN32: 1.86 | AO32: 0.14 | AP32: 高浏览低转化 | AQ32: P3 | AR32: 产品端：竞对与市场价格核查；运营端：看页面承接与评价 | AS32: 林心园 | AT32: ⚫近7日0销量 / 🎯进度落后(0%/53%)
A34: 【近14日销量矩阵】出库口径 | B34: 2026-10-03 | C34: 2026-10-04 | D34: 2026-10-05 | E34: 2026-10-06 | F34: 2026-10-07 | G34: 2026-10-08 | H34: 2026-10-09 | I34: 2026-10-10 | J34: 2026-10-11 | K34: 2026-10-12 | L34: 2026-10-13 | M34: 2026-10-14 | N34: 2026-10-15 | O34: 2026-10-16 | P34: 合计
A35: OO2EWP00400 | B35: B0CKX9SK3Y | C35: 1.0 | D35: 0.0 | E35: 1.0 | F35: 0.0 | G35: 1.0 | H35: 1.0 | I35: 0.0 | J35: 1.0 | K35: 0.0 | L35: 2.0 | M35: 0.0 | N35: 0.0 | O35: 0.0 | P35: 0.0 | Q35: 7.0
A36: OO2EWP01300 | B36: B0CKX85NSB | C36: 0.0 | D36: 0.0 | E36: 0.0 | F36: 0.0 | G36: 0.0 | H36: 0.0 | I36: 0.0 | J36: 0.0 | K36: 0.0 | L36: 0.0 | M36: 0.0 | N36: 0.0 | O36: 0.0 | P36: 0.0 | Q36: 0.0
A37: OO2EWP01600 | B37: B0CKX9959W | C37: 1.0 | D37: 0.0 | E37: 0.0 | F37: 2.0 | G37: 1.0 | H37: 0.0 | I37: 0.0 | J37: 0.0 | K37: 0.0 | L37: 1.0 | M37: 0.0 | N37: 0.0 | O37: 0.0 | P37: 0.0 | Q37: 5.0
A38: OO2EWP01800 | B38: B0HJ4NTDXG | C38: 0.0 | D38: 1.0 | E38: 1.0 | F38: 0.0 | G38: 1.0 | H38: 0.0 | I38: 0.0 | J38: 0.0 | K38: 0.0 | L38: 0.0 | M38: 0.0 | N38: 1.0 | O38: 0.0 | P38: 0.0 | Q38: 4.0
A39: OO2EWP02000 | B39: B0CKX8PSXX | C39: 0.0 | D39: 0.0 | E39: 0.0 | F39: 2.0 | G39: 2.0 | H39: 1.0 | I39: 0.0 | J39: 0.0 | K39: 0.0 | L39: 0.0 | M39: 1.0 | N39: 1.0 | O39: 0.0 | P39: 0.0 | Q39: 7.0
A40: OO2EWP02100 | B40: B0GWQY9RW4 | C40: 0.0 | D40: 0.0 | E40: 0.0 | F40: 0.0 | G40: 1.0 | H40: 0.0 | I40: 0.0 | J40: 0.0 | K40: 0.0 | L40: 0.0 | M40: 0.0 | N40: 0.0 | O40: 0.0 | P40: 0.0 | Q40: 1.0
A41: OO2EWP03100 | B41: B0GWZNCP7S | C41: 0.0 | D41: 0.0 | E41: 0.0 | F41: 0.0 | G41: 0.0 | H41: 0.0 | I41: 0.0 | J41: 0.0 | K41: 0.0 | L41: 0.0 | M41: 0.0 | N41: 0.0 | O41: 0.0 | P41: 0.0 | Q41: 0.0
A42: OO2EWP04700 | B42: B0GWZLNY3H | C42: 0.0 | D42: 0.0 | E42: 0.0 | F42: 0.0 | G42: 0.0 | H42: 0.0 | I42: 1.0 | J42: 0.0 | K42: 0.0 | L42: 0.0 | M42: 0.0 | N42: 0.0 | O42: 0.0 | P42: 0.0 | Q42: 1.0
A43: OO2EWP05000 | B43: B0GWZKWRT4 | C43: 0.0 | D43: 0.0 | E43: 1.0 | F43: 0.0 | G43: 0.0 | H43: 0.0 | I43: 1.0 | J43: 0.0 | K43: 1.0 | L43: 1.0 | M43: 2.0 | N43: 1.0 | O43: 0.0 | P43: 0.0 | Q43: 7.0
A44: OO2EWP05800 | B44: B0G3LJYFZX | C44: 0.0 | D44: 1.0 | E44: 0.0 | F44: 0.0 | G44: 0.0 | H44: 0.0 | I44: 0.0 | J44: 0.0 | K44: 1.0 | L44: 1.0 | M44: 0.0 | N44: 0.0 | O44: 0.0 | P44: 0.0 | Q44: 3.0
A45: OO2EWP05900 | B45: B0GWQLN3LT | C45: 0.0 | D45: 0.0 | E45: 0.0 | F45: 0.0 | G45: 0.0 | H45: 0.0 | I45: 0.0 | J45: 0.0 | K45: 0.0 | L45: 0.0 | M45: 0.0 | N45: 0.0 | O45: 0.0 | P45: 0.0 | Q45: 0.0
A46: OO2EWP06000 | B46: B0GWQFSGVJ | C46: 0.0 | D46: 0.0 | E46: 0.0 | F46: 0.0 | G46: 0.0 | H46: 0.0 | I46: 0.0 | J46: 1.0 | K46: 1.0 | L46: 0.0 | M46: 0.0 | N46: 0.0 | O46: 0.0 | P46: 0.0 | Q46: 2.0
... A64: ZC2CLK05300 | B64: B0GWR5G1FG | C64: 0.0 | D64: 0.0 | E64: 0.0 | F64: 0.0 | G64: 0.0 | H64: 0.0 | I64: 0.0 | J64: 0.0 | K64: 0.0 | L64: 0.0 | M64: 0.0 | N64: 0.0 | O64: 0.0 | P64: 0.0 | Q64: 0.0
A66: 【ASIN 经营异常闭环台账】诊断顺序：库存→流量→转化→价格｜DRI=林心园｜状态机：待通知→已通知→已回复→处理中→已验证→CLOSED/REOPENED
A67: 异常ID | B67: 等级 | C67: ASIN | D67: 商编 | E67: 分组 | F67: 异常类型 | G67: 异常事实 | H67: 基准值 | I67: 当前值 | J67: 经营影响 | K67: 原因判断 | L67: 置信度 | M67: DRI | N67: 改善动作 | O67: 截止时间 | P67: 验收标准 | Q67: 当前状态
A68: ASIN-001 | B68: P0 | C68: B0GWZKWRT4 | D68: OO2EWP05000 | E68: 小组 | F68: 断货高风险 | G68: FBA可售仅 4.7 天（FBA可用 4 件，近7日卖 6 件） | H68: ≥ 14 天 | I68: 4.7 天 | J68: 一周内断货，推广会断档 | K68: 补货不足 / 销量突增 | L68: 置信度A | M68: 林心园 | N68: 运营：控销节奏、暂停加码；供应链：确认在途批量与到货时间 | O68: 当天 | P68: FBA可售 ≥ 14 天 | Q68: 待通知
A69: ASIN-002 | B69: P0 | C69: B0GWZLNY3H | D69: OO2EWP04700 | E69: 小组 | F69: 断货高风险 | G69: FBA可用=0，近30日仍卖 5 件 | H69: FBA可用 ≥ 7日销量 | I69: FBA可用=0 | J69: 需求在但无货可卖，推广投入打水漂 | K69: 断货（非需求问题） | L69: 置信度A | M69: 林心园 | N69: 运营：调价控销；供应链：海外仓发货加倍 + 同步最近一批到货时间 | O69: 当天 | P69: FBA可售 ≥ 14 天 | Q69: 待通知
A70: ASIN-003 | B70: P1 | C70: B0DSW8VBT5 | D70: OO2EWP08100 | E70: 小组 | F70: 断货中风险 | G70: FBA可用仅 12 件（可售 21.0 天），近30日卖 20 件 | H70: FBA可用 ≥ 30日销量(20) | I70: FBA可用 12 件 | J70: 库存跟不上当前动销，随时断货 | K70: 补货节奏滞后 / 动销超预期 | L70: 置信度A | M70: 林心园 | N70: 运营：确认调价与节奏；供应链：确认最近一批到货时间与数量 | O70: 本周内 | P70: FBA可售 ≥ 14 天 | Q70: 待通知
A71: ASIN-004 | B71: P1 | C71: B0GWQKHTNJ | D71: OO2EWP10400 | E71: 小组 | F71: 断货中风险 | G71: FBA可用仅 9 件（可售 21.0 天），近30日卖 11 件 | H71: FBA可用 ≥ 30日销量(11) | I71: FBA可用 9 件 | J71: 库存跟不上当前动销，随时断货 | K71: 补货节奏滞后 / 动销超预期 | L71: 置信度A | M71: 林心园 | N71: 运营：确认调价与节奏；供应链：确认最近一批到货时间与数量 | O71: 本周内 | P71: FBA可售 ≥ 14 天 | Q71: 待通知
A72: ASIN-005 | B72: P1 | C72: B0GWZH2JVV | D72: OO2EWP11900 | E72: 小组 | F72: 断货中风险 | G72: FBA可用仅 6 件（可售 21.0 天），近30日卖 8 件 | H72: FBA可用 ≥ 30日销量(8) | I72: FBA可用 6 件 | J72: 库存跟不上当前动销，随时断货 | K72: 补货节奏滞后 / 动销超预期 | L72: 置信度A | M72: 林心园 | N72: 运营：确认调价与节奏；供应链：确认最近一批到货时间与数量 | O72: 本周内 | P72: FBA可售 ≥ 14 天 | Q72: 待通知
A73: ASIN-006 | B73: P1 | C73: B0HJ4NTDXG | D73: OO2EWP01800 | E73: 大组 | F73: 断货中风险 | G73: FBA可用仅 4 件（可售 28.0 天），近30日卖 7 件 | H73: FBA可用 ≥ 30日销量(7) | I73: FBA可用 4 件 | J73: 库存跟不上当前动销，随时断货 | K73: 补货节奏滞后 / 动销超预期 | L73: 置信度A | M73: 林心园 | N73: 运营：确认调价与节奏；供应链：确认最近一批到货时间与数量 | O73: 本周内 | P73: FBA可售 ≥ 14 天 | Q73: 待通知
A74: ASIN-007 | B74: P1 | C74: B0GWZG6T4W | D74: OO2EWP06100 | E74: 小组 | F74: 断货中风险 | G74: FBA可用仅 4 件（可售 28.0 天），近30日卖 6 件 | H74: FBA可用 ≥ 30日销量(6) | I74: FBA可用 4 件 | J74: 库存跟不上当前动销，随时断货 | K74: 补货节奏滞后 / 动销超预期 | L74: 置信度A | M74: 林心园 | N74: 运营：确认调价与节奏；供应链：确认最近一批到货时间与数量 | O74: 本周内 | P74: FBA可售 ≥ 14 天 | Q74: 待通知
A75: ASIN-008 | B75: P1 | C75: B0GWQLN3LT | D75: OO2EWP05900 | E75: 小组 | F75: 滞销风险 | G75: 近7日 0 销量，近30日仅 1 件，库销比 45.0 月 | H75: 近7日 ≥ 1 件 | I75: 0 件 | J75: 库存占用，仓储费累积 | K75: 推广未起量（待验证：价格 / 流量 / 转化） | L75: 置信度A | M75: 林心园 | N75: 运营+推广：促销/降价换量；供应链：缩减海外仓发货计划 | O75: 本周内 | P75: 近7日 ≥ 1 件 | Q75: 待通知
A76: ASIN-009 | B76: P1 | C76: B0GWQVBRBB | D76: ZC2CLK04900 | E76: 小组 | F76: 滞销风险 | G76: 近7日 0 销量，近30日仅 1 件，库销比 22.17 月 | H76: 近7日 ≥ 1 件 | I76: 0 件 | J76: 库存占用，仓储费累积 | K76: 推广未起量（待验证：价格 / 流量 / 转化） | L76: 置信度A | M76: 林心园 | N76: 运营+推广：促销/降价换量；供应链：缩减海外仓发货计划 | O76: 本周内 | P76: 近7日 ≥ 1 件 | Q76: 待通知
A77: ASIN-010 | B77: P1 | C77: B0GWQNW9QC | D77: OO2EWP08900 | E77: 小组 | F77: 滞销风险 | G77: 近7日 0 销量，近30日仅 1 件，库销比 42.0 月 | H77: 近7日 ≥ 1 件 | I77: 0 件 | J77: 库存占用，仓储费累积 | K77: 推广未起量（待验证：价格 / 流量 / 转化） | L77: 置信度A | M77: 林心园 | N77: 运营+推广：促销/降价换量；供应链：缩减海外仓发货计划 | O77: 本周内 | P77: 近7日 ≥ 1 件 | Q77: 待通知
A78: ASIN-011 | B78: P1 | C78: B0GWQSPYL6 | D78: OO2EWP12000 | E78: 小组 | F78: 滞销风险 | G78: 近7日 0 销量，近30日仅 1 件，库销比 22.2 月 | H78: 近7日 ≥ 1 件 | I78: 0 件 | J78: 库存占用，仓储费累积 | K78: 推广未起量（待验证：价格 / 流量 / 转化） | L78: 置信度A | M78: 林心园 | N78: 运营+推广：促销/降价换量；供应链：缩减海外仓发货计划 | O78: 本周内 | P78: 近7日 ≥ 1 件 | Q78: 待通知
... A89: ASIN-022 | B89: P3 | C89: B0GWR5G1FG | D89: ZC2CLK05300 | E89: 小组 | F89: 高浏览低转化 | G89: 近30日PV 161（≥中位 87），转化率 1.9%（< 中位×0.6 = 3.6%） | H89: 转化率中位 6.0% | I89: 1.9% | J89: 流量没被承接，浪费曝光 | K89: 待验证：价格偏高 / 页面承接 / 评价 | L89: 置信度B | M89: 林心园 | N89: 产品端：竞对与市场价格核查；运营端：看页面承接与评价 | O89: 持续观察 | P89: 转化率 ≥ 品类中位 | Q89: 待通知
A91: 【降价换量机会】低销 · 高毛 · 未达10%市占目标｜成交价=BI出库销售单价(￥)÷6.70（已含coupon/促销）｜建议降幅=min(守住毛利底线18%可降幅度， 距价格下限空间)｜降后毛利率=(m−p)/(1−p)
A92: 商编 | B92: ASIN | C92: 当前成交价$(折算) | D92: 建议价$ | E92: 建议降幅% | F92: 当前毛利率% | G92: 降后毛利率% | H92: 约束 | I92: 价格下限$ | J92: 界面LP$ | K92: 近7日 | L92: 近30日 | M92: 10%市占月目标
A93: OO2EWP05900 | B93: B0GWQLN3LT | C93: 43.63 | D93: 32.36 | E93: 25.8 | F93: 39.2 | G93: 18.0 | H93: ⚠️受毛利底线约束 | I93: 30.86 | J93: 42.99 | K93: 0 | L93: 1 | M93: 8
A94: OO2EWP08400 | B94: B0GWZRG6FQ | C94: 25.96 | D94: 22.79 | E94: 12.2 | F94: 28.0 | G94: 18.0 | H94: ⚠️受毛利底线约束 | I94: 19.12 | J94: 22.99 | K94: 1 | L94: 8 | M94: 18
A95: OO2EWP08500 | B95: B0GWQX2NTR | C95: 29.73 | D95: 26.24 | E95: 11.7 | F95: 27.6 | G95: 18.0 | H95: ⚠️受毛利底线约束 | I95: 25.32 | J95: 26.67 | K95: 3 | L95: 5 | M95: 7
A96: OO2EWP01600 | B96: B0CKX9959W | C96: 25.91 | D96: 22.97 | E96: 11.3 | F96: 27.3 | G96: 18.0 | H96: ⚠️受毛利底线约束 | I96: 19.66 | J96: 22.07 | K96: 1 | L96: 12 | M96: 33
A97: ZC2CLK04900 | B97: B0GWQVBRBB | C97: 38.99 | D97: 35.05 | E97: 10.1 | F97: 38.3 | G97: 31.4 | H97: 可降到下限 | I97: 35.05 | J97: 35.87 | K97: 0 | L97: 1 | M97: 14
A98: OO2EWP06600 | B98: B0GWQY1VKB | C98: 28.45 | D98: 25.8 | E98: 9.3 | F98: 25.6 | G98: 18.0 | H98: ⚠️受毛利底线约束 | I98: 22.08 | J98: 26.67 | K98: 2 | L98: 5 | M98: 13
A99: OO2EWP08600 | B99: B0GWQTZDGZ | C99: 54.21 | D99: 49.41 | E99: 8.8 | F99: 25.3 | G99: 18.0 | H99: ⚠️受毛利底线约束 | I99: 41.88 | J99: 49.67 | K99: 1 | L99: 7 | M99: 11
A100: OO2EWP02100 | B100: B0GWQY9RW4 | C100: 18.08 | D100: 16.72 | E100: 7.5 | F100: 30.2 | G100: 24.5 | H100: 可降到下限 | I100: 16.72 | J100: 24.43 | K100: 0 | L100: 3 | M100: 19
A101: OO2EWP07000 | B101: B0G3LHFPHD | C101: 24.08 | D101: 22.72 | E101: 5.7 | F101: 22.6 | G101: 18.0 | H101: ⚠️受毛利底线约束 | I101: 20.51 | J101: 22.07 | K101: 1 | L101: 4 | M101: 21

Sheet 潜力
A1: 商品编码 | B1: PT品牌asin | C1: 平台商品编码 | D1: 发货方式 | E1: 平台SKU状态 | F1: 新/老品 | G1: Q2 bcg（asin） | H1: Q3 bcg（asin） | I1: bcg（商编维度） | J1: 当前界面list price | K1: 红线价 | L1: 中心价 | M1: 价格下限 | N1: 价格上限 | O1: 4月销量 | P1: 5月销量 | Q1: 6月销量 | R1: 7月销量 | S1: 8月销量 | T1: 9月销量 | U1: 10月销量（截至10.4） | V1: p1考核销量目标 | W1: 9月销量达标进度 | X1: Q2毛利率 | Y1: Q3毛利率 | Z1: 9月毛利率 | AA1: 9月退款率 | AB1: 9月广告费率 | AC1: 9月促销费率 | AD1: 9月转化率 | AE1: 9月广告转化率 | AF1: FBA可用 | AG1: FBA可售 | AH1: FBA在途 | AI1: 海外仓可用库存 | AJ1: 海外仓在途库存 | AK1: Q2市场月均销量 | AL1: Q3市场月均销量 | AM1: Q2月均销量 | AN1: Q3月均销量 | AO1: PT Q2asin市占 | AP1: PT Q3asin市占 | AQ1: 销量目标到10% | AR1: 202609目标 | AS1: 202610目标 | AT1: 202611目标 | AU1: 202612目标 | AV1: 202701目标 | AW1: 202702目标 | AX1: 分组（以组销200分界） | AY1: 开始推广月份 | AZ1: 链接质量检测得分 | BA1: 备注（实际执行情况）
A2: OO2EWP05800 | B2: B0G3LJYFZX | C2: 6114EWP058CUS | D2: FBA | E2: 维稳 | F2: 老品 | G2: 潜力 | H2: 明星 | I2: 明星 | J2: =49.99*0.92 -> 45.9908 | K2: 43.65 | L2: 51.08 | M2: 45.97 | N2: 56.19 | O2: 0 | P2: 3 | Q2: 12 | R2: 15 | S2: 3 | T2: 10 | U2: 4 | V2: 11 | W2: =T2/V2 -> 0.90909091 | X2: 0.243 | Y2: 0.20699482 | Z2: 0.39243854 | AA2: 0.10731844 | AB2: 0.021167429 | AC2: 0.040896758 | AD2: 0.14492754 | AE2: 0.11741438 | AF2: =_xlfn.XLOOKUP(B2,库存明细报表10.16!L:L,库存明细报表10.16!P:P) -> 46 | AG2: =_xlfn.XLOOKUP(B2,库存明细报表10.16!L:L,库存明细报表10.16!Q:Q) -> 38 | AH2: =_xlfn.XLOOKUP(B2,库存明细报表10.16!L:L,库存明细报表10.16!T:T) -> 4 | AI2: =VLOOKUP(A:A,进销存报表10.16!A:J,10,0) -> 44 | AJ2: =VLOOKUP(A:A,进销存报表10.16!A:K,11,0) -> 24 | AK2: 68.51 | AL2: 42.92 | AM2: 5.33 | AN2: 9 | AO2: =AM2/AK2 -> 0.077798861 | AP2: =AN2/AL2 -> 0.20969245 | AQ2: =ROUNDUP(AK2*10%,0) -> 7 | AR2: 4 | AS2: 6 | AT2: =AS2*1.5 -> 9 | AU2: 11 | AV2: 12 | AW2: 15 | AX2: 小组 | AY2: 9月 | AZ2: =VLOOKUP(B:B,链接质量检测!A:V,22,0) -> 97 | BA2: 8月下滑-8月初即将断货，降低促销后销量下滑
A3: OO2EWP07000 | B3: B0G3LHFPHD | C3: 7009EWP070JUS | D3: FBA | E3: 维稳 | F3: 老品 | G3: 潜力 | H3: 瘦狗 | I3: 潜力 | J3: =23.99*0.92 -> 22.0708 | K3: 18.44 | L3: 22.79 | M3: 20.51 | N3: 25.07 | O3: 0 | P3: 4 | Q3: 4 | R3: 18 | S3: 10 | T3: 2 | U3: 3 | V3: 16 | W3: =T3/V3 -> 0.125 | X3: 0.216 | Y3: 0.14171206 | Z3: -0.18193169 | AA3: 0.32199459 | AB3: 0.17575055 | AC3: 0.056392115 | AD3: 0.035714286 | AE3: 0.10234494 | AF3: =_xlfn.XLOOKUP(B3,库存明细报表10.16!L:L,库存明细报表10.16!P:P) -> 31 | AG3: =_xlfn.XLOOKUP(B3,库存明细报表10.16!L:L,库存明细报表10.16!Q:Q) -> 14 | AH3: =_xlfn.XLOOKUP(B3,库存明细报表10.16!L:L,库存明细报表10.16!T:T) -> 0 | AI3: =VLOOKUP(A:A,进销存报表10.16!A:J,10,0) -> 5 | AJ3: =VLOOKUP(A:A,进销存报表10.16!A:K,11,0) -> 13 | AK3: 201.99 | AL3: 119.35 | AM3: 2.67 | AN3: 11 | AO3: =AM3/AK3 -> 0.013218476 | AP3: =AN3/AL3 -> 0.092165899 | AQ3: =ROUNDUP(AK3*10%,0) -> 21 | AR3: 12 | AS3: 12 | AT3: 15 | AU3: 16 | AV3: 17 | AW3: 21 | AX3: 大组 | AY3: 9月 | AZ3: =VLOOKUP(B:B,链接质量检测!A:V,22,0) -> 97 | BA3: 8月下滑-8月库存不足有小幅涨价，期间coupon中断过
A4: OO2EWP02000 | B4: B0CKX8PSXX | C4: 2100EWP020ZUS | D4: FBA | E4: 维稳 | F4: 老品 | G4: 潜力 | H4: 瘦狗 | I4: 潜力 | J4: =23.99*0.92 -> 22.0708 | K4: 18.42 | L4: 22.83 | M4: 20.54 | N4: 25.11 | O4: 10 | P4: 6 | Q4: 21 | R4: 19 | S4: 7 | T4: 19 | U4: 8 | V4: 28 | W4: =T4/V4 -> 0.67857143 | X4: 0.255 | Y4: 0.057603836 | Z4: -0.03076376 | AA4: 0.15626385 | AB4: 0.071610239 | AC4: 0.071021779 | AD4: 0.048969072 | AE4: 0.085500004 | AF4: =_xlfn.XLOOKUP(B4,库存明细报表10.16!L:L,库存明细报表10.16!P:P) -> 26 | AG4: =_xlfn.XLOOKUP(B4,库存明细报表10.16!L:L,库存明细报表10.16!Q:Q) -> 22 | AH4: =_xlfn.XLOOKUP(B4,库存明细报表10.16!L:L,库存明细报表10.16!T:T) -> 20 | AI4: =VLOOKUP(A:A,进销存报表10.16!A:J,10,0) -> 83 | AJ4: =VLOOKUP(A:A,进销存报表10.16!A:K,11,0) -> 59 | AK4: 452.27 | AL4: 324.08 | AM4: 9.67 | AN4: 18 | AO4: =AM4/AK4 -> 0.021381033 | AP4: =AN4/AL4 -> 0.055541842 | AQ4: =ROUNDUP(AK4*10%,0) -> 46 | AR4: 7 | AS4: 14 | AT4: 21 | AU4: 28 | AV4: 37 | AW4: 46 | AX4: 大组 | AY4: 9月 | AZ4: =VLOOKUP(B:B,链接质量检测!A:V,22,0) -> 97 | BA4: 6、7月份大多是PO出单，价格和利润相对较低，后期转FBA价格相对较高，销量有所下滑
A5: OO2EWP00400 | B5: B0CKX9SK3Y | C5: 8753EWP0043US | D5: FBA | E5: 维稳 | F5: 老品 | G5: 潜力 | H5: 瘦狗 | I5: 潜力 | J5: =24.99*0.92 -> 22.9908 | K5: 21.21 | L5: 20.15 | M5: 18.14 | N5: 22.17 | O5: 16 | P5: 10 | Q5: 10 | R5: 21 | S5: 7 | T5: 10 | U5: 7 | V5: 35 | W5: =T5/V5 -> 0.28571429 | X5: 0.235 | Y5: 0.1891784 | Z5: 0.074141481 | AA5: 0.10980346 | AB5: 0.11878702 | AC5: 0.068156981 | AD5: 0.029761905 | AE5: 0.065627557 | AF5: =_xlfn.XLOOKUP(B5,库存明细报表10.16!L:L,库存明细报表10.16!P:P) -> 47 | AG5: =_xlfn.XLOOKUP(B5,库存明细报表10.16!L:L,库存明细报表10.16!Q:Q) -> 46 | AH5: =_xlfn.XLOOKUP(B5,库存明细报表10.16!L:L,库存明细报表10.16!T:T) -> 60 | AI5: =VLOOKUP(A:A,进销存报表10.16!A:J,10,0) -> 8 | AJ5: =VLOOKUP(A:A,进销存报表10.16!A:K,11,0) -> 27 | AK5: 947.59 | AL5: 838.05 | AM5: 11.67 | AN5: 13.333333 | AO5: =AM5/AK5 -> 0.012315453 | AP5: =AN5/AL5 -> 0.01590995 | AQ5: =ROUNDUP(AK5*10%,0) -> 95 | AR5: 15 | AS5: 23 | AT5: 30 | AU5: 35 | AV5: 46 | AW5: 60 | AX5: 大组 | AY5: 9月 | AZ5: =VLOOKUP(B:B,链接质量检测!A:V,22,0) -> 97 | BA5: 7月底库存较低有进行过涨价操作，8月销量下滑，目前库存恢复
A6: OO2EWP01600 | B6: B0CKX9959W | C6: 8703EWP016ZUS | D6: FBA | E6: 维稳 | F6: 老品 | G6: 潜力 | H6: 潜力 | I6: 潜力 | J6: =23.99*0.92 -> 22.0708 | K6: 19.39 | L6: 21.84 | M6: 19.66 | N6: 24.03 | O6: 3 | P6: 4 | Q6: 3 | R6: 22 | S6: 20 | T6: 16 | U6: 5 | V6: 20 | W6: =T6/V6 -> 0.8 | X6: 0.297 | Y6: 0.2197321 | Z6: 0.23201475 | AA6: 0 | AB6: 0.046243748 | AC6: 0.083852331 | AD6: 0.12121212 | AE6: 0.10231112 | AF6: =_xlfn.XLOOKUP(B6,库存明细报表10.16!L:L,库存明细报表10.16!P:P) -> 44 | AG6: =_xlfn.XLOOKUP(B6,库存明细报表10.16!L:L,库存明细报表10.16!Q:Q) -> 17 | AH6: =_xlfn.XLOOKUP(B6,库存明细报表10.16!L:L,库存明细报表10.16!T:T) -> 20 | AI6: =VLOOKUP(A:A,进销存报表10.16!A:J,10,0) -> 52 | AJ6: =VLOOKUP(A:A,进销存报表10.16!A:K,11,0) -> 23 | AK6: 320.08 | AL6: 239.53 | AM6: 3.67 | AN6: 19.666667 | AO6: =AM6/AK6 -> 0.011465884 | AP6: =AN6/AL6 -> 0.082105234 | AQ6: =ROUNDUP(AK6*10%,0) -> 33 | AR6: 15 | AS6: 15 | AT6: 15 | AU6: 20 | AV6: 27 | AW6: 33 | AX6: 大组 | AZ6: =VLOOKUP(B:B,链接质量检测!A:V,22,0) -> 97
A7: OO2EWP08100 | B7: B0DSW8VBT5 | C7: 1753EWP081HUS | D7: FBA | E7: 维稳 | F7: 老品 | G7: 潜力 | H7: 明星 | I7: 潜力 | J7: =31.99*0.92 -> 29.4308 | K7: 23.39 | L7: 25.64 | M7: 23.08 | N7: 28.2 | O7: 0 | P7: 1 | Q7: 7 | R7: 7 | S7: 9 | T7: 17 | U7: 8 | V7: 10 | W7: =T7/V7 -> 1.7 | X7: 0.321 | Y7: 0.21564095 | Z7: 0.20614158 | AA7: 0 | AB7: 0.078417363 | AC7: 0.083846562 | AD7: 0.14049587 | AE7: 0.1187757 | AF7: =_xlfn.XLOOKUP(B7,库存明细报表10.16!L:L,库存明细报表10.16!P:P) -> 10 | AG7: =_xlfn.XLOOKUP(B7,库存明细报表10.16!L:L,库存明细报表10.16!Q:Q) -> 9 | AH7: =_xlfn.XLOOKUP(B7,库存明细报表10.16!L:L,库存明细报表10.16!T:T) -> 7 | AI7: =VLOOKUP(A:A,进销存报表10.16!A:J,10,0) -> 53 | AJ7: =VLOOKUP(A:A,进销存报表10.16!A:K,11,0) -> 28 | AK7: 110.96 | AL7: 52.31 | AM7: 2.67 | AN7: 10.333333 | AO7: =AM7/AK7 -> 0.024062725 | AP7: =AN7/AL7 -> 0.1975403 | AQ7: =ROUNDUP(AK7*10%,0) -> 12 | AR7: 4 | AS7: 5 | AT7: 6 | AU7: 8 | AV7: 10 | AW7: 12 | AX7: 小组 | AY7: 9月 | AZ7: =VLOOKUP(B:B,链接质量检测!A:V,22,0) -> 89
A8: OO2EWP08500 | B8: B0GWQX2NTR | C8: 9973EWP085JUS | D8: FBA | E8: 维稳 | F8: 老品 | G8: 潜力 | H8: 明星 | I8: 潜力 | J8: =28.99*0.92 -> 26.6708 | K8: 21.48 | L8: 28.14 | M8: 25.32 | N8: 30.95 | O8: 0 | P8: 2 | Q8: 2 | R8: 10 | S8: 8 | T8: 4 | U8: 4 | V8: 13 | W8: =T8/V8 -> 0.30769231 | X8: 0.358 | Y8: 0.27017427 | Z8: 0.3290419 | AA8: 0 | AB8: 0.053588441 | AC8: 0.083846994 | AD8: 0.11111111 | AE8: 0 | AF8: =_xlfn.XLOOKUP(B8,库存明细报表10.16!L:L,库存明细报表10.16!P:P) -> 8 | AG8: =_xlfn.XLOOKUP(B8,库存明细报表10.16!L:L,库存明细报表10.16!Q:Q) -> 8 | AH8: =_xlfn.XLOOKUP(B8,库存明细报表10.16!L:L,库存明细报表10.16!T:T) -> 1 | AI8: =VLOOKUP(A:A,进销存报表10.16!A:J,10,0) -> 18 | AJ8: =VLOOKUP(A:A,进销存报表10.16!A:K,11,0) -> 0 | AK8: 67.58 | AL8: 51.7 | AM8: 1.33 | AN8: 7.3333333 | AO8: =AM8/AK8 -> 0.019680379 | AP8: =AN8/AL8 -> 0.14184397 | AQ8: =ROUNDUP(AK8*10%,0) -> 7 | AR8: 11 | AS8: 11 | AT8: 12 | AU8: 13 | AV8: 14 | AW8: 15 | AX8: 小组 | AZ8: =VLOOKUP(B:B,链接质量检测!A:V,22,0) -> 97
A9: OO2EWP06100 | B9: B0GWZG6T4W | C9: 4365EWP061CUS | D9: FBA | E9: 维稳 | F9: 老品 | G9: 潜力 | H9: 金牛 | I9: 明星 | J9: =31.99 -> 31.99 | K9: 23.41 | L9: 54.96 | M9: 49.46 | N9: 60.46 | O9: 0 | P9: 1 | Q9: 0 | R9: 6 | S9: 4 | T9: 6 | U9: 2 | V9: 6 | W9: =T9/V9 -> 1 | X9: 0.225 | Y9: 0.10375858 | Z9: 0.2754715 | AA9: 0.13477452 | AB9: 0.042677824 | AC9: 0.045244127 | AD9: 0.18181818 | AE9: 0.24928278 | AF9: =_xlfn.XLOOKUP(B9,库存明细报表10.16!L:L,库存明细报表10.16!P:P) -> 2 | AG9: =_xlfn.XLOOKUP(B9,库存明细报表10.16!L:L,库存明细报表10.16!Q:Q) -> 2 | AH9: =_xlfn.XLOOKUP(B9,库存明细报表10.16!L:L,库存明细报表10.16!T:T) -> 2 | AI9: =VLOOKUP(A:A,进销存报表10.16!A:J,10,0) -> 5 | AJ9: =VLOOKUP(A:A,进销存报表10.16!A:K,11,0) -> 16 | AK9: 9.34 | AL9: 12.92 | AM9: 0.33 | AN9: 6.3333333 | AO9: =AM9/AK9 -> 0.035331906 | AP9: =AN9/AL9 -> 0.49019608 | AQ9: =ROUNDUP(AK9*10%,0) -> 1 | AR9: 5 | AS9: 5 | AT9: 6 | AU9: 6 | AV9: 7 | AW9: 7 | AX9: 小组 | AZ9: =VLOOKUP(B:B,链接质量检测!A:V,22,0) -> 81
A10: OO2EWP01800 | B10: B0HJ4NTDXG | C10: 4892EWP018PUS | D10: FBA | E10: 风险 | F10: 老品 | G10: 潜力 | H10: 瘦狗 | I10: 潜力 | J10: =45.99*0.92 -> 42.3108 | K10: 42.15 | L10: 38.44 | M10: 34.59 | N10: 42.28 | O10: 0 | P10: 2 | Q10: 3 | R10: 1 | S10: 0 | T10: 3 | U10: 3 | V10: #N/A | W10: =IF(T10>V10,"YES","NO") -> #N/A | X10: 0.222 | Y10: 0.06153889 | Z10: 0.13648205 | AA10: 0 | AB10: 0.050568643 | AC10: 0.08383781 | AD10: 0.15789474 | AE10: 0.13289077 | AF10: =_xlfn.XLOOKUP(B10,库存明细报表10.16!L:L,库存明细报表10.16!P:P) -> 4 | AG10: =_xlfn.XLOOKUP(B10,库存明细报表10.16!L:L,库存明细报表10.16!Q:Q) -> 3 | AH10: =_xlfn.XLOOKUP(B10,库存明细报表10.16!L:L,库存明细报表10.16!T:T) -> 0 | AI10: =VLOOKUP(A:A,进销存报表10.16!A:J,10,0) -> 8 | AJ10: =VLOOKUP(A:A,进销存报表10.16!A:K,11,0) -> 11 | AK10: 252.62 | AL10: 161.38 | AM10: 1.67 | AN10: 2 | AO10: =AM10/AK10 -> 0.0066107197 | AP10: =AN10/AL10 -> 0.012393109 | AQ10: =ROUNDUP(AK10*10%,0) -> 26 | AR10: 2 | AS10: 3 | AT10: 4 | AU10: 5 | AV10: 8 | AW10: 12 | AX10: 大组 | AY10: 9月 | AZ10: =VLOOKUP(B:B,链接质量检测!A:V,22,0) -> 89 | BA10: 8月初断货，目前刚到货，且库存较低
A11: OO2EWP03100 | B11: B0GWZNCP7S | C11: 6070EWP0315US | D11: FBA | E11: 维稳 | F11: 老品 | G11: 潜力 | H11: 瘦狗 | I11: 潜力 | J11: =38.99*0.92 -> 35.8708 | K11: 32.05 | L11: 37.99 | M11: 34.19 | N11: 41.79 | O11: 0 | P11: 0 | Q11: 1 | R11: 7 | S11: 2 | T11: 0 | U11: 1 | V11: 10 | W11: =T11/V11 -> 0 | X11: 0.231 | Y11: 0.16010831 | Z11: 0 | AA11: 0 | AB11: #DIV/0! | AC11: #DIV/0! | AD11: 0 | AE11: 0 | AF11: =_xlfn.XLOOKUP(B11,库存明细报表10.16!L:L,库存明细报表10.16!P:P) -> 9 | AG11: =_xlfn.XLOOKUP(B11,库存明细报表10.16!L:L,库存明细报表10.16!Q:Q) -> 0 | AH11: =_xlfn.XLOOKUP(B11,库存明细报表10.16!L:L,库存明细报表10.16!T:T) -> 0 | AI11: =VLOOKUP(A:A,进销存报表10.16!A:J,10,0) -> 8 | AJ11: =VLOOKUP(A:A,进销存报表10.16!A:K,11,0) -> 26 | AK11: 155.92 | AL11: 123.99 | AM11: 0.33 | AN11: 3.3333333 | AO11: =AM11/AK11 -> 0.00211647 | AP11: =AN11/AL11 -> 0.026883888 | AQ11: =ROUNDUP(AK11*10%,0) -> 16 | AR11: 4 | AS11: 5 | AT11: 8 | AU11: 10 | AV11: 13 | AW11: 16 | AX11: 小组 | AZ11: =VLOOKUP(B:B,链接质量检测!A:V,22,0) -> 97
A12: OO2EWP06600 | B12: B0GWQY1VKB | C12: 8525EWP0665US | D12: FBA | E12: 维稳 | F12: 老品 | G12: 潜力 | H12: 潜力 | I12: 瘦狗 | J12: =28.99*0.92 -> 26.6708 | K12: 21.08 | L12: 24.54 | M12: 22.08 | N12: 26.99 | O12: 0 | P12: 4 | Q12: 0 | R12: 3 | S12: 1 | T12: 9 | U12: 2 | V12: 10 | W12: =T12/V12 -> 0.9 | X12: 0.208 | Y12: 0.21657343 | Z12: 0.23684707 | AA12: 0 | AB12: 0.028860527 | AC12: 0.070511208 | AD12: 0.20930233 | AE12: 0.23026062 | AF12: =_xlfn.XLOOKUP(B12,库存明细报表10.16!L:L,库存明细报表10.16!P:P) -> 11 | AG12: =_xlfn.XLOOKUP(B12,库存明细报表10.16!L:L,库存明细报表10.16!Q:Q) -> 11 | AH12: =_xlfn.XLOOKUP(B12,库存明细报表10.16!L:L,库存明细报表10.16!T:T) -> 0 | AI12: =VLOOKUP(A:A,进销存报表10.16!A:J,10,0) -> 23 | AJ12: =VLOOKUP(A:A,进销存报表10.16!A:K,11,0) -> 9 | AK12: 127.73 | AL12: 97.31 | AM12: 1.33 | AN12: 4.3333333 | AO12: =AM12/AK12 -> 0.010412589 | AP12: =AN12/AL12 -> 0.044531223 | AQ12: =ROUNDUP(AK12*10%,0) -> 13 | AR12: 3 | AS12: 4 | AT12: 6 | AU12: 8 | AV12: 11 | AW12: 13 | AX12: 小组 | AY12: 9月 | AZ12: =VLOOKUP(B:B,链接质量检测!A:V,22,0) -> 97
A13: OO2EWP08600 | B13: B0GWQTZDGZ | C13: 4633EWP0866US | D13: FBA | E13: 维稳 | F13: 老品 | G13: 潜力 | H13: 瘦狗 | I13: 瘦狗 | J13: =53.99*0.92 -> 49.6708 | K13: 45.43 | L13: 46.54 | M13: 41.88 | N13: 51.19 | O13: 0 | P13: 1 | Q13: 0 | R13: 6 | S13: 5 | T13: 8 | U13: 6 | V13: 10 | W13: =T13/V13 -> 0.8 | X13: 0.275 | Y13: 0.19843972 | Z13: 0.18035891 | AA13: 0.25225266 | AB13: 0.023269959 | AC13: 0.051037269 | AD13: 0.15384615 | AE13: 0.15349244 | AF13: =_xlfn.XLOOKUP(B13,库存明细报表10.16!L:L,库存明细报表10.16!P:P) -> 17 | AG13: =_xlfn.XLOOKUP(B13,库存明细报表10.16!L:L,库存明细报表10.16!Q:Q) -> 6 | AH13: =_xlfn.XLOOKUP(B13,库存明细报表10.16!L:L,库存明细报表10.16!T:T) -> 2 | AI13: =VLOOKUP(A:A,进销存报表10.16!A:J,10,0) -> 21 | AJ13: =VLOOKUP(A:A,进销存报表10.16!A:K,11,0) -> 10 | AK13: 107.6 | AL13: 85.99 | AM13: 0.33 | AN13: 6.6666667 | AO13: =AM13/AK13 -> 0.0030669145 | AP13: =AN13/AL13 -> 0.077528395 | AQ13: =ROUNDUP(AK13*10%,0) -> 11 | AR13: 6 | AS13: 6 | AT13: 7 | AU13: 8 | AV13: 9 | AW13: 11 | AX13: 小组 | AY13: 9月 | AZ13: =VLOOKUP(B:B,链接质量检测!A:V,22,0) -> 97
A14: OO2EWP05900 | B14: B0GWQLN3LT | C14: 2193EWP059HUS | D14: FBA | E14: 维稳 | F14: 老品 | G14: 潜力 | H14: 明星 | I14: 潜力 | J14: =42.99 -> 42.99 | K14: 31.01 | L14: 34.28 | M14: 30.86 | N14: 37.71 | O14: 0 | P14: 1 | Q14: 1 | R14: 7 | S14: 15 | T14: 6 | U14: 1 | V14: 11 | W14: =T14/V14 -> 0.54545455 | X14: 0.331 | Y14: 0.23030727 | Z14: 0.28549064 | AA14: 0.1639088 | AB14: 0.018758579 | AC14: 0.043168824 | AD14: 0.11111111 | AE14: 0.14260555 | AF14: =_xlfn.XLOOKUP(B14,库存明细报表10.16!L:L,库存明细报表10.16!P:P) -> 0 | AG14: =_xlfn.XLOOKUP(B14,库存明细报表10.16!L:L,库存明细报表10.16!Q:Q) -> 0 | AH14: =_xlfn.XLOOKUP(B14,库存明细报表10.16!L:L,库存明细报表10.16!T:T) -> 40 | AI14: =VLOOKUP(A:A,进销存报表10.16!A:J,10,0) -> 1 | AJ14: =VLOOKUP(A:A,进销存报表10.16!A:K,11,0) -> 36 | AK14: 72.93 | AL14: 60.29 | AM14: 0.67 | AN14: 9.6666667 | AO14: =AM14/AK14 -> 0.0091868915 | AP14: =AN14/AL14 -> 0.16033615 | AQ14: =ROUNDUP(AK14*10%,0) -> 8 | AR14: 8 | AS14: 11 | AT14: 11 | AU14: 11 | AV14: 12 | AW14: 13 | AX14: 小组 | AZ14: =VLOOKUP(B:B,链接质量检测!A:V,22,0) -> 89
A15: ZC2CLK04900 | B15: B0GWQVBRBB | C15: 6936CLK0491US | D15: FBA | E15: 维稳 | F15: 老品 | G15: 潜力 | H15: 潜力 | I15: 潜力 | J15: =38.99*0.92 -> 35.8708 | K15: 22.2 | L15: 38.95 | M15: 35.05 | N15: 42.84 | O15: 0 | P15: 0 | Q15: 1 | R15: 1 | S15: 1 | T15: 4 | U15: 0 | V15: 10 | W15: =T15/V15 -> 0.4 | X15: 0.384 | Y15: 0.30951289 | Z15: 0.31383031 | AA15: 0 | AB15: 0.065070493 | AC15: 0.083824903 | AD15: 0.11764706 | AE15: 0.10696505 | AF15: =_xlfn.XLOOKUP(B15,库存明细报表10.16!L:L,库存明细报表10.16!P:P) -> 15 | AG15: =_xlfn.XLOOKUP(B15,库存明细报表10.16!L:L,库存明细报表10.16!Q:Q) -> 14 | AH15: =_xlfn.XLOOKUP(B15,库存明细报表10.16!L:L,库存明细报表10.16!T:T) -> 0 | AI15: =VLOOKUP(A:A,进销存报表10.16!A:J,10,0) -> 19 | AJ15: =VLOOKUP(A:A,进销存报表10.16!A:K,11,0) -> 12 | AK15: 131.47 | AL15: 90.4 | AM15: 0.33 | AN15: 1.6666667 | AO15: =AM15/AK15 -> 0.0025100783 | AP15: =AN15/AL15 -> 0.018436578 | AQ15: =ROUNDUP(AK15*10%,0) -> 14 | AR15: 3 | AS15: 5 | AT15: 7 | AU15: 9 | AV15: 12 | AW15: 14 | AX15: 小组 | AY15: 9月 | AZ15: =VLOOKUP(B:B,链接质量检测!A:V,22,0) -> 97 | BA15: 历史销量较低，6.7月份均只出一单
A16: OO2EWP08400 | B16: B0GWZRG6FQ | C16: 5033EWP084GUS | D16: FBA | E16: 维稳 | F16: 老品 | G16: 潜力 | H16: 潜力 | I16: 潜力 | J16: =24.99*0.92 -> 22.9908 | K16: 20.43 | L16: 21.24 | M16: 19.12 | N16: 23.37 | O16: 0 | P16: 0 | Q16: 5 | R16: 4 | S16: 10 | T16: 11 | U16: 1 | V16: 14 | W16: =T16/V16 -> 0.78571429 | X16: 0.229 | Y16: 0.20939489 | Z16: 0.14386674 | AA16: 0.19267571 | AB16: 0.014318166 | AC16: 0.06088771 | AD16: 0.2037037 | AE16: 0.22170855 | AF16: =_xlfn.XLOOKUP(B16,库存明细报表10.16!L:L,库存明细报表10.16!P:P) -> 15 | AG16: =_xlfn.XLOOKUP(B16,库存明细报表10.16!L:L,库存明细报表10.16!Q:Q) -> 14 | AH16: =_xlfn.XLOOKUP(B16,库存明细报表10.16!L:L,库存明细报表10.16!T:T) -> 20 | AI16: =VLOOKUP(A:A,进销存报表10.16!A:J,10,0) -> 11 | AJ16: =VLOOKUP(A:A,进销存报表10.16!A:K,11,0) -> 28 | AK16: 176.38 | AL16: 142.47 | AM16: 1.33 | AN16: 9.3333333 | AO16: =AM16/AK16 -> 0.0075405375 | AP16: =AN16/AL16 -> 0.065510868 | AQ16: =ROUNDUP(AK16*10%,0) -> 18 | AR16: 11 | AS16: 12 | AT16: 13 | AU16: 14 | AV16: 15 | AW16: 18 | AX16: 小组 | AZ16: =VLOOKUP(B:B,链接质量检测!A:V,22,0) -> 97
A17: OO2EWP05000 | B17: B0GWZKWRT4 | C17: 6571EWP050XUS | D17: FBA | E17: 维稳 | F17: 老品 | G17: 潜力 | H17: 瘦狗 | I17: 潜力 | J17: =22.99*0.92 -> 21.1508 | K17: 20.85 | L17: 17.57 | M17: 15.81 | N17: 19.33 | O17: 0 | P17: 0 | Q17: 1 | R17: 0 | S17: 4 | T17: 8 | U17: 9 | V17: 10 | W17: =T17/V17 -> 0.8 | X17: 0.347 | Y17: 0.088299283 | Z17: 0.004619175 | AA17: 0.12622019 | AB17: 0.071438978 | AC17: 0.073755017 | AD17: 0.1038961 | AE17: 0.083134443 | AF17: =_xlfn.XLOOKUP(B17,库存明细报表10.16!L:L,库存明细报表10.16!P:P) -> 4 | AG17: =_xlfn.XLOOKUP(B17,库存明细报表10.16!L:L,库存明细报表10.16!Q:Q) -> 4 | AH17: =_xlfn.XLOOKUP(B17,库存明细报表10.16!L:L,库存明细报表10.16!T:T) -> 0 | AI17: =VLOOKUP(A:A,进销存报表10.16!A:J,10,0) -> 0 | AJ17: =VLOOKUP(A:A,进销存报表10.16!A:K,11,0) -> 0 | AK17: 89.74 | AL17: 62.2 | AM17: 0.33 | AN17: 4.6666667 | AO17: =AM17/AK17 -> 0.0036772899 | AP17: =AN17/AL17 -> 0.075026795 | AQ17: =ROUNDUP(AK17*10%,0) -> 9 | AR17: 3 | AS17: 3 | AT17: 5 | AU17: 6 | AV17: 8 | AW17: 9 | AX17: 小组 | AY17: 9月 | AZ17: =VLOOKUP(B:B,链接质量检测!A:V,22,0) -> 89
A18: OO2EWP06000 | B18: B0GWQFSGVJ | C18: 3666EWP0603US | D18: FBA | E18: 维稳 | F18: 老品 | G18: 潜力 | H18: 明星 | I18: 潜力 | J18: =25.99*0.94 -> 24.4306 | K18: 18.98 | L18: 22.49 | M18: 20.24 | N18: 24.74 | O18: 0 | P18: 2 | Q18: 3 | R18: 3 | S18: 13 | T18: 5 | U18: 1 | V18: 14 | W18: =T18/V18 -> 0.35714286 | X18: 0.29 | Y18: 0.29609919 | Z18: 0.33211584 | AA18: 0 | AB18: 0.03214543 | AC18: 0.07964042 | AD18: 0.047619048 | AE18: 0.099710023 | AF18: =_xlfn.XLOOKUP(B18,库存明细报表10.16!L:L,库存明细报表10.16!P:P) -> 23 | AG18: =_xlfn.XLOOKUP(B18,库存明细报表10.16!L:L,库存明细报表10.16!Q:Q) -> 3 | AH18: =_xlfn.XLOOKUP(B18,库存明细报表10.16!L:L,库存明细报表10.16!T:T) -> 20 | AI18: =VLOOKUP(A:A,进销存报表10.16!A:J,10,0) -> 23 | AJ18: =VLOOKUP(A:A,进销存报表10.16!A:K,11,0) -> 5 | AK18: 99.86 | AL18: 64.92 | AM18: 1.33 | AN18: 7.6666667 | AO18: =AM18/AK18 -> 0.013318646 | AP18: =AN18/AL18 -> 0.11809406 | AQ18: =ROUNDUP(AK18*10%,0) -> 10 | AR18: 12 | AS18: 13 | AT18: 13 | AU18: 14 | AV18: 14 | AW18: 14 | AX18: 小组 | AZ18: =VLOOKUP(B:B,链接质量检测!A:V,22,0) -> 97
A19: OO2EWP10400 | B19: B0GWQKHTNJ | C19: 4702EWP104MUS | D19: FBA | E19: 维稳 | F19: 老品 | G19: 潜力 | H19: 瘦狗 | I19: 潜力 | J19: =36.99*0.92 -> 34.0308 | K19: 26.05 | L19: 36.91 | M19: 33.22 | N19: 40.6 | O19: 0 | P19: 0 | Q19: 5 | R19: 12 | S19: 3 | T19: 8 | U19: 6 | V19: 10 | W19: =T19/V19 -> 0.8 | X19: 0.275 | Y19: 0.1003237 | Z19: 0.15880766 | AA19: 0.25539724 | AB19: 0.071747265 | AC19: 0.04660364 | AD19: 0.16 | AE19: 0.080834751 | AF19: =_xlfn.XLOOKUP(B19,库存明细报表10.16!L:L,库存明细报表10.16!P:P) -> 9 | AG19: =_xlfn.XLOOKUP(B19,库存明细报表10.16!L:L,库存明细报表10.16!Q:Q) -> 9 | AH19: =_xlfn.XLOOKUP(B19,库存明细报表10.16!L:L,库存明细报表10.16!T:T) -> 0 | AI19: =VLOOKUP(A:A,进销存报表10.16!A:J,10,0) -> 0 | AJ19: =VLOOKUP(A:A,进销存报表10.16!A:K,11,0) -> 59 | AK19: 125.64 | AL19: 120.76 | AM19: 1.67 | AN19: 8 | AO19: =AM19/AK19 -> 0.013291945 | AP19: =AN19/AL19 -> 0.066247102 | AQ19: =ROUNDUP(AK19*10%,0) -> 13 | AR19: 3 | AS19: 4 | AT19: 6 | AU19: 8 | AV19: 11 | AW19: 13 | AX19: 小组 | AY19: 9月 | AZ19: =VLOOKUP(B:B,链接质量检测!A:V,22,0) -> 97
A20: OO2EWP04700 | B20: B0GWZLNY3H | C20: 9699EWP047ZUS | D20: FBA | E20: 风险 | F20: 老品 | G20: 潜力 | H20: 明星 | I20: 金牛 | J20: 46.99 | K20: 35.67 | L20: 45.28 | M20: 40.76 | N20: 49.81 | O20: 0 | P20: 1 | Q20: 2 | R20: 9 | S20: 1 | T20: 7 | U20: 1 | V20: #N/A | W20: =IF(T20>V20,"YES","NO") -> #N/A | X20: 0.332 | Y20: 0.23484554 | Z20: 0.17640463 | AA20: 0.13956188 | AB20: 0.013482945 | AC20: 0.059747497 | AD20: 0.08974359 | AE20: 0.076789009 | AF20: =_xlfn.XLOOKUP(B20,库存明细报表10.16!L:L,库存明细报表10.16!P:P) -> #N/A | AG20: =_xlfn.XLOOKUP(B20,库存明细报表10.16!L:L,库存明细报表10.16!Q:Q) -> #N/A | AH20: =_xlfn.XLOOKUP(B20,库存明细报表10.16!L:L,库存明细报表10.16!T:T) -> #N/A | AI20: =VLOOKUP(A:A,进销存报表10.16!A:J,10,0) -> 5 | AJ20: =VLOOKUP(A:A,进销存报表10.16!A:K,11,0) -> 24 | AK20: 30.74 | AL20: 33.76 | AM20: 1 | AN20: 7 | AO20: =AM20/AK20 -> 0.032530904 | AP20: =AN20/AL20 -> 0.20734597 | AQ20: =ROUNDUP(AK20*10%,0) -> 4 | AR20: 2 | AS20: 2 | AT20: 2 | AU20: 3 | AV20: 4 | AW20: 4 | AX20: 小组 | AY20: 9月 | AZ20: =VLOOKUP(B:B,链接质量检测!A:V,22,0) -> 97
A21: OO2EWP08700 | B21: B0GWZLNVH8 | C21: 5409EWP087HUS | D21: FBA | E21: 风险 | F21: 老品 | G21: 潜力 | H21: 金牛 | I21: 明星 | J21: =25.99*0.92 -> 23.9108 | K21: 20.13 | L21: 25.8 | M21: 23.22 | N21: 28.38 | O21: 0 | P21: 0 | Q21: 1 | R21: 0 | S21: 4 | T21: 5 | U21: 1 | V21: #N/A | W21: =IF(T21>V21,"YES","NO") -> #N/A | X21: 0.345 | Y21: 0.12526249 | Z21: 0.080482841 | AA21: 0.18749511 | AB21: 0.031731145 | AC21: 0.068846975 | AD21: 0.22727273 | AE21: 0.22167585 | AF21: =_xlfn.XLOOKUP(B21,库存明细报表10.16!L:L,库存明细报表10.16!P:P) -> 10 | AG21: =_xlfn.XLOOKUP(B21,库存明细报表10.16!L:L,库存明细报表10.16!Q:Q) -> 9 | AH21: =_xlfn.XLOOKUP(B21,库存明细报表10.16!L:L,库存明细报表10.16!T:T) -> 0 | AI21: =VLOOKUP(A:A,进销存报表10.16!A:J,10,0) -> 4 | AJ21: =VLOOKUP(A:A,进销存报表10.16!A:K,11,0) -> 2 | AK21: 23.45 | AL21: 14.07 | AM21: 0.33 | AN21: 3 | AO21: =AM21/AK21 -> 0.014072495 | AP21: =AN21/AL21 -> 0.21321962 | AQ21: =ROUNDUP(AK21*10%,0) -> 3 | AR21: 3 | AS21: 3 | AT21: 3 | AU21: 4 | AV21: 4 | AW21: 4 | AX21: 小组 | AY21: 9月 | AZ21: =VLOOKUP(B:B,链接质量检测!A:V,22,0) -> 97
A22: OO2EWP08900 | B22: B0GWQNW9QC | C22: 3328EWP089HUS | D22: FBA | E22: 维稳 | F22: 老品 | G22: 潜力 | H22: 瘦狗 | I22: 潜力 | J22: =24.99*0.92 -> 22.9908 | K22: 19.05 | L22: 23.99 | M22: 21.59 | N22: 26.39 | O22: 0 | P22: 0 | Q22: 1 | R22: 1 | S22: 1 | T22: 2 | U22: 1 | V22: 10 | W22: =T22/V22 -> 0.2 | X22: 0.31 | Y22: 0.088390617 | Z22: 0.062125706 | AA22: 0 | AB22: 0.084433774 | AC22: 0.083853506 | AD22: 0.095238095 | AE22: 0.036980607 | AF22: =_xlfn.XLOOKUP(B22,库存明细报表10.16!L:L,库存明细报表10.16!P:P) -> 11 | AG22: =_xlfn.XLOOKUP(B22,库存明细报表10.16!L:L,库存明细报表10.16!Q:Q) -> 10 | AH22: =_xlfn.XLOOKUP(B22,库存明细报表10.16!L:L,库存明细报表10.16!T:T) -> 2 | AI22: =VLOOKUP(A:A,进销存报表10.16!A:J,10,0) -> 21 | AJ22: =VLOOKUP(A:A,进销存报表10.16!A:K,11,0) -> 1 | AK22: 153.58 | AL22: 115.22 | AM22: 0.33 | AN22: 1.3333333 | AO22: =AM22/AK22 -> 0.0021487173 | AP22: =AN22/AL22 -> 0.011572065 | AQ22: =ROUNDUP(AK22*10%,0) -> 16 | AR22: 3 | AS22: 5 | AT22: 8 | AU22: 10 | AV22: 13 | AW22: 16 | AX22: 小组 | AY22: 9月 | AZ22: =VLOOKUP(B:B,链接质量检测!A:V,22,0) -> 97 | BA22: 历史销量较低，6.7月份均只出一单
A23: OO2EWP02100 | B23: B0GWQY9RW4 | C23: 9087EWP021RUS | D23: FBA | E23: 风险 | F23: 老品 | G23: 潜力 | H23: 瘦狗 | I23: 潜力 | J23: =25.99*0.94 -> 24.4306 | K23: 22.59 | L23: 18.58 | M23: 16.72 | N23: 20.44 | O23: 0 | P23: 0 | Q23: 2 | R23: 1 | S23: 7 | T23: 2 | U23: 0 | V23: 12 | W23: =T23/V23 -> 0.16666667 | X23: 0.284 | Y23: 0.049795808 | Z23: 0.24754104 | AA23: 0 | AB23: 0.04546355 | AC23: 0.024383773 | AD23: 0.05 | AE23: 0.1246411 | AF23: =_xlfn.XLOOKUP(B23,库存明细报表10.16!L:L,库存明细报表10.16!P:P) -> 5 | AG23: =_xlfn.XLOOKUP(B23,库存明细报表10.16!L:L,库存明细报表10.16!Q:Q) -> 1 | AH23: =_xlfn.XLOOKUP(B23,库存明细报表10.16!L:L,库存明细报表10.16!T:T) -> 0 | AI23: =VLOOKUP(A:A,进销存报表10.16!A:J,10,0) -> 18 | AJ23: =VLOOKUP(A:A,进销存报表10.16!A:K,11,0) -> 8 | AK23: 189.31 | AL23: 164.27 | AM23: 0.67 | AN23: 4.6666667 | AO23: =AM23/AK23 -> 0.0035391686 | AP23: =AN23/AL23 -> 0.028408514 | AQ23: =ROUNDUP(AK23*10%,0) -> 19 | AR23: 3 | AS23: 7 | AT23: 9 | AU23: 12 | AV23: 16 | AW23: 19 | AX23: 小组 | AZ23: =VLOOKUP(B:B,链接质量检测!A:V,22,0) -> 89 | BA23: 目前FBA可用库存较低
A24: ZC2CLK05300 | B24: B0GWR5G1FG | C24: 9951CLK053VUS | D24: FBA | E24: 维稳 | F24: 老品 | G24: 潜力 | H24: 金牛 | I24: 潜力 | J24: =47.99*0.92 -> 44.1508 | K24: 36.03 | L24: 36.89 | M24: 33.2 | N24: 40.58 | O24: 0 | P24: 2 | Q24: 5 | R24: 4 | S24: 9 | T24: 12 | U24: 0 | V24: 11 | W24: =T24/V24 -> 1.0909091 | X24: 0.317 | Y24: 0.14774242 | Z24: 0.12256968 | AA24: 0.24589277 | AB24: 0.00703394 | AC24: 0.056272771 | AD24: 0.087591241 | AE24: 0.39914232 | AF24: =_xlfn.XLOOKUP(B24,库存明细报表10.16!L:L,库存明细报表10.16!P:P) -> 22 | AG24: =_xlfn.XLOOKUP(B24,库存明细报表10.16!L:L,库存明细报表10.16!Q:Q) -> 22 | AH24: =_xlfn.XLOOKUP(B24,库存明细报表10.16!L:L,库存明细报表10.16!T:T) -> 18 | AI24: =VLOOKUP(A:A,进销存报表10.16!A:J,10,0) -> 36 | AJ24: =VLOOKUP(A:A,进销存报表10.16!A:K,11,0) -> 7 | AK24: 129.61 | AL24: 88.24 | AM24: 2 | AN24: 9.3333333 | AO24: =AM24/AK24 -> 0.015430908 | AP24: =AN24/AL24 -> 0.10577214 | AQ24: =ROUNDUP(AK24*10%,0) -> 13 | AR24: 10 | AS24: 10 | AT24: 10 | AU24: 11 | AV24: 13 | AW24: 13 | AX24: 小组 | AZ24: =VLOOKUP(B:B,链接质量检测!A:V,22,0) -> 89
A25: OO2EWP08200 | B25: B0GWQRW5DS | C25: 8050EWP082GUS | D25: FBA | E25: 维稳 | F25: 老品 | G25: 潜力 | H25: 潜力 | I25: 明星 | J25: =32.16 -> 32.16 | K25: 20.32 | L25: 33.24 | M25: 29.91 | N25: 36.56 | O25: 0 | P25: 1 | Q25: 2 | R25: 5 | S25: 5 | T25: 2 | U25: 2 | V25: 6 | W25: =T25/V25 -> 0.33333333 | X25: 0.204 | Y25: 0.31508666 | Z25: 0.34515489 | AA25: 0 | AB25: 0 | AC25: 0 | AD25: 0.11111111 | AE25: #DIV/0! | AF25: =_xlfn.XLOOKUP(B25,库存明细报表10.16!L:L,库存明细报表10.16!P:P) -> 0 | AG25: =_xlfn.XLOOKUP(B25,库存明细报表10.16!L:L,库存明细报表10.16!Q:Q) -> 0 | AH25: =_xlfn.XLOOKUP(B25,库存明细报表10.16!L:L,库存明细报表10.16!T:T) -> 20 | AI25: =VLOOKUP(A:A,进销存报表10.16!A:J,10,0) -> 14 | AJ25: =VLOOKUP(A:A,进销存报表10.16!A:K,11,0) -> 83 | AK25: 78.55 | AL25: 51.24 | AM25: 1 | AN25: 3.3333333 | AO25: =AM25/AK25 -> 0.012730745 | AP25: =AN25/AL25 -> 0.065053344 | AQ25: =ROUNDUP(AK25*10%,0) -> 8 | AR25: 5 | AS25: 5 | AT25: 6 | AU25: 6 | AV25: 7 | AW25: 8 | AX25: 小组 | AZ25: =VLOOKUP(B:B,链接质量检测!A:V,22,0) -> 97
A26: OO2EWP12000 | B26: B0GWQSPYL6 | C26: 8948EWP1204US | D26: FBA | E26: 维稳 | F26: 老品 | G26: 潜力 | H26: 瘦狗 | I26: 明星 | J26: =28.99*0.92 -> 26.6708 | K26: 22.42 | L26: 28.36 | M26: 25.52 | N26: 31.19 | O26: 0 | P26: 1 | Q26: 0 | R26: 3 | S26: 2 | T26: 1 | U26: 1 | V26: #N/A | W26: =IF(T26>V26,"YES","NO") -> #N/A | X26: 0.255 | Y26: 0.12104269 | Z26: -0.059893165 | AA26: 0 | AB26: 0.2354118 | AC26: 0.083848185 | AD26: 0.034482759 | AE26: 0 | AF26: =_xlfn.XLOOKUP(B26,库存明细报表10.16!L:L,库存明细报表10.16!P:P) -> 21 | AG26: =_xlfn.XLOOKUP(B26,库存明细报表10.16!L:L,库存明细报表10.16!Q:Q) -> 14 | AH26: =_xlfn.XLOOKUP(B26,库存明细报表10.16!L:L,库存明细报表10.16!T:T) -> 17 | AI26: =VLOOKUP(A:A,进销存报表10.16!A:J,10,0) -> 15 | AJ26: =VLOOKUP(A:A,进销存报表10.16!A:K,11,0) -> 13 | AK26: 42.26 | AL26: 27.83 | AM26: 0.33 | AN26: 2 | AO26: =AM26/AK26 -> 0.0078088027 | AP26: =AN26/AL26 -> 0.071864894 | AQ26: =ROUNDUP(AK26*10%,0) -> 5 | AR26: 2 | AS26: 2 | AT26: 3 | AU26: 3 | AV26: 4 | AW26: 5 | AX26: 小组 | AY26: 9月 | AZ26: =VLOOKUP(B:B,链接质量检测!A:V,22,0) -> 97
A27: OO2EWP06700 | B27: B0GWQWCMPT | C27: 5900EWP0675US | D27: FBA | E27: 维稳 | F27: 老品 | G27: 潜力 | H27: 明星 | I27: 潜力 | J27: =26.99*0.94 -> 25.3706 | K27: 20.24 | L27: 24.61 | M27: 22.15 | N27: 27.07 | O27: 0 | P27: 1 | Q27: 3 | R27: 14 | S27: 13 | T27: 11 | U27: 2 | V27: 16 | W27: =T27/V27 -> 0.6875 | X27: 0.303 | Y27: 0.20537964 | Z27: 0.19110717 | AA27: 0.090909091 | AB27: 0.041799993 | AC27: 0.071119216 | AD27: 0.18644068 | AE27: 0.13008279 | AF27: =_xlfn.XLOOKUP(B27,库存明细报表10.16!L:L,库存明细报表10.16!P:P) -> 5 | AG27: =_xlfn.XLOOKUP(B27,库存明细报表10.16!L:L,库存明细报表10.16!Q:Q) -> 3 | AH27: =_xlfn.XLOOKUP(B27,库存明细报表10.16!L:L,库存明细报表10.16!T:T) -> 23 | AI27: =VLOOKUP(A:A,进销存报表10.16!A:J,10,0) -> 35 | AJ27: =VLOOKUP(A:A,进销存报表10.16!A:K,11,0) -> 14 | AK27: 107.84 | AL27: 82.77 | AM27: 1.33 | AN27: 13 | AO27: =AM27/AK27 -> 0.012333086 | AP27: =AN27/AL27 -> 0.15706174 | AQ27: =ROUNDUP(AK27*10%,0) -> 11 | AR27: 15 | AS27: 15 | AT27: 15 | AU27: 16 | AV27: 16 | AW27: 16 | AX27: 小组 | AZ27: =VLOOKUP(B:B,链接质量检测!A:V,22,0) -> 97
A28: OO2EWP11900 | B28: B0GWZH2JVV | C28: 1189EWP119BUS | D28: FBA | E28: 维稳 | F28: 老品 | G28: 潜力 | H28: 金牛 | I28: 瘦狗 | J28: =64.99*0.92 -> 59.7908 | K28: 54.13 | L28: 54.78 | M28: 49.3 | N28: 60.25 | O28: 0 | P28: 0 | Q28: 1 | R28: 2 | S28: 4 | T28: 6 | U28: 1 | V28: #N/A | W28: =IF(T28>V28,"YES","NO") -> #N/A | X28: 0.235 | Y28: 0.17234422 | Z28: 0.092458435 | AA28: 0 | AB28: 0.007135393 | AC28: 0.093834993 | AD28: 0.24 | AE28: 0 | AF28: =_xlfn.XLOOKUP(B28,库存明细报表10.16!L:L,库存明细报表10.16!P:P) -> 6 | AG28: =_xlfn.XLOOKUP(B28,库存明细报表10.16!L:L,库存明细报表10.16!Q:Q) -> 5 | AH28: =_xlfn.XLOOKUP(B28,库存明细报表10.16!L:L,库存明细报表10.16!T:T) -> 0 | AI28: =VLOOKUP(A:A,进销存报表10.16!A:J,10,0) -> 1 | AJ28: =VLOOKUP(A:A,进销存报表10.16!A:K,11,0) -> 23 | AK28: 55.14 | AL28: 39.25 | AM28: 0.33 | AN28: 4 | AO28: =AM28/AK28 -> 0.0059847661 | AP28: =AN28/AL28 -> 0.10191083 | AQ28: =ROUNDUP(AK28*10%,0) -> 6 | AR28: 4 | AS28: 4 | AT28: 4 | AU28: 4 | AV28: 5 | AW28: 6 | AX28: 小组 | AZ28: =VLOOKUP(B:B,链接质量检测!A:V,22,0) -> 97
A29: OO2EWP01300 | B29: B0CKX85NSB | C29: 1002EWP0137US | D29: FBA | E29: 维稳 | F29: 老品 | G29: 潜力 | H29: 瘦狗 | I29: 潜力 | J29: =79.67*0.9 -> 71.703 | K29: 54.74 | L29: 58.29 | M29: 52.46 | N29: 64.11 | O29: 6 | P29: 3 | Q29: 3 | R29: 10 | S29: 12 | T29: 0 | U29: 0 | V29: 15 | W29: =T29/V29 -> 0 | X29: 0.213 | Y29: 0.14881248 | Z29: 0.12051237 | AA29: 2 | AB29: 0.058985492 | AC29: 0.05 | AD29: 0 | AE29: 0 | AF29: =_xlfn.XLOOKUP(B29,库存明细报表10.16!L:L,库存明细报表10.16!P:P) -> 0 | AG29: =_xlfn.XLOOKUP(B29,库存明细报表10.16!L:L,库存明细报表10.16!Q:Q) -> 0 | AH29: =_xlfn.XLOOKUP(B29,库存明细报表10.16!L:L,库存明细报表10.16!T:T) -> 35 | AI29: =VLOOKUP(A:A,进销存报表10.16!A:J,10,0) -> 15 | AJ29: =VLOOKUP(A:A,进销存报表10.16!A:K,11,0) -> 64 | AK29: 199.78 | AL29: 149.23 | AM29: 3 | AN29: 8.3333333 | AO29: =AM29/AK29 -> 0.015016518 | AP29: =AN29/AL29 -> 0.055842212 | AQ29: =ROUNDUP(AK29*10%,0) -> 20 | AR29: 12 | AS29: 12 | AT29: 14 | AU29: 15 | AV29: 16 | AW29: 20 | AX29: 小组 | AZ29: =VLOOKUP(B:B,链接质量检测!A:V,22,0) -> 92 | BA29: 新增的VC转FBA链接，目前VC在售但海外仓库存3，库存不足
A30: ZC2CLK02000 | B30: B0DG2D424T | C30: 1683CLK020HUS | D30: FBA | E30: 维稳 | F30: 老品 | G30: 潜力 | H30: 潜力 | I30: 潜力 | J30: =29.99 -> 29.99 | K30: 21.64 | L30: 20.18 | M30: 18.16 | N30: 22.2 | O30: 1 | P30: 3 | Q30: 2 | R30: 3 | S30: 0 | T30: 0 | U30: 1 | V30: 6 | W30: =T30/V30 -> 0 | X30: 0.303 | Y30: 0.29207241 | Z30: #N/A | AA30: #N/A | AB30: #N/A | AC30: #N/A | AD30: 0 | AE30: #DIV/0! | AF30: =_xlfn.XLOOKUP(B30,库存明细报表10.16!L:L,库存明细报表10.16!P:P) -> 0 | AG30: =_xlfn.XLOOKUP(B30,库存明细报表10.16!L:L,库存明细报表10.16!Q:Q) -> 0 | AH30: =_xlfn.XLOOKUP(B30,库存明细报表10.16!L:L,库存明细报表10.16!T:T) -> 1 | AI30: =VLOOKUP(A:A,进销存报表10.16!A:J,10,0) -> 14 | AJ30: =VLOOKUP(A:A,进销存报表10.16!A:K,11,0) -> 10 | AK30: 80.46 | AL30: 63.56 | AM30: 2 | AN30: 1 | AO30: =AM30/AK30 -> 0.024857072 | AP30: =AN30/AL30 -> 0.015733166 | AQ30: =ROUNDUP(AK30*10%,0) -> 9 | AR30: 2 | AS30: 3 | AT30: 5 | AU30: 6 | AV30: 8 | AW30: 9 | AX30: 小组 | AZ30: =VLOOKUP(B:B,链接质量检测!A:V,22,0) -> 92 | BA30: 新增的VC转FBA链接，目前VC在售，海外仓库存6，在途17，可先VC推
A31: OO2EWP12500 | B31: B0FC5MCKB1 | C31: 8957EWP125VUS | D31: VC | E31: 维稳 | F31: 老品 | G31: 潜力 | H31: 潜力 | I31: 明星 | J31: =36.99*0.9 -> 33.291 | K31: 16.23 | O31: 1 | P31: 1 | Q31: 0 | R31: 1 | S31: 0 | T31: 0 | U31: 0 | V31: #N/A | W31: =IF(T31>V31,"YES","NO") -> #N/A | X31: 0.382 | Y31: 0.41870425 | Z31: #N/A | AA31: #N/A | AB31: #N/A | AC31: #N/A | AD31: 0 | AE31: #DIV/0! | AF31: =_xlfn.XLOOKUP(B31,库存明细报表10.16!L:L,库存明细报表10.16!P:P) -> #N/A | AG31: =_xlfn.XLOOKUP(B31,库存明细报表10.16!L:L,库存明细报表10.16!Q:Q) -> #N/A | AH31: =_xlfn.XLOOKUP(B31,库存明细报表10.16!L:L,库存明细报表10.16!T:T) -> #N/A | AI31: =VLOOKUP(A:A,进销存报表10.16!A:J,10,0) -> 11 | AJ31: =VLOOKUP(A:A,进销存报表10.16!A:K,11,0) -> 2 | AK31: 16.39 | AL31: 7.84 | AM31: 0.67 | AN31: 0.33333333 | AO31: =AM31/AK31 -> 0.040878585 | AP31: =AN31/AL31 -> 0.042517007 | AQ31: =ROUNDUP(AK31*10%,0) -> 2 | AR31: 1 | AS31: 1 | AT31: 1 | AU31: 2 | AV31: 2 | AW31: 2 | AX31: 小组 | AZ31: =VLOOKUP(B:B,链接质量检测!A:V,22,0) -> 92

Sheet 链接质量检测
A1: ASIN | B1: Fitment前台生效 | C1: 定价符合要求（折后价） | D1: 星级/评论≥4.3 | E1: 标题/亮点规范 | F1: 标题亮点卖点适配 | G1: OE件号 | H1: 套图≥7张 | I1: 首图彩盒 | J1: SKU维度细节图 | K1: 视频（开箱、安装、品牌） | L1: 超级A+ | M1: 品牌故事 | N1: 属性栏OE号精简（唯一） | O1: 后台搜索词 | P1: 购物车/可售 | Q1: 产品描述 | R1: 类目节点 | S1: 属性字段合规 | T1: 首页差评 | U1: 高退货标签 | V1: 加权总分 | W1: 最终等级
A2: 权重 | B2: 10 | C2: 8 | D2: 10 | E2: 8 | F2: 8 | G2: 5 | H2: 5 | I2: 4 | J2: 3 | K2: 6 | L2: 4 | M2: 4 | N2: 5 | O2: 5 | P2: 5 | Q2: 2 | R2: 4 | S2: 4 | T2: 一个扣3分 | U2: 扣8分 | V2: 100
A3: B0G3LJYFZX | B3: 10 | C3: 8 | D3: 10 | E3: 8 | F3: 8 | G3: 5 | H3: 5 | I3: 4 | J3: 3 | K3: 6 | L3: 4 | M3: 4 | N3: 5 | O3: 5 | P3: 5 | Q3: 2 | R3: 4 | S3: 4 | T3: 3 | U3: 0 | V3: =SUM(B3:S3)-T3-U3 -> 97
A4: B0G3LHFPHD | B4: 10 | C4: 8 | D4: 10 | E4: 8 | F4: 8 | G4: 5 | H4: 5 | I4: 4 | J4: 3 | K4: 6 | L4: 4 | M4: 4 | N4: 5 | O4: 5 | P4: 5 | Q4: 2 | R4: 4 | S4: 4 | T4: 3 | U4: 0 | V4: =SUM(B4:S4)-T4-U4 -> 97
A5: B0CKX8PSXX | B5: 10 | C5: 8 | D5: 10 | E5: 8 | F5: 8 | G5: 5 | H5: 5 | I5: 4 | J5: 3 | K5: 6 | L5: 4 | M5: 4 | N5: 5 | O5: 5 | P5: 5 | Q5: 2 | R5: 4 | S5: 4 | T5: 3 | U5: 0 | V5: =SUM(B5:S5)-T5-U5 -> 97
A6: B0CKX9SK3Y | B6: 10 | C6: 8 | D6: 10 | E6: 8 | F6: 8 | G6: 5 | H6: 5 | I6: 4 | J6: 3 | K6: 6 | L6: 4 | M6: 4 | N6: 5 | O6: 5 | P6: 5 | Q6: 2 | R6: 4 | S6: 4 | T6: 3 | U6: 0 | V6: =SUM(B6:S6)-T6-U6 -> 97
A7: B0CKX9959W | B7: 10 | C7: 8 | D7: 10 | E7: 8 | F7: 8 | G7: 5 | H7: 5 | I7: 4 | J7: 3 | K7: 6 | L7: 4 | M7: 4 | N7: 5 | O7: 5 | P7: 5 | Q7: 2 | R7: 4 | S7: 4 | T7: 3 | U7: 0 | V7: =SUM(B7:S7)-T7-U7 -> 97
A8: B0DSW8VBT5 | B8: 10 | C8: 0 | D8: 10 | E8: 8 | F8: 8 | G8: 5 | H8: 5 | I8: 4 | J8: 3 | K8: 6 | L8: 4 | M8: 4 | N8: 5 | O8: 5 | P8: 5 | Q8: 2 | R8: 4 | S8: 4 | T8: 3 | U8: 0 | V8: =SUM(B8:S8)-T8-U8 -> 89
A9: B0GWQX2NTR | B9: 10 | C9: 8 | D9: 10 | E9: 8 | F9: 8 | G9: 5 | H9: 5 | I9: 4 | J9: 3 | K9: 6 | L9: 4 | M9: 4 | N9: 5 | O9: 5 | P9: 5 | Q9: 2 | R9: 4 | S9: 4 | T9: 3 | U9: 0 | V9: =SUM(B9:S9)-T9-U9 -> 97
A10: B0GWZG6T4W | B10: 10 | C10: 0 | D10: 10 | E10: 8 | F10: 0 | G10: 5 | H10: 5 | I10: 4 | J10: 3 | K10: 6 | L10: 4 | M10: 4 | N10: 5 | O10: 5 | P10: 5 | Q10: 2 | R10: 4 | S10: 4 | T10: 3 | U10: 0 | V10: =SUM(B10:S10)-T10-U10 -> 81
A11: B0HJ4NTDXG | B11: 10 | C11: 0 | D11: 10 | E11: 8 | F11: 8 | G11: 5 | H11: 5 | I11: 4 | J11: 3 | K11: 6 | L11: 4 | M11: 4 | N11: 5 | O11: 5 | P11: 5 | Q11: 2 | R11: 4 | S11: 4 | T11: 3 | U11: 0 | V11: =SUM(B11:S11)-T11-U11 -> 89
A12: B0GWZNCP7S | B12: 10 | C12: 8 | D12: 10 | E12: 8 | F12: 8 | G12: 5 | H12: 5 | I12: 4 | J12: 3 | K12: 6 | L12: 4 | M12: 4 | N12: 5 | O12: 5 | P12: 5 | Q12: 2 | R12: 4 | S12: 4 | T12: 3 | U12: 0 | V12: =SUM(B12:S12)-T12-U12 -> 97
A13: B0GWQY1VKB | B13: 10 | C13: 8 | D13: 10 | E13: 8 | F13: 8 | G13: 5 | H13: 5 | I13: 4 | J13: 3 | K13: 6 | L13: 4 | M13: 4 | N13: 5 | O13: 5 | P13: 5 | Q13: 2 | R13: 4 | S13: 4 | T13: 3 | U13: 0 | V13: =SUM(B13:S13)-T13-U13 -> 97
A14: B0GWQTZDGZ | B14: 10 | C14: 8 | D14: 10 | E14: 8 | F14: 8 | G14: 5 | H14: 5 | I14: 4 | J14: 3 | K14: 6 | L14: 4 | M14: 4 | N14: 5 | O14: 5 | P14: 5 | Q14: 2 | R14: 4 | S14: 4 | T14: 3 | U14: 0 | V14: =SUM(B14:S14)-T14-U14 -> 97
... A32: B0FC5MCKB1 | B32: 10 | C32: 0 | D32: 10 | E32: 8 | F32: 8 | G32: 5 | H32: 5 | I32: 4 | J32: 3 | K32: 6 | L32: 4 | M32: 4 | N32: 5 | O32: 5 | P32: 5 | Q32: 2 | R32: 4 | S32: 4 | T32: 0 | U32: 0 | V32: =SUM(B32:S32)-T32-U32 -> 92

Sheet Sheet6
A1: 平台销售编码 | B1: sku | C1: 业务分类 | D1: 品牌 | E1: 流量 | F1: 页面浏览量 | G1: 销量 | H1: 销售额 | I1: 转化率 | J1: 展示量 | K1: 点击数 | L1: 广告花费 | M1: CPC | N1: ACOS | O1: 广告sku销售额 | P1: 广告sku销量 | Q1: 毛利润-实际 | R1: 毛利率 | S1: 推广占比 | T1: 退款率 | U1: 促销折扣 | V1: coupon使用费
A2: 合计 | E2: 1339 | F2: 1819 | G2: 120 | H2: 28082.708 | I2: 0.089619119 | J2: 25670.382 | K2: 297.82119 | L2: 963.83365 | M2: 3.2362829 | N2: 0.10399146 | O2: 8773.904 | P2: 37 | Q2: 6330.7723 | R2: 0.21072219 | S2: 0.095484354 | T2: 0.10700932 | U2: 1766.368 | V2: 138.45543
A3: B0GWR5G1FG | B3: ZC2CLK05300 | C3: 水泵 | D3: PHILTOP | E3: 105 | F3: 131 | G3: 12 | H3: 4078.504 | I3: 0.11428571 | J3: 501.34248 | K3: 8.019544 | L3: 22.784726 | M3: 2.8411498 | N3: 0.016705644 | O3: 1359.728 | P3: 4 | Q3: 712.93814 | R3: 0.17364865 | S3: 0.063287155 | T3: 0.16559286 | U3: 217.532 | V3: 19.517294
A4: B0GWQLN3LT | B4: OO2EWP05900 | C4: 水泵 | D4: PHILTOP | E4: 48 | F4: 65 | G4: 5 | H4: 1461.66 | I4: 0.10416667 | J4: 683.45058 | K4: 14.028806 | L4: 33.563336 | M4: 2.3924585 | N4: 0.056809925 | O4: 584.664 | P4: 2 | Q4: 215.75253 | R4: 0.14468655 | S4: 0.07432278 | T4: 0.19604177 | U4: 70.176 | V4: 7.088713
A5: B0CKX85NSB | B5: OO2EWP01300 | C5: 水泵 | D5: PHILTOP | E5: 47 | F5: 47 | G5: 0 | H5: 0 | I5: 0 | J5: 945.01899 | K5: 5.000151 | L5: 7.073318 | M5: 1.4146209 | N5: 277.13505 | O5: 0 | P5: 0 | Q5: 84.813156 | R5: 0.1807612 | S5: 0.048408606 | T5: 0 | U5: 15.64 | V5: 0
A6: B0G3LJYFZX | B6: OO2EWP05800 | C6: 水泵 | D6: PHILTOP | E6: 40 | F6: 61 | G6: 6 | H6: 2066.792 | I6: 0.15 | J6: 1671.2402 | K6: 12.027036 | L6: 31.516892 | M6: 2.6205037 | N6: 0.091169807 | O6: 339.932 | P6: 1 | Q6: 1005.8698 | R6: 0.4866817 | S6: 0.034216285 | T6: 0.16447325 | U6: 29.376 | V6: 9.825053
A7: B0CKX9959W | B7: OO2EWP01600 | C7: 水泵 | D7: PHILTOP | E7: 98 | F7: 147 | G7: 11 | H7: 1944.052 | I7: 0.1122449 | J7: 2962.3406 | K7: 33.094664 | L7: 110.30875 | M7: 3.3331279 | N7: 0.20042853 | O7: 530.196 | P7: 3 | Q7: 428.37607 | R7: 0.22035217 | S7: 0.14152623 | T7: 0 | U7: 155.584 | V7: 9.241591
A8: B0GWZLNY3H | B8: OO2EWP04700 | C8: 水泵 | D8: PHILTOP | E8: 57 | F8: 70 | G8: 7 | H8: 2236.044 | I8: 0.12280702 | J8: 756.17706 | K8: 13.026513 | L8: 30.902888 | M8: 2.372307 | N8: 0.09503252 | O8: 319.532 | P8: 1 | Q8: 326.30866 | R8: 0.14282567 | S8: 0.074205959 | T8: 0.13956188 | U8: 127.772 | V8: 10.860796
A9: B0CKX8PSXX | B9: OO2EWP02000 | C9: 水泵 | D9: PHILTOP | E9: 191 | F9: 226 | G9: 12 | H9: 1807.984 | I9: 0.062827225 | J9: 2630.9 | K9: 25.074295 | L9: 86.568905 | M9: 3.4524961 | N9: 0.50283965 | O9: 156.332 | P9: 1 | Q9: -90.705655 | R9: -0.049839586 | S9: 0.11867815 | T9: 0.16432521 | U9: 120.768 | V9: 8.651639
A10: B0GWQVBRBB | B10: ZC2CLK04900 | C10: 水泵 | D10: PHILTOP | E10: 19 | F10: 26 | G10: 3 | H10: 815.116 | I10: 0.15789474 | J10: 212.28636 | K10: 5.019095 | L10: 22.238999 | M10: 4.4308783 | N10: 0.080576626 | O10: 271.932 | P10: 1 | Q10: 301.63146 | R10: 0.37004728 | S10: 0.11204034 | T10: 0 | U10: 65.212 | V10: 3.874878
A11: B0CKX9SK3Y | B11: OO2EWP00400 | C11: 水泵 | D11: PHILTOP | E11: 166 | F11: 197 | G11: 4 | H11: 713.796 | I11: 0.024096386 | J11: 1449.0999 | K11: 11.025888 | L11: 30.152381 | M11: 2.7346896 | N11: 0.15396047 | O11: 190.332 | P11: 1 | Q11: 167.01714 | R11: 0.23398441 | S11: 0.11006333 | T11: 0 | U11: 45.696 | V11: 2.714382
A12: B0GWQY9RW4 | B12: OO2EWP02100 | C12: 水泵 | D12: PHILTOP | E12: 29 | F12: 38 | G12: 0 | H12: 0 | I12: 0 | J12: 1095.5488 | K12: 9.029614 | L12: 34.518465 | M12: 3.8228063 | N12: 5.4693842 | O12: 0 | P12: 0 | Q12: 63.985607 | R12: 0.19211205 | S12: 0.1503583 | T12: 0 | U12: 14.688 | V12: 0.872472
A13: B0GWZRG6FQ | B13: OO2EWP08400 | C13: 水泵 | D13: PHILTOP | E13: 37 | F13: 54 | G13: 7 | H13: 1295.944 | I13: 0.18918919 | J13: 942.92868 | K13: 6.016094 | L13: 18.759934 | M13: 3.1182914 | N13: 0.051581636 | O13: 360.264 | P13: 2 | Q13: 211.97105 | R13: 0.19172281 | S13: 0.074492472 | T13: 0.17215081 | U13: 58.344 | V13: 5.255837
A14: B0GWZLNVH8 | B14: OO2EWP08700 | C14: 水泵 | D14: PHILTOP | E14: 10 | F14: 17 | G14: 1 | H14: 163.132 | I14: 0.1 | J14: 184.36761 | K14: 4.01141 | L14: 13.302696 | M14: 3.3162145 | N14: 0.0274228 | O14: 163.132 | P14: 1 | Q14: -108.10263 | R14: -0.6626697 | S14: 0.08629934 | T14: 1 | U14: 0 | V14: 0.775488
A15: B0DG2D424T | B15: ZC2CLK02000 | C15: 水泵 | D15: PHILTOP | E15: 11 | F15: 11 | G15: 0 | H15: 0 | I15: 0 | J15: 12.999994 | K15: 0 | L15: 0 | O15: 0 | P15: 0 | Q15: 0 | U15: 0 | V15: 0
A16: B0DSW8VBT5 | B16: OO2EWP08100 | C16: 水泵 | D16: PHILTOP | E16: 75 | F16: 137 | G16: 8 | H16: 1740.256 | I16: 0.10666667 | J16: 2274.8766 | K16: 38.107474 | L16: 125.2487 | M16: 3.2867226 | N16: 0.14025168 | O16: 870.128 | P16: 4 | Q16: 314.36458 | R16: 0.20644883 | S16: 0.16703183 | T16: 0 | U16: 121.856 | V16: 7.238687
A17: B0FC5MCKB1 | B17: OO2EWP12500 | C17: 水泵 | D17: PHILTOP | E17: 2 | F17: 2 | G17: 0 | H17: 0 | I17: 0 | J17: 0 | K17: 0 | L17: 0 | O17: 0 | P17: 0 | Q17: 0 | U17: 0 | V17: 0
A18: B0G3LHFPHD | B18: OO2EWP07000 | C18: 水泵 | D18: PHILTOP | E18: 27 | F18: 41 | G18: 1 | H18: 176.732 | I18: 0.037037037 | J18: 896.58093 | K18: 8.021543 | L18: 25.104194 | M18: 3.1295966 | N18: 0.13845084 | O18: 176.732 | P18: 1 | Q18: -51.963867 | R18: -0.14251669 | S18: 0.1138883 | T18: 0.46605744 | U18: 14.688 | V18: 1.733301
A19: B0GWQFSGVJ | B19: OO2EWP06000 | C19: 水泵 | D19: PHILTOP | E19: 87 | F19: 112 | G19: 4 | H19: 815.728 | I19: 0.045977011 | J19: 395.14198 | K19: 8.026241 | L19: 30.561667 | M19: 3.8077186 | N19: 0.073918325 | O19: 407.864 | P19: 2 | Q19: 349.61778 | R19: 0.33727617 | S19: 0.11295612 | T19: 0 | U19: 81.6 | V19: 4.927748
A20: B0GWQKHTNJ | B20: OO2EWP10400 | C20: 水泵 | D20: PHILTOP | E20: 25 | F20: 38 | G20: 5 | H20: 1155.66 | I20: 0.2 | J20: 1230.4547 | K20: 7.020467 | L20: 23.876501 | M20: 3.4009847 | N20: 5.4692971 | O20: 0 | P20: 0 | Q20: 620.71044 | R20: 0.37886916 | S20: 0.088061165 | T20: 0 | U20: 112.608 | V20: 7.788219
A21: B0GWQNW9QC | B21: OO2EWP08900 | C21: 水泵 | D21: PHILTOP | E21: 11 | F21: 17 | G21: 2 | H21: 339.864 | I21: 0.18181818 | J21: 738.11101 | K21: 7.017631 | L21: 20.533815 | M21: 2.9260323 | N21: 0.11822356 | O21: 169.932 | P21: 1 | Q21: 58.593932 | R21: 0.17240406 | S21: 0.14520349 | T21: 0 | U21: 27.2 | V21: 1.615624
A22: B0GWQRW5DS | B22: OO2EWP08200 | C22: 水泵 | D22: PHILTOP | E22: 10 | F22: 10 | G22: 1 | H22: 156.332 | I22: 0.1 | J22: 0 | K22: 0 | L22: 0 | O22: 0 | P22: 0 | Q22: 54.012078 | R22: 0.34549598 | S22: 0 | T22: 0 | U22: 0 | V22: 0
A23: B0GWQSPYL6 | B23: OO2EWP12000 | C23: 水泵 | D23: PHILTOP | E23: 16 | F23: 21 | G23: 1 | H23: 203.932 | I23: 0.0625 | J23: 567.04791 | K23: 6.017097 | L23: 19.919727 | M23: 3.3105212 | N23: 5.469237 | O23: 0 | P23: 0 | Q23: 27.247383 | R23: 0.13361014 | S23: 0.18245878 | T23: 0 | U23: 16.32 | V23: 0.969457
A24: B0GWQTZDGZ | B24: OO2EWP08600 | C24: 水泵 | D24: PHILTOP | E24: 35 | F24: 64 | G24: 6 | H24: 2284.392 | I24: 0.17142857 | J24: 860.41141 | K24: 12.036827 | L24: 42.909326 | M24: 3.564837 | N24: 0.037311119 | O24: 1142.196 | P24: 3 | Q24: 276.15977 | R24: 0.12088984 | S24: 0.060210691 | T24: 0.33333333 | U24: 83.776 | V24: 10.859494
A25: B0GWQWCMPT | B25: OO2EWP06700 | C25: 水泵 | D25: PHILTOP | E25: 47 | F25: 70 | G25: 9 | H25: 1651.788 | I25: 0.19148936 | J25: 1324.2518 | K25: 19.060534 | L25: 70.537716 | M25: 3.7007209 | N25: 0.12517944 | O25: 550.596 | P25: 3 | Q25: 433.72019 | R25: 0.26257618 | S25: 0.12526422 | T25: 0 | U25: 128.52 | V25: 7.852222
A26: B0GWQX2NTR | B26: OO2EWP08500 | C26: 水泵 | D26: PHILTOP | E26: 24 | F26: 42 | G26: 3 | H26: 652.596 | I26: 0.125 | J26: 578.05784 | K26: 10.025525 | L26: 29.7431 | M26: 2.9667374 | N26: 5.4694512 | O26: 0 | P26: 0 | Q26: 175.60991 | R26: 0.26909437 | S26: 0.13035538 | T26: 0 | U26: 52.224 | V26: 3.102298
A27: B0GWQY1VKB | B27: OO2EWP06600 | C27: 水泵 | D27: PHILTOP | E27: 27 | F27: 40 | G27: 8 | H27: 1577.056 | I27: 0.2962963 | J27: 530.96957 | K27: 10.033125 | L27: 38.611604 | M27: 3.8484125 | N27: 0.048532188 | O27: 788.528 | P27: 4 | Q27: 406.37983 | R27: 0.25768256 | S27: 0.094259551 | T27: 0 | U27: 102.544 | V27: 7.496986
A28: B0GWZG6T4W | B28: OO2EWP06100 | C28: 水泵 | D28: PHILTOP | E28: 20 | F28: 30 | G28: 2 | H28: 391.884 | I28: 0.1 | J28: 223.42254 | K28: 8.028579 | L28: 33.290441 | M28: 4.1464923 | N28: 0.083650475 | O28: 391.884 | P28: 2 | Q28: 173.85409 | R28: 0.29516022 | S28: 0.14127712 | T28: 0 | U28: 47.124 | V28: 2.800044
A29: B0GWZH2JVV | B29: OO2EWP11900 | C29: 水泵 | D29: PHILTOP | E29: 10 | F29: 13 | G29: 0 | H29: 0 | I29: 0 | J29: 650.91876 | K29: 3.00767 | L29: 8.936514 | M29: 2.9712415 | N29: 5.469394 | O29: 0 | P29: 0 | Q29: -18.551714 | U29: 0 | V29: 0
A30: B0GWZKWRT4 | B30: OO2EWP05000 | C30: 水泵 | D30: PHILTOP | E30: 42 | F30: 57 | G30: 2 | H30: 353.464 | I30: 0.047619048 | J30: 719.91056 | K30: 7.024307 | L30: 28.310595 | M30: 4.0303755 | N30: 5.4693337 | O30: 0 | P30: 0 | Q30: 61.180389 | R30: 0.17308803 | S30: 0.16487926 | T30: 0 | U30: 28.288 | V30: 1.680288
A31: B0GWZNCP7S | B31: OO2EWP03100 | C31: 水泵 | D31: PHILTOP | E31: 19 | F31: 30 | G31: 0 | H31: 0 | I31: 0 | J31: 510.52483 | K31: 9.021064 | L31: 24.558466 | M31: 2.7223469 | N31: 5.4694502 | O31: 0 | P31: 0 | Q31: 50.603754 | U31: 0 | V31: 0
A32: B0HJ4NTDXG | B32: OO2EWP01800 | C32: 水泵 | D32: PHILTOP | E32: 4 | F32: 5 | G32: 0 | H32: 0 | I32: 0 | J32: 122 | K32: 0 | L32: 0 | O32: 0 | P32: 0 | Q32: 79.3784 | R32: 0.2202924 | S32: 0.08476883 | T32: 0 | U32: 28.832 | V32: 1.712922

Sheet 竞对表
A1: 商品编码 | B1: 全量链接
A2: OO2EWP09900 | B2: B00NPVK3I0:24.48/74.93/1835.15/AISIN B097XHTBWH:16.48/46.01/759.63/A-Premium B017AFSYHS:13.99/34.94/487.24/OAW B0G3LJ7K3X:13.33/29.22/389.66/Philtop B0F3D562DY:12.67/22.32/282.72/Kax B0D99DF8NB:10.39/37.37/390.05/BDFHYK B001FJE49S:9.12/61.92/563.0/Gates B0FC6N3DYG:7.18/23.99/172.14/ECCPP B0B42GWRZC:7.12/34.37/244.79/Vipcar B0DNLX8HBK:4.64/29.99/139.14/ADIGARAUTO B0D9NG1NPB:4.35/32.81/142.75/zayody B0DG5B9HFM:1.72/28.88/49.79/UNITHUB B0G1BLHT4C:0.33/23.13/7.71/Torchbeam B00BFDFT0M:0.23/313.19/70.81/Honda
A3: OO2EWP10100 | B3: B0CX1HWZT5:14.54/48.85/706.9/AULINK B09JNW6DMF:7.47/48.19/359.99/TUCAREST B0F3P58B1H:3.98/51.39/203.97/CUGANO B0GWQLK91B:3.67/49.81/182.63/Philtop B0143PZOJO:1.42/49.22/69.45/OAW B0F3D7DNRX:1.0/51.99/51.99/Kax B0C77G85VD:0.7/17.09/36.11/ADIGARAUTO B01CR451DC:0.05/59.22/2.74/MTC
A4: OO2EWP11800 | B4: B097XSWQPQ:15.88/38.36/605.33/A-Premium B01D0JYZV2:9.36/57.44/537.76/AISIN B0GWQVWRRZ:9.33/25.19/235.14/Philtop B019ND400K:2.9/30.33/150.82/OAW B0F9F27FSF:1.26/9.66/36.45/EMTMOUN B086WXMW16:0.85/64.91/55.2/TRQ B0H25WXF4W:0.67/19.99/13.33/Kax B0H46B78NL:0.33/21.99/7.33/Kax B00GVIP8HU:0.2/67.45/13.58/Gates B06WWHVB8L:0.08/18.66/4.47/DNJ
A5: OO2EWP11000 | B5: B0B7X75MRR:21.76/27.63/600.21/A-Premium B0C3G5JV3N:14.52/40.99/594.99/NewYall B0FLX4C3CN:13.91/39.64/552.12/BRTEC B00EPPS986:12.56/78.71/986.89/Gates B0DC6CJZNZ:8.67/23.98/207.53/CUGANO B07RYVXSG3:4.51/61.62/391.63/Beck/Arnley B0C77F7GCC:4.51/25.61/113.2/ADIGARAUTO B0BYNQNN58:3.78/41.0/155.39/MPLUS OE SOLUTION AUTOPARTS B0GWZL1L53:3.67/23.94/87.76/Philtop B09J1JKHL7:3.64/159.99/582.04/A.A B0178JV8ZQ:3.1/29.13/172.42/OAW B0F38C8FW5:2.67/19.99/53.31/Kax B0DXZJYB83:1.15/134.3/148.34/QNCKJZV B07KXYTBKY:0.8/79.99/63.7/Marine Engines 4 Less B0FJL88228:0.67/20.87/13.91/Torchbeam B0G3LJ159C:0.67/21.99/14.66/Philtop B01KHL4GTC:0.64/42.1/81.45/Motorcraft B0BZ4445NB:0.09/14.0/3.61/WINBEST B0C826KFHW:0.0/57.4/0.59/Rareelectrical
A6: OO2EWP05700 | B6: B097XSJZB6:34.35/32.17/1106.48/A-Premium B0CX17V3LB:10.77/22.81/240.67/AULINK B08VDLYQYD:8.99/24.1/216.89/AUQDD B0GWZGC7Q9:8.67/23.19/200.97/Philtop B096VP5SD7:8.1/27.62/223.7/TUCAREST B09GXMV3FP:4.62/26.08/120.42/KEYOOG B0066TLSR8:3.34/46.97/157.05/URO Parts B0F3D7RGMB:1.67/24.73/41.22/Kax B093GLRJGX:1.11/85.0/94.02/MAC B09HX9S3LN:0.92/59.92/55.39/TRQ B00TM2CE3S:0.52/62.97/32.74/DNJ B003YMRL12:0.45/81.09/35.57/Gates B0C77GG22F:0.29/9.16/8.08/ADIGARAUTO B0B27VY8JG:0.17/27.8/4.78/MOCA AUTOPARTS B00LTL0SU6:0.13/53.18/10.49/Beck/Arnley B07SSTZVJL:0.12/21.19/3.82/Carock
A7: OO2EWP07200 | B7: B0B7X9Z65V:21.32/24.74/525.94/A-Premium B096VNHM42:8.19/23.71/194.71/TUCAREST B0F3D6YL65:3.33/21.78/72.59/Kax B0GX5FC5K7:2.67/23.61/62.97/Philtop B01F5XN1VG:2.27/28.69/65.04/OAW B0G3LGZNV3:1.67/22.79/37.98/Philtop B0C77FLRDR:1.64/16.99/41.24/ADIGARAUTO B07MX9RWPN:1.35/21.96/46.46/ECCPP B0CJ919JRJ:1.32/20.41/40.7/SCITOO B09HX93W6M:0.84/60.95/51.47/TRQ B01KHLJTSK:0.81/22.88/55.85/ACDelco B00IU70JCE:0.75/70.78/52.85/Gates B07MXTG884:0.72/6.66/14.41/SCITOO B0FZGTSBSZ:0.67/13.77/9.18/Philtop B013EI96KE:0.1/74.54/21.89/Gates B006DZBRIK:0.08/27.88/7.01/Motorcraft B00TM2AA8O:0.04/44.07/1.55/DNJ
A8: OO2EWP11100 | B8: B000C9IJBQ:11.72/39.66/464.29/ACDelco B0B7X8ZCXM:6.4/34.76/222.97/A-Premium B0DX19L9L8:4.79/34.6/164.98/KAYULONE B0D9PZQC3R:4.18/32.31/134.87/UNITHUB B08SMNCP4C:4.03/23.93/144.61/TUUMOND B0GWZBTZQ1:3.0/31.77/95.3/Philtop B000C2S666:2.96/42.99/127.23/Gates B0F387N5D3:1.67/23.05/38.42/Kax B0BTVMLD5P:1.5/35.31/53.35/CUGANO B07G96Z9CS:0.31/13.33/12.3/ECCPP B09HX7VTBZ:0.24/19.98/14.34/TRQ
A9: OO2EWP11200 | B9: B0BCQSX2HM:12.77/26.81/341.88/A-Premium B0G3LKS8KV:3.67/19.5/71.49/Philtop B000C2U7OU:1.78/41.22/73.42/Gates B0GWQXJ3LD:0.33/32.99/11.0/Philtop B08D3K6J8Q:0.02/8.66/0.54/MPLUS OE SOLUTION AUTOPARTS
A10: OO2EWP04400 | B10: B08L38GRLT:10.56/43.25/456.3/TUUMOND B097XS8TZ6:6.81/57.17/389.72/A-Premium B0FZGR1J14:5.67/34.75/196.92/Philtop B0GWZBPSDW:5.33/37.36/199.24/Philtop B08HXXYVRK:5.3/43.31/227.74/ADIGARAUTO B000C2W8HE:4.84/53.76/260.26/Gates B0B42FNKRH:3.58/56.51/202.42/Vipcar B0143Q07O0:0.96/50.29/48.42/OAW B000C9IJ2A:0.94/77.29/72.04/ACDelco B0G1BRF5NH:0.67/34.75/23.17/Torchbeam B00U0TPFXS:0.19/63.14/12.18/DNJ B0BW89NBMZ:0.16/40.99/6.66/PartsFlow B09KC1J59Z:0.01/26.71/0.46/TOM
A11: OO2EWP09800 | B11: B097XP7NC8:59.73/29.25/1752.19/A-Premium B07X6JG7H8:26.02/25.07/648.03/IRONTREE B001C97VUU:9.99/55.07/550.33/Gates B0CFPTFN19:8.13/24.16/197.88/TUUMOND B096VQ39BL:7.94/24.17/192.23/TUCAREST B0DKXQ8J32:7.75/22.51/174.64/Autodevil B0DX19MJN9:7.69/23.29/179.18/KAYULONE B0B1PMH8ZT:7.58/32.57/247.02/Vipcar B0178DOMSW:5.25/35.21/185.43/OAW B0F3D43NHV:3.67/23.08/84.63/Kax B0CPS87LWW:2.65/25.92/68.81/UCUT B0D6R7998H:2.59/23.59/61.04/UNITHUB B0BFHDBJNQ:2.39/15.99/57.37/ADIGARAUTO B00T3MIXAU:2.23/26.41/176.33/Hitachi B00GTIHIAC:1.41/33.37/44.91/Hitachi B0GWQPPJ13:1.33/29.99/39.99/Philtop B08VDGYPL1:1.07/23.61/25.24/AUQDD B078HS6FZQ:0.88/8.59/22.6/MOCA AUTOPARTS B0CM5LWCW1:0.83/15.94/19.78/CUGANO B09HWW8F8X:0.59/19.98/35.37/TRQ B07NPHGRXS:0.57/11.33/19.37/ECCPP B08SQNTRF5:0.08/11.95/2.79/MPLUS OE SOLUTION AUTOPARTS B0CW3CYQJ5:0.07/13.88/3.12/SCITOO B0CJDV1BV8:0.06/7.99/1.54/SCITOO
A12: OO2EWP12200 | B12: B097XTLD2X:37.42/63.81/2386.18/A-Premium B07TCJL3LC:20.25/61.55/1245.3/OAW B001C9G3D6:16.71/73.07/1224.73/Gates B08HXZ1KRT:5.98/54.75/322.54/ADIGARAUTO B096VMJ24Q:5.13/31.88/245.33/TUCAREST B0GWQMTQY9:3.67/59.16/216.93/Philtop B0B42FS6D7:3.5/75.99/265.71/Vipcar B0049EL80E:3.15/251.81/778.66/Mopar B0FZGP7XFB:2.0/49.91/99.82/Philtop B0049OPB3Y:1.08/75.57/81.47/DNJ B0F3D3S7VG:0.67/57.99/38.66/Kax B0CJRG4MXK:0.54/56.79/30.76/MPLUS OE SOLUTION AUTOPARTS B0FC6N91BF:0.02/62.69/1.28/ECCPP
... A215: OO2EWP12600 | B215: B09Q8YFYDR:2.22/44.55/99.28/A-Premium B019ND3PZG:1.58/30.73/46.77/OAW B0H7YXDXBV:1.33/25.99/34.65/Philtop B00829I0SA:1.31/36.92/72.38/AISIN B0F3D6T4YR:0.33/23.99/8.0/Kax

Sheet 库存明细报表10.16
A1: 日期 | B1: 仓库名称 | C1: 仓库类型 | D1: 站点 | E1: 区域 | F1: 品线 | G1: 业务分类 | H1: 系列 | I1: 型号 | J1: 商品状态 | K1: 平台SKU | L1: ASIN | M1: SKU | N1: 产品编码 | O1: 尾程类型 | P1: 可用库存 | Q1: 可售库存 | R1: 不可售库存 | S1: 待上架库存 | T1: 头程在途 | U1: 采购在途（剩余订单） | V1: 总库存数量 | W1: 总库存金额 | X1: 采购单价 | Y1: 品牌名称 | Z1: 产品分类 | AA1: 是否VC锁定 | AB1: 仓库所在国家 | AC1: 开发人员 | AD1: 单箱数量
A2: 合计 | P2: 1287 | Q2: 1029 | R2: 1 | S2: 391 | T2: 682 | U2: 0 | V2: 1969 | W2: 142640.93
A3: 46311 | B3: US22 | C3: FBA | D3: US | E3: US22 | F3: 配件 | G3: 水泵 | J3: 维稳 | K3: 7263EWP083CUS | L3: B0G3LGYZX4 | M3: OO2EWP08300 | N3: 2EWP0830 | O3: FBA | P3: 6 | Q3: 1 | R3: 0 | S3: 0 | T3: 7 | U3: 0 | V3: 13 | W3: 866.06 | X3: 66.62 | Y3: Others | Z3: 水泵 | AA3: 否 | AB3: US | AC3: 李莉玲 | AD3: 1
A4: 46311 | B4: US22 | C4: FBA | D4: US | E4: US22 | F4: 配件 | G4: 水泵 | J4: 维稳 | K4: 6131EWP0939US | L4: B0GWZDQ8Q1 | M4: OO2EWP09300 | N4: 2EWP0930 | O4: FBA | P4: 9 | Q4: 9 | R4: 0 | S4: 0 | T4: 0 | U4: 0 | V4: 9 | W4: 350.91 | X4: 38.99 | Y4: Others | Z4: 水泵 | AA4: 否 | AB4: US | AC4: 李莉玲 | AD4: 1
A5: 46311 | B5: US22 | C5: FBA | D5: US | E5: US22 | F5: 配件 | G5: 水泵 | J5: 淘汰 | K5: 6879EWP015AUS | L5: B0G3LJC955 | M5: OO2EWP01500 | N5: 2EWP0150 | O5: FBA | P5: 1 | Q5: 1 | R5: 0 | S5: 0 | T5: 0 | U5: 0 | V5: 1 | W5: 231.86 | X5: 231.86 | Y5: Others | Z5: 水泵 | AA5: 否 | AB5: US | AC5: 李莉玲 | AD5: 1
A6: 46311 | B6: US22 | C6: FBA | D6: US | E6: US22 | F6: 配件 | G6: 水泵 | J6: 维稳 | K6: 3666EWP0603US | L6: B0GWQFSGVJ | M6: OO2EWP06000 | N6: 2EWP0600 | O6: FBA | P6: 23 | Q6: 3 | R6: 0 | S6: 20 | T6: 20 | U6: 0 | V6: 43 | W6: 1712.26 | X6: 39.82 | Y6: Others | Z6: 水泵 | AA6: 否 | AB6: US | AC6: 李莉玲 | AD6: 1
A7: 46311 | B7: US22 | C7: FBA | D7: US | E7: US22 | F7: 配件 | G7: 水泵 | J7: 风险 | K7: 7744EWP1127US | L7: B0G3LKS8KV | M7: OO2EWP11200 | N7: 2EWP1120 | O7: FBA | P7: 1 | Q7: 0 | R7: 0 | S7: 0 | T7: 0 | U7: 0 | V7: 1 | W7: 53.98 | X7: 53.98 | Y7: Others | Z7: 水泵 | AA7: 否 | AB7: US | AC7: 李莉玲 | AD7: 1
A8: 46311 | B8: US22 | C8: FBA | D8: US | E8: US22 | F8: 配件 | G8: 水泵 | J8: 维稳 | K8: 2051EWP056VUS | L8: B0G3LHYVT1 | M8: OO2EWP05600 | N8: 2EWP0560 | O8: FBA | P8: 3 | Q8: 3 | R8: 0 | S8: 0 | T8: 0 | U8: 0 | V8: 3 | W8: 241.77 | X8: 80.59 | Y8: Others | Z8: 水泵 | AA8: 否 | AB8: US | AC8: 李莉玲 | AD8: 1
A9: 46311 | B9: US22 | C9: FBA | D9: US | E9: US22 | F9: 配件 | G9: 水泵 | J9: 推新 | K9: 9302EWP1601US | L9: B0HD6DL9B4 | M9: KC2EWP16000 | N9: 2EWP1600 | O9: FBA | P9: 0 | Q9: 0 | R9: 0 | S9: 6 | T9: 6 | U9: 0 | V9: 6 | W9: 235.14 | X9: 39.19 | Y9: KAC | Z9: 水泵 | AA9: 否 | AB9: US | AC9: 李莉玲 | AD9: 1
A10: 46311 | B10: US22 | C10: FBA | D10: US | E10: US22 | F10: 配件 | G10: 水泵 | J10: 维稳 | K10: 2577EWP115BUS | L10: B0GWZLHQS3 | M10: OO2EWP11500 | N10: 2EWP1150 | O10: FBA | P10: 2 | Q10: 2 | R10: 0 | S10: 0 | T10: 0 | U10: 0 | V10: 2 | W10: 103.54 | X10: 51.77 | Y10: Others | Z10: 水泵 | AA10: 否 | AB10: US | AC10: 李莉玲 | AD10: 1
A11: 46311 | B11: US22 | C11: FBA | D11: US | E11: US22 | F11: 配件 | G11: 水泵 | J11: 维稳 | K11: 7785EWP044NUS | L11: B0GWZBPSDW | M11: OO2EWP04400 | N11: 2EWP0440 | O11: FBA | P11: 19 | Q11: 19 | R11: 0 | S11: 0 | T11: 0 | U11: 0 | V11: 19 | W11: 1950.73 | X11: 102.67 | Y11: Others | Z11: 水泵 | AA11: 否 | AB11: US | AC11: 李莉玲 | AD11: 1
A12: 46311 | B12: US22 | C12: FBA | D12: US | E12: US22 | F12: 配件 | G12: 水泵 | J12: 维稳 | K12: 6505CLK050KUS | L12: B0HD5FB81R | M12: ZC2CLK05000 | N12: 2CLK0500 | O12: FBA | P12: 12 | Q12: 3 | R12: 0 | S12: 3 | T12: 6 | U12: 0 | V12: 18 | W12: 2813.22 | X12: 156.29 | Y12: ZonCar | Z12: 水泵 | AA12: 否 | AB12: US | AC12: 李莉玲 | AD12: 1
A13: 46311 | B13: US22 | C13: FBA | D13: US | E13: US22 | F13: 配件 | G13: 水泵 | J13: 风险 | K13: 7229EWP054RUS | L13: B0FLJW7Y8P | M13: OO2EWP05400 | N13: 2EWP0540 | O13: FBA | P13: 14 | Q13: 14 | R13: 0 | S13: 0 | T13: 0 | U13: 0 | V13: 14 | W13: 596.12 | X13: 42.58 | Y13: Others | Z13: 水泵 | AA13: 否 | AB13: US | AC13: 李莉玲 | AD13: 1
A14: 46311 | B14: US22 | C14: FBA | D14: US | E14: US22 | F14: 配件 | G14: 水泵 | J14: 维稳 | K14: 9087EWP021RUS | L14: B0GWQY9RW4 | M14: OO2EWP02100 | N14: 2EWP0210 | O14: FBA | P14: 5 | Q14: 1 | R14: 0 | S14: 0 | T14: 0 | U14: 0 | V14: 5 | W14: 243.6 | X14: 48.72 | Y14: Others | Z14: 水泵 | AA14: 否 | AB14: US | AC14: 李莉玲 | AD14: 1
... A133: 46303 | B133: US22 | C133: FBA | D133: US | E133: US22 | F133: 配件 | G133: 水泵 | J133: 维稳 | K133: 9973EWP085JUS | L133: B0GWQX2NTR | M133: OO2EWP08500 | N133: 2EWP0850 | O133: FBA | P133: 25 | Q133: 11 | R133: 0 | S133: 0 | T133: 1 | U133: 0 | V133: 26 | W133: 1334.58 | X133: 51.33 | Y133: Others | Z133: 水泵 | AA133: 否 | AB133: US | AC133: 李莉玲 | AD133: 1

Sheet 进销存报表10.16
A1: 商品编码 | B1: 品线 | C1: 业务分类 | D1: 系列 | E1: 型号 | F1: 商品等级 | G1: 开发人员 | H1: FBA可用库存 | I1: FBA在途库存 | J1: 海外仓可用库存 | K1: 海外仓在途库存 | L1: 本地仓可用库存 | M1: 总库存 | N1: 采购在途库存 | O1: 含采购在途总库存 | P1: 总库存金额 | Q1: 含采购在途总库存金额 | R1: 7天销量 | S1: 14天销量 | T1: 30天销量 | U1: 30-60天销量 | V1: 60-90天销量 | W1: 近7天入库数量 | X1: 近14天入库数量 | Y1: 近30天入库数量 | Z1: 采购单价 | AA1: 30天出库金额 | AB1: 全链路库销比 | AC1: 成品库销比 | AD1: 离岸库销比 | AE1: FBA库销比 | AF1: 海外仓在库库销比 | AG1: 海外仓在途库销比 | AH1: 库销比-预警值 | AI1: 滞销数量 | AJ1: 库销比-红线值 | AK1: 滞销金额 | AL1: 品牌 | AM1: FBA30天销量 | AN1: FBM30天销量 | AO1: FBA首次到货时间 | AP1: FBM首次到货时间 | AQ1: 是否滞销 | AR1: 品类
A2: 合计 | H2: 1678 | I2: 682 | J2: 2892 | K2: 2930 | L2: 5102 | M2: 13284 | N2: 7441 | O2: 20725 | P2: 1041678.1 | Q2: 1647096.8 | R2: 438 | S2: 894 | T2: 1839 | U2: 1668 | V2: 1505 | W2: 922 | X2: 1754 | Y2: 2538 | Z2: 82.576376 | AA2: 144327.16 | AI2: 4466 | AK2: 355993.16
A3: OO2EWP02000 | B3: 配件 | C3: 水泵 | F3: A | G3: 李莉玲 | H3: 46 | I3: 20 | J3: 83 | K3: 59 | L3: 82 | M3: 290 | N3: 240 | O3: 530 | P3: 11039.72 | Q3: 20176.039 | R3: 7 | S3: 15 | T3: 46 | U3: 31 | V3: 21 | W3: 0 | X3: 0 | Y3: 0 | Z3: 38.067999 | AA3: 1751.128 | AB3: 11.521739 | AC3: 6.3043478 | AD3: 4.5217391 | AE3: 1 | AF3: 1.8043478 | AG3: 1.2826087 | AH3: 4.5 | AI3: 14 | AJ3: 6 | AK3: 532.95199 | AL3: Others | AM3: 20 | AN3: 26 | AO3: 45368 | AP3: 45351 | AQ3: N | AR3: 水泵
A4: OO2EWP08300 | B4: 配件 | C4: 水泵 | F4: B | G4: 李莉玲 | H4: 6 | I4: 7 | J4: 13 | K4: 74 | L4: 135 | M4: 235 | N4: 60 | O4: 295 | P4: 15654.809 | Q4: 19651.781 | R4: 4 | S4: 7 | T4: 25 | U4: 35 | V4: 45 | W4: 0 | X4: 120 | Y4: 120 | Z4: 66.616208 | AA4: 1665.4052 | AB4: 11.8 | AC4: 9.4 | AD4: 4 | AE4: 0.24 | AF4: 0.52 | AG4: 2.96 | AH4: 4.5 | AI4: 85 | AJ4: 6 | AK4: 5662.3777 | AL4: Others | AM4: 4 | AN4: 21 | AO4: 46044 | AP4: 45696 | AQ4: N | AR4: 水泵
A5: OO2EWP11400 | B5: 配件 | C5: 水泵 | F5: S | G5: 李莉玲 | H5: 24 | I5: 0 | J5: 22 | K5: 48 | L5: 139 | M5: 233 | N5: 0 | O5: 233 | P5: 20239.072 | Q5: 20239.072 | R5: 8 | S5: 22 | T5: 33 | U5: 32 | V5: 39 | W5: 0 | X5: 0 | Y5: 30 | Z5: 86.862972 | AA5: 2866.4781 | AB5: 7.0606061 | AC5: 7.0606061 | AD5: 2.8484848 | AE5: 0.72727273 | AF5: 0.66666667 | AG5: 1.4545455 | AH5: 4.5 | AI5: 35 | AJ5: 6 | AK5: 3040.204 | AL5: Others | AM5: 7 | AN5: 7 | AO5: 46035 | AP5: 45768 | AQ5: N | AR5: 水泵
A6: OO2EWP05800 | B6: 配件 | C6: 水泵 | F6: A | G6: 李莉玲 | H6: 46 | I6: 4 | J6: 44 | K6: 24 | L6: 98 | M6: 216 | N6: 0 | O6: 216 | P6: 25426.1 | Q6: 25426.1 | R6: 2 | S6: 8 | T6: 25 | U6: 12 | V6: 20 | W6: 0 | X6: 0 | Y6: 0 | Z6: 117.71342 | AA6: 2942.8356 | AB6: 8.64 | AC6: 8.64 | AD6: 4.72 | AE6: 1.84 | AF6: 1.76 | AG6: 0.96 | AH6: 4.5 | AI6: 66 | AJ6: 6 | AK6: 7769.086 | AL6: Others | AM6: 10 | AN6: 9 | AO6: 46012 | AP6: 45688 | AQ6: N | AR6: 水泵
A7: OO2EWP00400 | B7: 配件 | C7: 水泵 | F7: A | G7: 李莉玲 | H7: 87 | I7: 60 | J7: 8 | K7: 27 | L7: 24 | M7: 206 | N7: 120 | O7: 326 | P7: 9302.3451 | Q7: 14721.187 | R7: 9 | S7: 16 | T7: 39 | U7: 23 | V7: 33 | W7: 40 | X7: 40 | Y7: 40 | Z7: 45.157015 | AA7: 1761.1236 | AB7: 8.3589744 | AC7: 5.2820513 | AD7: 4.6666667 | AE7: 2.2307692 | AF7: 0.20512821 | AG7: 0.69230769 | AH7: 4.5 | AI7: 0 | AJ7: 6 | AK7: 0 | AL7: Others | AM7: 13 | AN7: 8 | AO7: 45368 | AP7: 45351 | AQ7: N | AR7: 水泵
A8: OO2EWP04900 | B8: 配件 | C8: 水泵 | F8: C | G8: 李莉玲 | H8: 0 | I8: 0 | J8: 54 | K8: 18 | L8: 113 | M8: 185 | N8: 0 | O8: 185 | P8: 15389.766 | Q8: 15389.766 | R8: 4 | S8: 5 | T8: 16 | U8: 10 | V8: 10 | W8: 0 | X8: 0 | Y8: 0 | Z8: 83.187924 | AA8: 1331.0068 | AB8: 11.5625 | AC8: 11.5625 | AD8: 4.5 | AE8: 0 | AF8: 3.375 | AG8: 1.125 | AH8: 4.5 | AI8: 89 | AJ8: 6 | AK8: 7403.7252 | AL8: Others | AM8: 0 | AN8: 13 | AP8: 45756 | AQ8: N | AR8: 水泵
A9: OO2EWP02400 | B9: 配件 | C9: 水泵 | F9: A | G9: 李莉玲 | H9: 25 | I9: 0 | J9: 0 | K9: 66 | L9: 91 | M9: 182 | N9: 24 | O9: 206 | P9: 18038.938 | Q9: 20417.699 | R9: 8 | S9: 14 | T9: 33 | U9: 36 | V9: 25 | W9: 96 | X9: 96 | Y9: 150 | Z9: 99.115044 | AA9: 3270.7965 | AB9: 6.2424242 | AC9: 5.5151515 | AD9: 2.7575758 | AE9: 0.75757576 | AF9: 0 | AG9: 2 | AH9: 4.5 | AI9: 0 | AJ9: 6 | AK9: 0 | AL9: Others | AM9: 8 | AN9: 20 | AO9: 45368 | AP9: 45351 | AQ9: N | AR9: 水泵
A10: OO2EWP06700 | B10: 配件 | C10: 水泵 | F10: A | G10: 李莉玲 | H10: 28 | I10: 23 | J10: 35 | K10: 14 | L10: 76 | M10: 176 | N10: 60 | O10: 236 | P10: 7013.2915 | Q10: 9404.1863 | R10: 5 | S10: 6 | T10: 14 | U10: 14 | V10: 31 | W10: 60 | X10: 60 | Y10: 60 | Z10: 39.848247 | AA10: 557.87546 | AB10: 16.857143 | AC10: 12.571429 | AD10: 7.1428571 | AE10: 2 | AF10: 2.5 | AG10: 1 | AH10: 4.5 | AI10: 92 | AJ10: 6 | AK10: 3666.0387 | AL10: Others | AM10: 7 | AN10: 5 | AO10: 46194 | AP10: 45767 | AQ10: N | AR10: 水泵
A11: OO2EWP01600 | B11: 配件 | C11: 水泵 | F11: A | G11: 李莉玲 | H11: 44 | I11: 20 | J11: 52 | K11: 23 | L11: 29 | M11: 168 | N11: 120 | O11: 288 | P11: 7341.1528 | Q11: 12584.833 | R11: 6 | S11: 17 | T11: 28 | U11: 35 | V11: 33 | W11: 40 | X11: 40 | Y11: 40 | Z11: 43.697338 | AA11: 1223.5255 | AB11: 10.285714 | AC11: 6 | AD11: 4.9642857 | AE11: 1.5714286 | AF11: 1.8571429 | AG11: 0.82142857 | AH11: 4.5 | AI11: 0 | AJ11: 6 | AK11: 0 | AL11: Others | AM11: 12 | AN11: 14 | AO11: 45368 | AP11: 45366 | AQ11: N | AR11: 水泵
A12: KC2EWP15400 | B12: 配件 | C12: 水泵 | F12: 推新 | G12: 李莉玲 | H12: 20 | I12: 0 | J12: 13 | K12: 4 | L12: 122 | M12: 159 | N12: 0 | O12: 159 | P12: 11538.053 | Q12: 11538.053 | R12: 0 | S12: 1 | T12: 2 | U12: 0 | V12: 0 | W12: 0 | X12: 120 | Y12: 120 | Z12: 72.566372 | AA12: 145.13274 | AB12: 79.5 | AC12: 79.5 | AD12: 18.5 | AE12: 10 | AF12: 6.5 | AG12: 2 | AH12: 4.5 | AI12: 147 | AJ12: 6 | AK12: 10667.257 | AL12: KAC | AM12: 0 | AN12: 2 | AO12: 46268 | AP12: 46277 | AQ12: N | AR12: 水泵
A13: OO2EWP00700 | B13: 配件 | C13: 水泵 | F13: B | G13: 李莉玲 | H13: 0 | I13: 0 | J13: 49 | K13: 1 | L13: 108 | M13: 158 | N13: 0 | O13: 158 | P13: 8249.5571 | Q13: 8249.5571 | R13: 2 | S13: 3 | T13: 7 | U13: 6 | V13: 8 | W13: 0 | X13: 0 | Y13: 0 | Z13: 52.212387 | AA13: 365.48671 | AB13: 22.571429 | AC13: 22.571429 | AD13: 7.1428571 | AE13: 0 | AF13: 7 | AG13: 0.14285714 | AH13: 4.5 | AI13: 116 | AJ13: 6 | AK13: 6056.6369 | AL13: Others | AM13: 0 | AN13: 7 | AO13: 45368 | AP13: 45351 | AQ13: N | AR13: 水泵
A14: ZC2CLK05300 | B14: 配件 | C14: 水泵 | F14: A | G14: 李莉玲 | H14: 34 | I14: 18 | J14: 36 | K14: 7 | L14: 60 | M14: 155 | N14: 60 | O14: 215 | P14: 14405.587 | Q14: 19981.943 | R14: 0 | S14: 4 | T14: 9 | U14: 26 | V14: 10 | W14: 48 | X14: 48 | Y14: 48 | Z14: 92.939272 | AA14: 836.45345 | AB14: 23.888889 | AC14: 17.222222 | AD14: 10.555556 | AE14: 3.7777778 | AF14: 4 | AG14: 0.77777778 | AH14: 4.5 | AI14: 101 | AJ14: 6 | AK14: 9386.8665 | AL14: ZonCar | AM14: 2 | AN14: 4 | AO14: 46184 | AP14: 44803 | AQ14: N | AR14: 水泵
A15: OO2EWP08100 | B15: 配件 | C15: 水泵 | F15: A | G15: 李莉玲 | H15: 12 | I15: 7 | J15: 53 | K15: 28 | L15: 54 | M15: 154 | N15: 140 | O15: 294 | P15: 8649.878 | Q15: 16513.403 | R15: 7 | S15: 19 | T15: 29 | U15: 28 | V15: 19 | W15: 0 | X15: 0 | Y15: 0 | Z15: 56.168039 | AA15: 1628.8731 | AB15: 10.137931 | AC15: 5.3103448 | AD15: 3.4482759 | AE15: 0.4137931 | AF15: 1.8275862 | AG15: 0.96551724 | AH15: 4.5 | AI15: 0 | AJ15: 6 | AK15: 0 | AL15: Others | AM15: 19 | AN15: 7 | AO15: 46203 | AP15: 45704 | AQ15: N | AR15: 水泵
A16: OO2EWP00100 | B16: 配件 | C16: 水泵 | F16: C | G16: 李莉玲 | H16: 0 | I16: 0 | J16: 68 | K16: 48 | L16: 33 | M16: 149 | N16: 56 | O16: 205 | P16: 11875.161 | Q16: 16338.309 | R16: 3 | S16: 10 | T16: 17 | U16: 19 | V16: 21 | W16: 0 | X16: 48 | Y16: 48 | Z16: 79.699068 | AA16: 1354.8842 | AB16: 12.058824 | AC16: 8.7647059 | AD16: 6.8235294 | AE16: 0 | AF16: 4 | AG16: 2.8235294 | AH16: 4.5 | AI16: 47 | AJ16: 6 | AK16: 3745.8562 | AL16: Others | AM16: 0 | AN16: 16 | AO16: 45368 | AP16: 45351 | AQ16: N | AR16: 水泵
A17: OO2EWP05700 | B17: 配件 | C17: 水泵 | F17: B | G17: 李莉玲 | H17: 23 | I17: 0 | J17: 3 | K17: 21 | L17: 99 | M17: 146 | N17: 0 | O17: 146 | P17: 6848.938 | Q17: 6848.938 | R17: 3 | S17: 3 | T17: 9 | U17: 10 | V17: 28 | W17: 80 | X17: 80 | Y17: 80 | Z17: 46.910534 | AA17: 422.19481 | AB17: 16.222222 | AC17: 16.222222 | AD17: 5.2222222 | AE17: 2.5555556 | AF17: 0.33333333 | AG17: 2.3333333 | AH17: 4.5 | AI17: 92 | AJ17: 6 | AK17: 4315.7691 | AL17: Others | AM17: 1 | AN17: 8 | AO17: 46206 | AP17: 45758 | AQ17: N | AR17: 水泵
A18: OO2EWP06200 | B18: 配件 | C18: 水泵 | F18: A | G18: 李莉玲 | H18: 21 | I18: 0 | J18: 39 | K18: 31 | L18: 52 | M18: 143 | N18: 160 | O18: 303 | P18: 6707.3525 | Q18: 14212.083 | R18: 3 | S18: 7 | T18: 30 | U18: 26 | V18: 19 | W18: 0 | X18: 0 | Y18: 0 | Z18: 46.904563 | AA18: 1407.1369 | AB18: 10.1 | AC18: 4.7666667 | AD18: 3.0333333 | AE18: 0.7 | AF18: 1.3 | AG18: 1.0333333 | AH18: 4.5 | AI18: 0 | AJ18: 6 | AK18: 0 | AL18: Others | AM18: 11 | AN18: 18 | AO18: 46044 | AP18: 45757 | AQ18: N | AR18: 水泵
A19: OO2EWP03000 | B19: 配件 | C19: 水泵 | F19: B | G19: 李莉玲 | H19: 19 | I19: 0 | J19: 37 | K19: 12 | L19: 72 | M19: 140 | N19: 0 | O19: 140 | P19: 26369.654 | Q19: 26369.654 | R19: 4 | S19: 9 | T19: 24 | U19: 10 | V19: 6 | W19: 0 | X19: 0 | Y19: 0 | Z19: 188.35467 | AA19: 4520.5122 | AB19: 5.8333333 | AC19: 5.8333333 | AD19: 2.8333333 | AE19: 0.79166667 | AF19: 1.5416667 | AG19: 0.5 | AH19: 4.5 | AI19: 0 | AJ19: 6 | AK19: 0 | AL19: Others | AM19: 2 | AN19: 19 | AO19: 45368 | AP19: 45351 | AQ19: N | AR19: 水泵
A20: OO2EWP08200 | B20: 配件 | C20: 水泵 | F20: A | G20: 李莉玲 | H20: 20 | I20: 20 | J20: 14 | K20: 83 | L20: 1 | M20: 138 | N20: 0 | O20: 138 | P20: 7083.3812 | Q20: 7083.3812 | R20: 1 | S20: 5 | T20: 17 | U20: 16 | V20: 9 | W20: 0 | X20: 0 | Y20: 0 | Z20: 51.328849 | AA20: 872.59043 | AB20: 8.1176471 | AC20: 8.1176471 | AD20: 8.0588235 | AE20: 1.1764706 | AF20: 0.82352941 | AG20: 4.8823529 | AH20: 4.5 | AI20: 36 | AJ20: 6 | AK20: 1847.8386 | AL20: Others | AM20: 0 | AN20: 17 | AO20: 46206 | AP20: 45757 | AQ20: N | AR20: 水泵
... A27: OO2EWP10600 | B27: 配件 | C27: 水泵 | F27: S | G27: 李莉玲 | H27: 24 | I27: 24 | J27: 13 | K27: 42 | L27: 24 | M27: 127 | N27: 96 | O27: 223 | P27: 13725.187 | Q27: 24100.131 | R27: 9 | S27: 12 | T27: 18 | U27: 24 | V27: 21 | W27: 18 | X27: 18 | Y27: 18 | Z27: 108.07234 | AA27: 1945.3021 | AB27: 12.388889 | AC27: 7.0555556 | AD27: 5.7222222 | AE27: 1.3333333 | AF27: 0.72222222 | AG27: 2.3333333 | AH27: 4.5 | AI27: 19 | AJ27: 6 | AK27: 2053.3744 | AL27: Others | AM27: 0 | AN27: 7 | AO27: 46012 | AP27: 45760 | AQ27: N | AR27: 水泵
A28: KC2EWP25500 | B28: 配件 | C28: 水泵 | F28: C | G28: 李莉玲 | H28: 0 | I28: 0 | J28: 41 | K28: 30 | L28: 55 | M28: 126 | N28: 0 | O28: 126 | P28: 14718.584 | Q28: 14718.584 | R28: 0 | S28: 0 | T28: 0 | U28: 1 | V28: 0 | W28: 0 | X28: 72 | Y28: 72 | Z28: 116.81416 | AA28: 0 | AH28: 4.5 | AI28: 126 | AJ28: 6 | AK28: 14718.584 | AL28: KAC | AM28: 0 | AN28: 0 | AP28: 46233 | AQ28: N | AR28: 水泵
A29: OO2EWP09100 | B29: 配件 | C29: 水泵 | F29: B | G29: 李莉玲 | H29: 25 | I29: 5 | J29: 10 | K29: 11 | L29: 73 | M29: 124 | N29: 0 | O29: 124 | P29: 5246.5728 | Q29: 5246.5728 | R29: 8 | S29: 11 | T29: 15 | U29: 11 | V29: 11 | W29: 0 | X29: 0 | Y29: 80 | Z29: 42.311071 | AA29: 634.66607 | AB29: 8.2666667 | AC29: 8.2666667 | AD29: 3.4 | AE29: 1.6666667 | AF29: 0.66666667 | AG29: 0.73333333 | AH29: 4.5 | AI29: 34 | AJ29: 6 | AK29: 1438.5764 | AL29: Others | AM29: 7 | AN29: 7 | AO29: 46012 | AP29: 45744 | AQ29: N | AR29: 水泵
A30: OO2EWP07100 | B30: 配件 | C30: 水泵 | F30: A | G30: 李莉玲 | H30: 22 | I30: 0 | J30: 3 | K30: 47 | L30: 50 | M30: 122 | N30: 160 | O30: 282 | P30: 4750.5386 | Q30: 10980.753 | R30: 5 | S30: 12 | T30: 32 | U30: 31 | V30: 41 | W30: 0 | X30: 0 | Y30: 80 | Z30: 38.938841 | AA30: 1246.0429 | AB30: 8.8125 | AC30: 3.8125 | AD30: 2.25 | AE30: 0.6875 | AF30: 0.09375 | AG30: 1.46875 | AH30: 4.5 | AI30: 0 | AJ30: 6 | AK30: 0 | AL30: Others | AM30: 17 | AN30: 12 | AO30: 46184 | AP30: 45757 | AQ30: N | AR30: 水泵
A31: OO2EWP08400 | B31: 配件 | C31: 水泵 | F31: A | G31: 李莉玲 | H31: 35 | I31: 20 | J31: 11 | K31: 28 | L31: 23 | M31: 117 | N31: 120 | O31: 237 | P31: 4970.0155 | Q31: 10067.467 | R31: 4 | S31: 8 | T31: 21 | U31: 21 | V31: 21 | W31: 0 | X31: 0 | Y31: 0 | Z31: 42.478765 | AA31: 892.05407 | AB31: 11.285714 | AC31: 5.5714286 | AD31: 4.4761905 | AE31: 1.6666667 | AF31: 0.52380952 | AG31: 1.3333333 | AH31: 4.5 | AI31: 0 | AJ31: 6 | AK31: 0 | AL31: Others | AM31: 10 | AN31: 4 | AO31: 46184 | AP31: 45757 | AQ31: N | AR31: 水泵
A32: ZC2CLK04900 | B32: 配件 | C32: 水泵 | F32: A | G32: 李莉玲 | H32: 15 | I32: 0 | J32: 19 | K32: 12 | L32: 67 | M32: 113 | N32: 20 | O32: 133 | P32: 6610.8129 | Q32: 7780.8683 | R32: 2 | S32: 7 | T32: 12 | U32: 13 | V32: 14 | W32: 60 | X32: 60 | Y32: 60 | Z32: 58.502769 | AA32: 702.03323 | AB32: 11.083333 | AC32: 9.4166667 | AD32: 3.8333333 | AE32: 1.25 | AF32: 1.5833333 | AG32: 1 | AH32: 4.5 | AI32: 41 | AJ32: 6 | AK32: 2398.6135 | AL32: ZonCar | AM32: 1 | AN32: 10 | AO32: 46249 | AP32: 44804 | AQ32: N | AR32: 水泵
A33: OO2EWP12000 | B33: 配件 | C33: 水泵 | F33: B | G33: 李莉玲 | H33: 31 | I33: 17 | J33: 15 | K33: 13 | L33: 35 | M33: 111 | N33: 0 | O33: 111 | P33: 6764.717 | Q33: 6764.717 | R33: 1 | S33: 2 | T33: 8 | U33: 11 | V33: 2 | W33: 0 | X33: 30 | Y33: 30 | Z33: 60.943396 | AA33: 487.54717 | AB33: 13.875 | AC33: 13.875 | AD33: 9.5 | AE33: 3.875 | AF33: 1.875 | AG33: 1.625 | AH33: 4.5 | AI33: 63 | AJ33: 6 | AK33: 3839.4339 | AL33: Others | AM33: 1 | AN33: 2 | AO33: 46212 | AP33: 45738 | AQ33: N | AR33: 水泵
A34: OO2EWP04000 | B34: 配件 | C34: 水泵 | F34: C | G34: 李莉玲 | H34: 19 | I34: 0 | J34: 18 | K34: 2 | L34: 67 | M34: 106 | N34: 0 | O34: 106 | P34: 12246.026 | Q34: 12246.026 | R34: 1 | S34: 4 | T34: 9 | U34: 12 | V34: 10 | W34: 0 | X34: 0 | Y34: 0 | Z34: 115.52855 | AA34: 1039.7569 | AB34: 11.777778 | AC34: 11.777778 | AD34: 4.3333333 | AE34: 2.1111111 | AF34: 2 | AG34: 0.22222222 | AH34: 4.5 | AI34: 52 | AJ34: 6 | AK34: 6007.4844 | AL34: Others | AM34: 4 | AN34: 5 | AO34: 45368 | AP34: 45351 | AQ34: N | AR34: 水泵
A35: OO2EWP09000 | B35: 配件 | C35: 水泵 | F35: B | G35: 李莉玲 | H35: 8 | I35: 3 | J35: 20 | K35: 13 | L35: 60 | M35: 104 | N35: 60 | O35: 164 | P35: 5614.4645 | Q35: 8853.5787 | R35: 5 | S35: 9 | T35: 18 | U35: 15 | V35: 16 | W35: 20 | X35: 20 | Y35: 20 | Z35: 53.985236 | AA35: 971.73425 | AB35: 9.1111111 | AC35: 5.7777778 | AD35: 2.4444444 | AE35: 0.44444444 | AF35: 1.1111111 | AG35: 0.72222222 | AH35: 4.5 | AI35: 0 | AJ35: 6 | AK35: 0 | AL35: Others | AM35: 2 | AN35: 12 | AO35: 46035 | AP35: 45758 | AQ35: N | AR35: 水泵
A36: OO2EWP07500 | B36: 配件 | C36: 水泵 | F36: B | G36: 李莉玲 | H36: 25 | I36: 0 | J36: 40 | K36: 8 | L36: 31 | M36: 104 | N36: 50 | O36: 154 | P36: 10349.13 | Q36: 15324.673 | R36: 1 | S36: 5 | T36: 9 | U36: 11 | V36: 8 | W36: 0 | X36: 0 | Y36: 0 | Z36: 99.510862 | AA36: 895.59776 | AB36: 17.111111 | AC36: 11.555556 | AD36: 8.1111111 | AE36: 2.7777778 | AF36: 4.4444444 | AG36: 0.88888889 | AH36: 4.5 | AI36: 50 | AJ36: 6 | AK36: 4975.5431 | AL36: Others | AM36: 1 | AN36: 6 | AO36: 46181 | AP36: 45688 | AQ36: N | AR36: 水泵
A37: OO2EWP00200 | B37: 配件 | C37: 水泵 | F37: C | G37: 李莉玲 | H37: 5 | I37: 0 | J37: 0 | K37: 72 | L37: 27 | M37: 104 | N37: 56 | O37: 160 | P37: 6111.9454 | Q37: 9402.993 | R37: 13 | S37: 30 | T37: 40 | U37: 41 | V37: 26 | W37: 24 | X37: 24 | Y37: 24 | Z37: 58.768706 | AA37: 2350.7482 | AB37: 4 | AC37: 2.6 | AD37: 1.925 | AE37: 0.125 | AF37: 0 | AG37: 1.8 | AH37: 4.5 | AI37: 0 | AJ37: 6 | AK37: 0 | AL37: Others | AM37: 1 | AN37: 39 | AO37: 45368 | AP37: 45351 | AQ37: N | AR37: 水泵
A38: OO2EWP04600 | B38: 配件 | C38: 水泵 | F38: B | G38: 李莉玲 | H38: 0 | I38: 0 | J38: 28 | K38: 1 | L38: 74 | M38: 103 | N38: 0 | O38: 103 | P38: 7657.2349 | Q38: 7657.2349 | R38: 3 | S38: 4 | T38: 5 | U38: 4 | V38: 1 | W38: 0 | X38: 0 | Y38: 0 | Z38: 74.342086 | AA38: 371.71043 | AB38: 20.6 | AC38: 20.6 | AD38: 5.8 | AE38: 0 | AF38: 5.6 | AG38: 0.2 | AH38: 4.5 | AI38: 73 | AJ38: 6 | AK38: 5426.9723 | AL38: Others | AM38: 0 | AN38: 5 | AO38: 46012 | AP38: 45759 | AQ38: N | AR38: 水泵
A39: OO2EWP03900 | B39: 配件 | C39: 水泵 | F39: C | G39: 李莉玲 | H39: 7 | I39: 0 | J39: 29 | K39: 27 | L39: 37 | M39: 100 | N39: 48 | O39: 148 | P39: 5402.9328 | Q39: 7996.3405 | R39: 9 | S39: 19 | T39: 27 | U39: 14 | V39: 32 | W39: 0 | X39: 16 | Y39: 16 | Z39: 54.029328 | AA39: 1458.7919 | AB39: 5.4814815 | AC39: 3.7037037 | AD39: 2.3333333 | AE39: 0.25925926 | AF39: 1.0740741 | AG39: 1 | AH39: 4.5 | AI39: 0 | AJ39: 6 | AK39: 0 | AL39: Others | AM39: 2 | AN39: 24 | AO39: 45368 | AP39: 45351 | AQ39: N | AR39: 水泵
A40: OO2EWP07800 | B40: 配件 | C40: 水泵 | F40: B | G40: 李莉玲 | H40: 5 | I40: 0 | J40: 0 | K40: 50 | L40: 44 | M40: 99 | N40: 115 | O40: 214 | P40: 8061.9571 | Q40: 17426.857 | R40: 2 | S40: 2 | T40: 18 | U40: 17 | V40: 6 | W40: 0 | X40: 0 | Y40: 57 | Z40: 81.43391 | AA40: 1465.8104 | AB40: 11.888889 | AC40: 5.5 | AD40: 3.0555556 | AE40: 0.27777778 | AF40: 0 | AG40: 2.7777778 | AH40: 4.5 | AI40: 0 | AJ40: 6 | AK40: 0 | AL40: Others | AM40: 5 | AN40: 13 | AO40: 46012 | AP40: 45766 | AQ40: N | AR40: 水泵
... A72: OO2EWP00900 | B72: 配件 | C72: 水泵 | F72: C | G72: 李莉玲 | H72: 0 | I72: 0 | J72: 19 | K72: 6 | L72: 47 | M72: 72 | N72: 0 | O72: 72 | P72: 5271.7091 | Q72: 5271.7091 | R72: 1 | S72: 1 | T72: 1 | U72: 0 | V72: 0 | W72: 0 | X72: 0 | Y72: 0 | Z72: 73.218182 | AA72: 73.218182 | AB72: 72 | AC72: 72 | AD72: 25 | AE72: 0 | AF72: 19 | AG72: 6 | AH72: 4.5 | AI72: 66 | AJ72: 6 | AK72: 4832.4 | AL72: Others | AM72: 0 | AN72: 1 | AO72: 45368 | AP72: 45351 | AQ72: N | AR72: 水泵
A73: ZC2CLK03000 | B73: 配件 | C73: 水泵 | F73: B | G73: 李莉玲 | H73: 0 | I73: 0 | J73: 18 | K73: 20 | L73: 34 | M73: 72 | N73: 0 | O73: 72 | P73: 3313.4664 | Q73: 3313.4664 | R73: 4 | S73: 9 | T73: 25 | U73: 7 | V73: 18 | W73: 0 | X73: 0 | Y73: 20 | Z73: 46.020366 | AA73: 1150.5092 | AB73: 2.88 | AC73: 2.88 | AD73: 1.52 | AE73: 0 | AF73: 0.72 | AG73: 0.8 | AH73: 4.5 | AI73: 0 | AJ73: 6 | AK73: 0 | AL73: ZonCar | AM73: 0 | AN73: 22 | AP73: 44804 | AQ73: N | AR73: 水泵
A74: OO2EWP03200 | B74: 配件 | C74: 水泵 | F74: C | G74: 李莉玲 | H74: 0 | I74: 0 | J74: 11 | K74: 5 | L74: 55 | M74: 71 | N74: 0 | O74: 71 | P74: 5304.804 | Q74: 5304.804 | R74: 0 | S74: 0 | T74: 0 | U74: 2 | V74: 2 | W74: 0 | X74: 0 | Y74: 0 | Z74: 74.71555 | AA74: 0 | AH74: 4.5 | AI74: 71 | AJ74: 6 | AK74: 5304.804 | AL74: Others | AM74: 0 | AN74: 0 | AO74: 45368 | AP74: 45351 | AQ74: N | AR74: 水泵
A75: ZC2CLK04100 | B75: 配件 | C75: 水泵 | F75: B | G75: 李莉玲 | H75: 14 | I75: 3 | J75: 9 | K75: 12 | L75: 32 | M75: 70 | N75: 0 | O75: 70 | P75: 3231.7098 | Q75: 3231.7098 | R75: 1 | S75: 5 | T75: 14 | U75: 2 | V75: 4 | W75: 0 | X75: 0 | Y75: 0 | Z75: 46.167283 | AA75: 646.34196 | AB75: 5 | AC75: 5 | AD75: 2.7142857 | AE75: 1 | AF75: 0.64285714 | AG75: 0.85714286 | AH75: 4.5 | AI75: 0 | AJ75: 6 | AK75: 0 | AL75: ZonCar | AM75: 5 | AN75: 5 | AO75: 46240 | AP75: 44804 | AQ75: N | AR75: 水泵
A76: OO2EWP11100 | B76: 配件 | C76: 水泵 | F76: B | G76: 李莉玲 | H76: 19 | I76: 0 | J76: 20 | K76: 15 | L76: 14 | M76: 68 | N76: 72 | O76: 140 | P76: 4473.8405 | Q76: 9210.8481 | R76: 7 | S76: 13 | T76: 16 | U76: 11 | V76: 14 | W76: 0 | X76: 0 | Y76: 0 | Z76: 65.791772 | AA76: 1052.6684 | AB76: 8.75 | AC76: 4.25 | AD76: 3.375 | AE76: 1.1875 | AF76: 1.25 | AG76: 0.9375 | AH76: 4.5 | AI76: 0 | AJ76: 6 | AK76: 0 | AL76: Others | AM76: 3 | AN76: 11 | AO76: 46042 | AP76: 45717 | AQ76: N | AR76: 水泵
A77: OO2EWP09800 | B77: 配件 | C77: 水泵 | F77: B | G77: 李莉玲 | H77: 28 | I77: 0 | J77: 19 | K77: 10 | L77: 10 | M77: 67 | N77: 0 | O77: 67 | P77: 3040.6558 | Q77: 3040.6558 | R77: 0 | S77: 3 | T77: 6 | U77: 8 | V77: 4 | W77: 0 | X77: 0 | Y77: 0 | Z77: 45.382923 | AA77: 272.29754 | AB77: 11.166667 | AC77: 11.166667 | AD77: 9.5 | AE77: 4.6666667 | AF77: 3.1666667 | AG77: 1.6666667 | AH77: 4.5 | AI77: 31 | AJ77: 6 | AK77: 1406.8706 | AL77: Others | AM77: 1 | AN77: 4 | AO77: 46012 | AP77: 45757 | AQ77: N | AR77: 水泵
A78: KC2EWP13700 | B78: 配件 | C78: 水泵 | F78: 推新 | G78: 李莉玲 | H78: 0 | I78: 0 | J78: 21 | K78: 12 | L78: 33 | M78: 66 | N78: 0 | O78: 66 | P78: 7709.7345 | Q78: 7709.7345 | R78: 3 | S78: 4 | T78: 6 | U78: 1 | V78: 0 | W78: 20 | X78: 40 | Y78: 40 | Z78: 116.81416 | AA78: 700.88495 | AB78: 11 | AC78: 11 | AD78: 5.5 | AE78: 0 | AF78: 3.5 | AG78: 2 | AH78: 4.5 | AI78: 30 | AJ78: 6 | AK78: 3504.4248 | AL78: KAC | AM78: 0 | AN78: 6 | AP78: 46233 | AQ78: N | AR78: 水泵
A79: OO2EWP11800 | B79: 配件 | C79: 水泵 | F79: B | G79: 李莉玲 | H79: 3 | I79: 0 | J79: 3 | K79: 2 | L79: 58 | M79: 66 | N79: 75 | O79: 141 | P79: 2723.3628 | Q79: 5818.0933 | R79: 4 | S79: 7 | T79: 13 | U79: 14 | V79: 12 | W79: 0 | X79: 0 | Y79: 0 | Z79: 41.263073 | AA79: 536.41995 | AB79: 10.846154 | AC79: 5.0769231 | AD79: 0.61538461 | AE79: 0.23076923 | AF79: 0.23076923 | AG79: 0.15384615 | AH79: 4.5 | AI79: 0 | AJ79: 6 | AK79: 0 | AL79: Others | AM79: 8 | AN79: 5 | AO79: 46200 | AP79: 45688 | AQ79: N | AR79: 水泵
A80: KC2EWP22000 | B80: 配件 | C80: 水泵 | F80: 推新 | G80: 李莉玲 | H80: 6 | I80: 3 | J80: 34 | K80: 14 | L80: 9 | M80: 66 | N80: 200 | O80: 266 | P80: 13836.637 | Q80: 55765.841 | R80: 1 | S80: 2 | T80: 2 | U80: 0 | V80: 0 | W80: 0 | X80: 0 | Y80: 0 | Z80: 209.64602 | AA80: 419.29204 | AB80: 133 | AC80: 33 | AD80: 28.5 | AE80: 3 | AF80: 17 | AG80: 7 | AH80: 4.5 | AI80: 54 | AJ80: 6 | AK80: 11320.885 | AL80: KAC | AM80: 0 | AN80: 2 | AO80: 46283 | AP80: 46255 | AQ80: N | AR80: 水泵
A81: OO2EWP12800 | B81: 配件 | C81: 水泵 | F81: C | G81: 李莉玲 | H81: 7 | I81: 15 | J81: 9 | K81: 11 | L81: 24 | M81: 66 | N81: 0 | O81: 66 | P81: 3855.4879 | Q81: 3855.4879 | R81: 2 | S81: 3 | T81: 5 | U81: 4 | V81: 6 | W81: 24 | X81: 24 | Y81: 24 | Z81: 58.416483 | AA81: 292.08242 | AB81: 13.2 | AC81: 13.2 | AD81: 8.4 | AE81: 1.4 | AF81: 1.8 | AG81: 2.2 | AH81: 4.5 | AI81: 36 | AJ81: 6 | AK81: 2102.9934 | AL81: Others | AM81: 0 | AN81: 3 | AO81: 46279 | AP81: 45765 | AQ81: N | AR81: 水泵
A82: OO2EWP02100 | B82: 配件 | C82: 水泵 | F82: B | G82: 李莉玲 | H82: 5 | I82: 0 | J82: 18 | K82: 8 | L82: 35 | M82: 66 | N82: 0 | O82: 66 | P82: 3215.646 | Q82: 3215.646 | R82: 3 | S82: 4 | T82: 11 | U82: 11 | V82: 12 | W82: 0 | X82: 0 | Y82: 0 | Z82: 48.721909 | AA82: 535.941 | AB82: 6 | AC82: 6 | AD82: 2.8181818 | AE82: 0.45454545 | AF82: 1.6363636 | AG82: 0.72727273 | AH82: 4.5 | AI82: 0 | AJ82: 6 | AK82: 0 | AL82: Others | AM82: 2 | AN82: 7 | AO82: 45368 | AP82: 45366 | AQ82: N | AR82: 水泵
A83: OO2EWP09700 | B83: 配件 | C83: 水泵 | F83: C | G83: 李莉玲 | H83: 15 | I83: 15 | J83: 34 | K83: 0 | L83: 0 | M83: 64 | N83: 20 | O83: 84 | P83: 2212.3276 | Q83: 2903.6799 | R83: 3 | S83: 4 | T83: 5 | U83: 2 | V83: 6 | W83: 0 | X83: 0 | Y83: 0 | Z83: 34.567618 | AA83: 172.83809 | AB83: 16.8 | AC83: 12.8 | AD83: 12.8 | AE83: 3 | AF83: 6.8 | AG83: 0 | AH83: 4.5 | AI83: 34 | AJ83: 6 | AK83: 1175.299 | AL83: Others | AM83: 0 | AN83: 5 | AO83: 46012 | AP83: 45758 | AQ83: N | AR83: 水泵
A84: OO2EWP08900 | B84: 配件 | C84: 水泵 | F84: B | G84: 李莉玲 | H84: 11 | I84: 2 | J84: 21 | K84: 1 | L84: 29 | M84: 64 | N84: 20 | O84: 84 | P84: 2982.3344 | Q84: 3914.3139 | R84: 4 | S84: 5 | T84: 7 | U84: 4 | V84: 1 | W84: 0 | X84: 0 | Y84: 0 | Z84: 46.598975 | AA84: 326.19283 | AB84: 12 | AC84: 9.1428571 | AD84: 5 | AE84: 1.5714286 | AF84: 3 | AG84: 0.14285714 | AH84: 4.5 | AI84: 22 | AJ84: 6 | AK84: 1025.1774 | AL84: Others | AM84: 1 | AN84: 5 | AO84: 46206 | AP84: 45696 | AQ84: N | AR84: 水泵
A85: KC2EWP20400 | B85: 配件 | C85: 水泵 | F85: 推新 | G85: 李莉玲 | H85: 0 | I85: 0 | J85: 19 | K85: 19 | L85: 25 | M85: 63 | N85: 0 | O85: 63 | P85: 4881.1062 | Q85: 4881.1062 | R85: 3 | S85: 4 | T85: 6 | U85: 1 | V85: 0 | W85: 0 | X85: 20 | Y85: 40 | Z85: 77.477876 | AA85: 464.86726 | AB85: 10.5 | AC85: 10.5 | AD85: 6.3333333 | AE85: 0 | AF85: 3.1666667 | AG85: 3.1666667 | AH85: 4.5 | AI85: 27 | AJ85: 6 | AK85: 2091.9027 | AL85: KAC | AM85: 0 | AN85: 6 | AP85: 46253 | AQ85: N | AR85: 水泵
A86: OO2EWP09600 | B86: 配件 | C86: 水泵 | F86: B | G86: 李莉玲 | H86: 3 | I86: 2 | J86: 12 | K86: 6 | L86: 39 | M86: 62 | N86: 0 | O86: 62 | P86: 2360.3123 | Q86: 2360.3123 | R86: 3 | S86: 5 | T86: 11 | U86: 7 | V86: 6 | W86: 40 | X86: 40 | Y86: 40 | Z86: 38.069553 | AA86: 418.76508 | AB86: 5.6363636 | AC86: 5.6363636 | AD86: 2.0909091 | AE86: 0.27272727 | AF86: 1.0909091 | AG86: 0.54545455 | AH86: 4.5 | AI86: 0 | AJ86: 6 | AK86: 0 | AL86: Others | AM86: 9 | AN86: 2 | AO86: 46207 | AP86: 45758 | AQ86: N | AR86: 水泵
A87: KC2EWP17900 | B87: 配件 | C87: 水泵 | F87: 推新 | G87: 李莉玲 | H87: 0 | I87: 0 | J87: 21 | K87: 40 | L87: 1 | M87: 62 | N87: 0 | O87: 62 | P87: 25513.274 | Q87: 25513.274 | R87: 1 | S87: 2 | T87: 3 | U87: 0 | V87: 0 | W87: 0 | X87: 24 | Y87: 24 | Z87: 411.50443 | AA87: 1234.5133 | AB87: 20.666667 | AC87: 20.666667 | AD87: 20.333333 | AE87: 0 | AF87: 7 | AG87: 13.333333 | AH87: 4.5 | AI87: 44 | AJ87: 6 | AK87: 18106.195 | AL87: KAC | AM87: 0 | AN87: 3 | AP87: 46233 | AQ87: N | AR87: 水泵
A88: OO2EWP09400 | B88: 配件 | C88: 水泵 | F88: C | G88: 李莉玲 | H88: 19 | I88: 0 | J88: 17 | K88: 1 | L88: 24 | M88: 61 | N88: 0 | O88: 61 | P88: 4862.7788 | Q88: 4862.7788 | R88: 0 | S88: 0 | T88: 0 | U88: 2 | V88: 3 | W88: 0 | X88: 24 | Y88: 24 | Z88: 79.717686 | AA88: 0 | AH88: 4.5 | AI88: 61 | AJ88: 6 | AK88: 4862.7788 | AL88: Others | AM88: 0 | AN88: 0 | AO88: 46184 | AP88: 45765 | AQ88: N | AR88: 水泵
A89: OO2EWP02700 | B89: 配件 | C89: 水泵 | F89: B | G89: 李莉玲 | H89: 16 | I89: 0 | J89: 26 | K89: 10 | L89: 8 | M89: 60 | N89: 32 | O89: 92 | P89: 3723.5681 | Q89: 5709.4711 | R89: 3 | S89: 5 | T89: 9 | U89: 6 | V89: 6 | W89: 0 | X89: 0 | Y89: 0 | Z89: 62.059468 | AA89: 558.53521 | AB89: 10.222222 | AC89: 6.6666667 | AD89: 5.7777778 | AE89: 1.7777778 | AF89: 2.8888889 | AG89: 1.1111111 | AH89: 4.5 | AI89: 6 | AJ89: 6 | AK89: 372.35681 | AL89: Others | AM89: 2 | AN89: 6 | AO89: 45368 | AP89: 45366 | AQ89: N | AR89: 水泵
A90: OO2EWP00300 | B90: 配件 | C90: 水泵 | F90: D | G90: 李莉玲 | H90: 1 | I90: 0 | J90: 1 | K90: 4 | L90: 54 | M90: 60 | N90: 0 | O90: 60 | P90: 15164.541 | Q90: 15164.541 | R90: 0 | S90: 0 | T90: 3 | U90: 1 | V90: 2 | W90: 0 | X90: 0 | Y90: 0 | Z90: 252.74235 | AA90: 758.22704 | AB90: 20 | AC90: 20 | AD90: 2 | AE90: 0.33333333 | AF90: 0.33333333 | AG90: 1.3333333 | AH90: 4.5 | AI90: 42 | AJ90: 6 | AK90: 10615.178 | AL90: Others | AM90: 0 | AN90: 3 | AO90: 45368 | AP90: 45351 | AQ90: N | AR90: 水泵
A91: OO2EWP10500 | B91: 配件 | C91: 水泵 | F91: C | G91: 李莉玲 | H91: 0 | I91: 0 | J91: 11 | K91: 6 | L91: 42 | M91: 59 | N91: 0 | O91: 59 | P91: 3603.9397 | Q91: 3603.9397 | R91: 0 | S91: 1 | T91: 1 | U91: 3 | V91: 2 | W91: 0 | X91: 0 | Y91: 0 | Z91: 61.083723 | AA91: 61.083723 | AB91: 59 | AC91: 59 | AD91: 17 | AE91: 0 | AF91: 11 | AG91: 6 | AH91: 4.5 | AI91: 53 | AJ91: 6 | AK91: 3237.4373 | AL91: Others | AM91: 0 | AN91: 1 | AP91: 45765 | AQ91: N | AR91: 水泵
A92: ZC2CLK02000 | B92: 配件 | C92: 水泵 | F92: C | G92: 李莉玲 | H92: 1 | I92: 1 | J92: 14 | K92: 10 | L92: 31 | M92: 57 | N92: 20 | O92: 77 | P92: 2624.0437 | Q92: 3544.7608 | R92: 1 | S92: 2 | T92: 2 | U92: 6 | V92: 2 | W92: 20 | X92: 20 | Y92: 20 | Z92: 46.035855 | AA92: 92.07171 | AB92: 38.5 | AC92: 28.5 | AD92: 13 | AE92: 0.5 | AF92: 7 | AG92: 5 | AH92: 4.5 | AI92: 45 | AJ92: 6 | AK92: 2071.6135 | AL92: ZonCar | AM92: 0 | AN92: 1 | AO92: 46279 | AP92: 44804 | AQ92: N | AR92: 水泵
A93: KC2EWP26400 | B93: 配件 | C93: 水泵 | F93: 推新 | G93: 李莉玲 | H93: 0 | I93: 15 | J93: 14 | K93: 14 | L93: 12 | M93: 55 | N93: 0 | O93: 55 | P93: 2506.6372 | Q93: 2506.6372 | R93: 1 | S93: 2 | T93: 4 | U93: 2 | V93: 0 | W93: 0 | X93: 0 | Y93: 0 | Z93: 45.575221 | AA93: 182.30088 | AB93: 13.75 | AC93: 13.75 | AD93: 10.75 | AE93: 0 | AF93: 3.5 | AG93: 3.5 | AH93: 4.5 | AI93: 31 | AJ93: 6 | AK93: 1412.8319 | AL93: KAC | AM93: 0 | AN93: 4 | AP93: 46233 | AQ93: N | AR93: 水泵
A94: OO2EWP03100 | B94: 配件 | C94: 水泵 | F94: B | G94: 李莉玲 | H94: 9 | I94: 0 | J94: 8 | K94: 26 | L94: 12 | M94: 55 | N94: 120 | O94: 175 | P94: 4490.8537 | Q94: 14289.08 | R94: 3 | S94: 9 | T94: 16 | U94: 26 | V94: 16 | W94: 0 | X94: 0 | Y94: 0 | Z94: 81.651885 | AA94: 1306.4302 | AB94: 10.9375 | AC94: 3.4375 | AD94: 2.6875 | AE94: 0.5625 | AF94: 0.5 | AG94: 1.625 | AH94: 4.5 | AI94: 0 | AJ94: 6 | AK94: 0 | AL94: Others | AM94: 0 | AN94: 16 | AO94: 45368 | AP94: 45351 | AQ94: N | AR94: 水泵
A95: KC2EWP24900 | B95: 配件 | C95: 水泵 | F95: 推新 | G95: 李莉玲 | H95: 5 | I95: 15 | J95: 5 | K95: 2 | L95: 26 | M95: 53 | N95: 0 | O95: 53 | P95: 3142.4779 | Q95: 3142.4779 | R95: 1 | S95: 1 | T95: 1 | U95: 0 | V95: 0 | W95: 0 | X95: 0 | Y95: 24 | Z95: 59.292035 | AA95: 59.292035 | AB95: 53 | AC95: 53 | AD95: 27 | AE95: 5 | AF95: 5 | AG95: 2 | AH95: 4.5 | AI95: 47 | AJ95: 6 | AK95: 2786.7256 | AL95: KAC | AM95: 0 | AN95: 1 | AO95: 46274 | AP95: 46275 | AQ95: N | AR95: 水泵
A96: OO2EWP06800 | B96: 配件 | C96: 水泵 | F96: A | G96: 李莉玲 | H96: 16 | I96: 0 | J96: 8 | K96: 12 | L96: 17 | M96: 53 | N96: 64 | O96: 117 | P96: 6382.551 | Q96: 14089.782 | R96: 1 | S96: 7 | T96: 17 | U96: 19 | V96: 17 | W96: 0 | X96: 0 | Y96: 20 | Z96: 120.42549 | AA96: 2047.2333 | AB96: 6.8823529 | AC96: 3.1176471 | AD96: 2.1176471 | AE96: 0.94117647 | AF96: 0.47058824 | AG96: 0.70588235 | AH96: 4.5 | AI96: 0 | AJ96: 6 | AK96: 0 | AL96: Others | AM96: 14 | AN96: 1 | AO96: 46044 | AP96: 45798 | AQ96: N | AR96: 水泵
A97: OO2EWP05400 | B97: 配件 | C97: 水泵 | F97: C | G97: 李莉玲 | H97: 14 | I97: 0 | J97: 7 | K97: 9 | L97: 23 | M97: 53 | N97: 40 | O97: 93 | P97: 2256.5367 | Q97: 3959.5833 | R97: 2 | S97: 2 | T97: 6 | U97: 9 | V97: 6 | W97: 0 | X97: 0 | Y97: 0 | Z97: 42.576164 | AA97: 255.45698 | AB97: 15.5 | AC97: 8.8333333 | AD97: 5 | AE97: 2.3333333 | AF97: 1.1666667 | AG97: 1.5 | AH97: 4.5 | AI97: 17 | AJ97: 6 | AK97: 723.79479 | AL97: Others | AM97: 1 | AN97: 2 | AO97: 46140 | AP97: 45757 | AQ97: N | AR97: 水泵
A98: OO2EWP01200 | B98: 配件 | C98: 水泵 | F98: B | G98: 李莉玲 | H98: 0 | I98: 0 | J98: 11 | K98: 42 | L98: 0 | M98: 53 | N98: 72 | O98: 125 | P98: 5488.7521 | Q98: 12945.17 | R98: 0 | S98: 2 | T98: 10 | U98: 14 | V98: 14 | W98: 0 | X98: 0 | Y98: 0 | Z98: 103.56136 | AA98: 1035.6136 | AB98: 12.5 | AC98: 5.3 | AD98: 5.3 | AE98: 0 | AF98: 1.1 | AG98: 4.2 | AH98: 4.5 | AI98: 0 | AJ98: 6 | AK98: 0 | AL98: Others | AM98: 0 | AN98: 10 | AO98: 45368 | AP98: 45351 | AQ98: N | AR98: 水泵
A99: OO2EWP03400 | B99: 配件 | C99: 水泵 | F99: B | G99: 李莉玲 | H99: 9 | I99: 1 | J99: 22 | K99: 3 | L99: 17 | M99: 52 | N99: 0 | O99: 52 | P99: 2487.9755 | Q99: 2487.9755 | R99: 6 | S99: 8 | T99: 10 | U99: 6 | V99: 6 | W99: 0 | X99: 0 | Y99: 20 | Z99: 47.845682 | AA99: 478.45682 | AB99: 5.2 | AC99: 5.2 | AD99: 3.5 | AE99: 0.9 | AF99: 2.2 | AG99: 0.3 | AH99: 4.5 | AI99: 0 | AJ99: 6 | AK99: 0 | AL99: Others | AM99: 5 | AN99: 5 | AO99: 45368 | AP99: 45351 | AQ99: N | AR99: 水泵
A100: OO2EWP04400 | B100: 配件 | C100: 水泵 | F100: B | G100: 李莉玲 | H100: 19 | I100: 0 | J100: 8 | K100: 24 | L100: 0 | M100: 51 | N100: 114 | O100: 165 | P100: 5236.0112 | Q100: 16940.036 | R100: 3 | S100: 8 | T100: 13 | U100: 22 | V100: 12 | W100: 0 | X100: 0 | Y100: 0 | Z100: 102.66689 | AA100: 1334.6695 | AB100: 12.692308 | AC100: 3.9230769 | AD100: 3.9230769 | AE100: 1.4615385 | AF100: 0.61538461 | AG100: 1.8461538 | AH100: 4.5 | AI100: 0 | AJ100: 6 | AK100: 0 | AL100: Others | AM100: 2 | AN100: 11 | AO100: 46165 | AP100: 45756 | AQ100: N | AR100: 水泵
A101: KC2EWP22700 | B101: 配件 | C101: 水泵 | F101: 推新 | G101: 李莉玲 | H101: 0 | I101: 0 | J101: 30 | K101: 0 | L101: 21 | M101: 51 | N101: 0 | O101: 51 | P101: 2888.4956 | Q101: 2888.4956 | R101: 0 | S101: 0 | T101: 0 | U101: 0 | V101: 0 | W101: 0 | X101: 20 | Y101: 20 | Z101: 56.637168 | AA101: 0 | AH101: 4.5 | AI101: 51 | AJ101: 6 | AK101: 2888.4956 | AL101: KAC | AM101: 0 | AN101: 0 | AP101: 46270 | AQ101: N | AR101: 水泵
A102: OO2EWP11900 | B102: 配件 | C102: 水泵 | F102: B | G102: 李莉玲 | H102: 6 | I102: 0 | J102: 1 | K102: 23 | L102: 21 | M102: 51 | N102: 18 | O102: 69 | P102: 9136.4428 | Q102: 12361.07 | R102: 2 | S102: 6 | T102: 13 | U102: 8 | V102: 11 | W102: 0 | X102: 30 | Y102: 30 | Z102: 179.14594 | AA102: 2328.8972 | AB102: 5.3076923 | AC102: 3.9230769 | AD102: 2.3076923 | AE102: 0.46153846 | AF102: 0.076923077 | AG102: 1.7692308 | AH102: 4.5 | AI102: 0 | AJ102: 6 | AK102: 0 | AL102: Others | AM102: 8 | AN102: 4 | AO102: 46188 | AP102: 45717 | AQ102: N | AR102: 水泵
A103: OO2EWP10300 | B103: 配件 | C103: 水泵 | F103: C | G103: 李莉玲 | H103: 10 | I103: 3 | J103: 15 | K103: 0 | L103: 22 | M103: 50 | N103: 0 | O103: 50 | P103: 2348.2895 | Q103: 2348.2895 | R103: 0 | S103: 0 | T103: 2 | U103: 1 | V103: 0 | W103: 0 | X103: 0 | Y103: 0 | Z103: 46.96579 | AA103: 93.93158 | AB103: 25 | AC103: 25 | AD103: 14 | AE103: 5 | AF103: 7.5 | AG103: 0 | AH103: 4.5 | AI103: 38 | AJ103: 6 | AK103: 1784.7 | AL103: Others | AM103: 1 | AN103: 1 | AO103: 46206 | AP103: 45765 | AQ103: N | AR103: 水泵
A104: ZC2CLK02900 | B104: 配件 | C104: 水泵 | F104: A | G104: 李莉玲 | H104: 11 | I104: 21 | J104: 11 | K104: 6 | L104: 0 | M104: 49 | N104: 21 | O104: 70 | P104: 5470.7178 | Q104: 7815.3112 | R104: 0 | S104: 3 | T104: 5 | U104: 7 | V104: 4 | W104: 0 | X104: 0 | Y104: 0 | Z104: 111.6473 | AA104: 558.23652 | AB104: 14 | AC104: 9.8 | AD104: 9.8 | AE104: 2.2 | AF104: 2.2 | AG104: 1.2 | AH104: 4.5 | AI104: 19 | AJ104: 6 | AK104: 2121.2988 | AL104: ZonCar | AM104: 1 | AN104: 4 | AO104: 46293 | AP104: 44672 | AQ104: N | AR104: 水泵
A105: KC2EWP16700 | B105: 配件 | C105: 水泵 | F105: 推新 | G105: 李莉玲 | H105: 16 | I105: 16 | J105: 8 | K105: 7 | L105: 2 | M105: 49 | N105: 20 | O105: 69 | P105: 2590.4956 | Q105: 3647.8407 | R105: 1 | S105: 4 | T105: 6 | U105: 0 | V105: 0 | W105: 0 | X105: 0 | Y105: 0 | Z105: 52.867257 | AA105: 317.20354 | AB105: 11.5 | AC105: 8.1666667 | AD105: 7.8333333 | AE105: 2.6666667 | AF105: 1.3333333 | AG105: 1.1666667 | AH105: 4.5 | AI105: 13 | AJ105: 6 | AK105: 687.27434 | AL105: KAC | AM105: 0 | AN105: 6 | AO105: 46274 | AP105: 46277 | AQ105: N | AR105: 水泵
A106: KC2EWP15500 | B106: 配件 | C106: 水泵 | F106: 推新 | G106: 李莉玲 | H106: 0 | I106: 0 | J106: 21 | K106: 0 | L106: 25 | M106: 46 | N106: 0 | O106: 46 | P106: 2605.3097 | Q106: 2605.3097 | R106: 1 | S106: 2 | T106: 3 | U106: 0 | V106: 0 | W106: 0 | X106: 24 | Y106: 24 | Z106: 56.637168 | AA106: 169.9115 | AB106: 15.333333 | AC106: 15.333333 | AD106: 7 | AE106: 0 | AF106: 7 | AG106: 0 | AH106: 4.5 | AI106: 28 | AJ106: 6 | AK106: 1585.8407 | AL106: KAC | AM106: 0 | AN106: 3 | AP106: 46270 | AQ106: N | AR106: 水泵
A107: KC2EWP27200 | B107: 配件 | C107: 水泵 | F107: 推新 | G107: 李莉玲 | H107: 5 | I107: 18 | J107: 15 | K107: 7 | L107: 1 | M107: 46 | N107: 40 | O107: 86 | P107: 2641.5398 | Q107: 4938.531 | R107: 0 | S107: 0 | T107: 0 | U107: 0 | V107: 0 | W107: 0 | X107: 0 | Y107: 0 | Z107: 57.424779 | AA107: 0 | AH107: 4.5 | AI107: 46 | AJ107: 6 | AK107: 2641.5398 | AL107: KAC | AM107: 0 | AN107: 0 | AO107: 46279 | AP107: 46257 | AQ107: N | AR107: 水泵
A108: OO2EWP10100 | B108: 配件 | C108: 水泵 | F108: B | G108: 李莉玲 | H108: 4 | I108: 0 | J108: 12 | K108: 6 | L108: 24 | M108: 46 | N108: 36 | O108: 82 | P108: 5617.9696 | Q108: 10014.641 | R108: 3 | S108: 4 | T108: 11 | U108: 6 | V108: 7 | W108: 12 | X108: 12 | Y108: 12 | Z108: 122.12977 | AA108: 1343.4275 | AB108: 7.4545455 | AC108: 4.1818182 | AD108: 2 | AE108: 0.36363636 | AF108: 1.0909091 | AG108: 0.54545455 | AH108: 4.5 | AI108: 0 | AJ108: 6 | AK108: 0 | AL108: Others | AM108: 3 | AN108: 7 | AO108: 46139 | AP108: 45765 | AQ108: N | AR108: 水泵
A109: KC2EWP25400 | B109: 配件 | C109: 水泵 | F109: 推新 | G109: 李莉玲 | H109: 0 | I109: 0 | J109: 22 | K109: 3 | L109: 21 | M109: 46 | N109: 0 | O109: 46 | P109: 4612.2124 | Q109: 4612.2124 | R109: 1 | S109: 2 | T109: 5 | U109: 0 | V109: 0 | W109: 0 | X109: 20 | Y109: 20 | Z109: 100.26549 | AA109: 501.32743 | AB109: 9.2 | AC109: 9.2 | AD109: 5 | AE109: 0 | AF109: 4.4 | AG109: 0.6 | AH109: 4.5 | AI109: 16 | AJ109: 6 | AK109: 1604.2478 | AL109: KAC | AM109: 0 | AN109: 5 | AP109: 46233 | AQ109: N | AR109: 水泵
A110: OO2EWP11200 | B110: 配件 | C110: 水泵 | F110: D | G110: 李莉玲 | H110: 9 | I110: 2 | J110: 18 | K110: 3 | L110: 13 | M110: 45 | N110: 40 | O110: 85 | P110: 2429.2035 | Q110: 4588.4955 | R110: 1 | S110: 1 | T110: 2 | U110: 5 | V110: 0 | W110: 0 | X110: 0 | Y110: 0 | Z110: 53.9823 | AA110: 107.9646 | AB110: 42.5 | AC110: 22.5 | AD110: 16 | AE110: 4.5 | AF110: 9 | AG110: 1.5 | AH110: 4.5 | AI110: 33 | AJ110: 6 | AK110: 1781.4159 | AL110: Others | AM110: 1 | AN110: 1 | AO110: 46000 | AP110: 45717 | AQ110: N | AR110: 水泵
A111: OO2EWP05300 | B111: 配件 | C111: 水泵 | F111: B | G111: 李莉玲 | H111: 5 | I111: 0 | J111: 12 | K111: 2 | L111: 26 | M111: 45 | N111: 24 | O111: 69 | P111: 3113.0945 | Q111: 4773.4116 | R111: 2 | S111: 2 | T111: 4 | U111: 4 | V111: 11 | W111: 0 | X111: 0 | Y111: 0 | Z111: 69.179878 | AA111: 276.71951 | AB111: 17.25 | AC111: 11.25 | AD111: 4.75 | AE111: 1.25 | AF111: 3 | AG111: 0.5 | AH111: 4.5 | AI111: 21 | AJ111: 6 | AK111: 1452.7774 | AL111: Others | AM111: 2 | AN111: 2 | AO111: 46200 | AP111: 45760 | AQ111: N | AR111: 水泵
A112: OO2EWP00800 | B112: 配件 | C112: 水泵 | F112: C | G112: 李莉玲 | H112: 0 | I112: 0 | J112: 31 | K112: 6 | L112: 7 | M112: 44 | N112: 0 | O112: 44 | P112: 11007.466 | Q112: 11007.466 | R112: 1 | S112: 4 | T112: 4 | U112: 1 | V112: 7 | W112: 0 | X112: 0 | Y112: 0 | Z112: 250.16968 | AA112: 1000.6787 | AB112: 11 | AC112: 11 | AD112: 9.25 | AE112: 0 | AF112: 7.75 | AG112: 1.5 | AH112: 4.5 | AI112: 20 | AJ112: 6 | AK112: 5003.3937 | AL112: Others | AM112: 0 | AN112: 3 | AO112: 45368 | AP112: 45382 | AQ112: N | AR112: 水泵
A113: OO2EWP03300 | B113: 配件 | C113: 水泵 | F113: B | G113: 李莉玲 | H113: 1 | I113: 0 | J113: 12 | K113: 4 | L113: 25 | M113: 42 | N113: 0 | O113: 42 | P113: 8238.4731 | Q113: 8238.4731 | R113: 0 | S113: 1 | T113: 1 | U113: 5 | V113: 5 | W113: 0 | X113: 0 | Y113: 0 | Z113: 196.15412 | AA113: 196.15412 | AB113: 42 | AC113: 42 | AD113: 17 | AE113: 1 | AF113: 12 | AG113: 4 | AH113: 4.5 | AI113: 36 | AJ113: 6 | AK113: 7061.5484 | AL113: Others | AM113: 0 | AN113: 1 | AO113: 45368 | AP113: 45351 | AQ113: N | AR113: 水泵
A114: OO2EWP09300 | B114: 配件 | C114: 水泵 | F114: B | G114: 李莉玲 | H114: 9 | I114: 0 | J114: 12 | K114: 7 | L114: 14 | M114: 42 | N114: 0 | O114: 42 | P114: 1637.7174 | Q114: 1637.7174 | R114: 2 | S114: 3 | T114: 7 | U114: 3 | V114: 1 | W114: 0 | X114: 0 | Y114: 0 | Z114: 38.993272 | AA114: 272.9529 | AB114: 6 | AC114: 6 | AD114: 4 | AE114: 1.2857143 | AF114: 1.7142857 | AG114: 1 | AH114: 4.5 | AI114: 0 | AJ114: 6 | AK114: 0 | AL114: Others | AM114: 3 | AN114: 4 | AO114: 46208 | AP114: 45765 | AQ114: N | AR114: 水泵
A115: KC2EWP25900 | B115: 配件 | C115: 水泵 | F115: 推新 | G115: 李莉玲 | H115: 0 | I115: 24 | J115: 12 | K115: 4 | L115: 1 | M115: 41 | N115: 40 | O115: 81 | P115: 2055.4425 | Q115: 4060.7522 | R115: 0 | S115: 0 | T115: 0 | U115: 0 | V115: 0 | W115: 0 | X115: 0 | Y115: 0 | Z115: 50.132743 | AA115: 0 | AH115: 4.5 | AI115: 41 | AJ115: 6 | AK115: 2055.4425 | AL115: KAC | AM115: 0 | AN115: 0 | AP115: 46296 | AQ115: N | AR115: 水泵
A116: OO2EWP02500 | B116: 配件 | C116: 水泵 | F116: D | G116: 李莉玲 | H116: 6 | I116: 0 | J116: 10 | K116: 2 | L116: 23 | M116: 41 | N116: 24 | O116: 65 | P116: 4047.9839 | Q116: 6417.5355 | R116: 2 | S116: 4 | T116: 5 | U116: 3 | V116: 9 | W116: 0 | X116: 0 | Y116: 19 | Z116: 98.731315 | AA116: 493.65657 | AB116: 13 | AC116: 8.2 | AD116: 3.6 | AE116: 1.2 | AF116: 2 | AG116: 0.4 | AH116: 4.5 | AI116: 11 | AJ116: 6 | AK116: 1086.0445 | AL116: Others | AM116: 0 | AN116: 5 | AO116: 45368 | AP116: 45351 | AQ116: N | AR116: 水泵
A117: KC2EWP16600 | B117: 配件 | C117: 水泵 | F117: 推新 | G117: 李莉玲 | H117: 0 | I117: 0 | J117: 4 | K117: 17 | L117: 20 | M117: 41 | N117: 0 | O117: 41 | P117: 3363.4513 | Q117: 3363.4513 | R117: 0 | S117: 0 | T117: 0 | U117: 0 | V117: 0 | W117: 0 | X117: 0 | Y117: 0 | Z117: 82.035398 | AA117: 0 | AH117: 4.5 | AI117: 41 | AJ117: 6 | AK117: 3363.4513 | AL117: KAC | AM117: 0 | AN117: 0 | AP117: 46271 | AQ117: N | AR117: 水泵
A118: KC2EWP24400 | B118: 配件 | C118: 水泵 | F118: 交付 | G118: 李莉玲 | H118: 0 | I118: 0 | J118: 0 | K118: 14 | L118: 27 | M118: 41 | N118: 0 | O118: 41 | P118: 1681.7257 | Q118: 1681.7257 | R118: 0 | S118: 0 | T118: 0 | U118: 0 | V118: 0 | W118: 0 | X118: 0 | Y118: 0 | Z118: 41.017699 | AA118: 0 | AH118: 4.5 | AI118: 41 | AJ118: 6 | AK118: 1681.7257 | AL118: KAC | AM118: 0 | AN118: 0 | AQ118: N | AR118: 水泵
A119: KC2EWP27000 | B119: 配件 | C119: 水泵 | F119: 推新 | G119: 李莉玲 | H119: 0 | I119: 0 | J119: 2 | K119: 12 | L119: 27 | M119: 41 | N119: 0 | O119: 41 | P119: 1719.0974 | Q119: 1719.0974 | R119: 0 | S119: 0 | T119: 0 | U119: 0 | V119: 0 | W119: 0 | X119: 0 | Y119: 0 | Z119: 41.929204 | AA119: 0 | AH119: 4.5 | AI119: 41 | AJ119: 6 | AK119: 1719.0974 | AL119: KAC | AM119: 0 | AN119: 0 | AP119: 46303 | AQ119: N | AR119: 水泵
A120: KC2EWP15300 | B120: 配件 | C120: 水泵 | F120: 交付 | G120: 李莉玲 | H120: 0 | I120: 0 | J120: 0 | K120: 30 | L120: 11 | M120: 41 | N120: 100 | O120: 141 | P120: 2552.2124 | Q120: 8777.1207 | R120: 0 | S120: 0 | T120: 0 | U120: 0 | V120: 0 | W120: 0 | X120: 0 | Y120: 0 | Z120: 62.249083 | AA120: 0 | AH120: 4.5 | AI120: 41 | AJ120: 6 | AK120: 2552.2124 | AL120: KAC | AM120: 0 | AN120: 0 | AQ120: N | AR120: 水泵
A121: OO2EWP05600 | B121: 配件 | C121: 水泵 | F121: B | G121: 李莉玲 | H121: 31 | I121: 0 | J121: 1 | K121: 7 | L121: 2 | M121: 41 | N121: 24 | O121: 65 | P121: 3304.3123 | Q121: 5238.5438 | R121: 2 | S121: 4 | T121: 10 | U121: 5 | V121: 8 | W121: 0 | X121: 0 | Y121: 0 | Z121: 80.592982 | AA121: 805.92982 | AB121: 6.5 | AC121: 4.1 | AD121: 3.9 | AE121: 3.1 | AF121: 0.1 | AG121: 0.7 | AH121: 4.5 | AI121: 0 | AJ121: 6 | AK121: 0 | AL121: Others | AM121: 3 | AN121: 6 | AO121: 46035 | AP121: 45770 | AQ121: N | AR121: 水泵
A122: KC2EWP18000 | B122: 配件 | C122: 水泵 | F122: 推新 | G122: 李莉玲 | H122: 0 | I122: 0 | J122: 18 | K122: 2 | L122: 20 | M122: 40 | N122: 0 | O122: 40 | P122: 1640.708 | Q122: 1640.708 | R122: 0 | S122: 0 | T122: 1 | U122: 0 | V122: 0 | W122: 0 | X122: 0 | Y122: 20 | Z122: 41.017699 | AA122: 41.017699 | AB122: 40 | AC122: 40 | AD122: 20 | AE122: 0 | AF122: 18 | AG122: 2 | AH122: 4.5 | AI122: 34 | AJ122: 6 | AK122: 1394.6018 | AL122: KAC | AM122: 0 | AN122: 1 | AP122: 46203 | AQ122: N | AR122: 水泵
A123: KC2EWP19400 | B123: 配件 | C123: 水泵 | F123: 推新 | G123: 李莉玲 | H123: 0 | I123: 2 | J123: 12 | K123: 9 | L123: 17 | M123: 40 | N123: 0 | O123: 40 | P123: 2442.4779 | Q123: 2442.4779 | R123: 0 | S123: 0 | T123: 1 | U123: 0 | V123: 0 | W123: 0 | X123: 0 | Y123: 20 | Z123: 61.061947 | AA123: 61.061947 | AB123: 40 | AC123: 40 | AD123: 23 | AE123: 0 | AF123: 12 | AG123: 9 | AH123: 4.5 | AI123: 34 | AJ123: 6 | AK123: 2076.1062 | AL123: KAC | AM123: 0 | AN123: 1 | AP123: 46233 | AQ123: N | AR123: 水泵
A124: OO2EWP12200 | B124: 配件 | C124: 水泵 | F124: A | G124: 李莉玲 | H124: 4 | I124: 2 | J124: 4 | K124: 26 | L124: 3 | M124: 39 | N124: 72 | O124: 111 | P124: 5851.6593 | Q124: 16654.722 | R124: 5 | S124: 10 | T124: 20 | U124: 13 | V124: 6 | W124: 0 | X124: 0 | Y124: 0 | Z124: 150.04254 | AA124: 3000.8509 | AB124: 5.55 | AC124: 1.95 | AD124: 1.8 | AE124: 0.2 | AF124: 0.2 | AG124: 1.3 | AH124: 4.5 | AI124: 0 | AJ124: 6 | AK124: 0 | AL124: Others | AM124: 6 | AN124: 13 | AO124: 46209 | AP124: 45758 | AQ124: N | AR124: 水泵
A125: KC2EWP14200 | B125: 配件 | C125: 水泵 | F125: 推新 | G125: 李莉玲 | H125: 0 | I125: 0 | J125: 18 | K125: 12 | L125: 9 | M125: 39 | N125: 20 | O125: 59 | P125: 4555.7522 | Q125: 6892.0354 | R125: 1 | S125: 1 | T125: 2 | U125: 0 | V125: 0 | W125: 0 | X125: 0 | Y125: 0 | Z125: 116.81416 | AA125: 233.62832 | AB125: 29.5 | AC125: 19.5 | AD125: 15 | AE125: 0 | AF125: 9 | AG125: 6 | AH125: 4.5 | AI125: 27 | AJ125: 6 | AK125: 3153.9823 | AL125: KAC | AM125: 0 | AN125: 2 | AP125: 46232 | AQ125: N | AR125: 水泵
A126: KC2EWP18900 | B126: 配件 | C126: 水泵 | F126: 推新 | G126: 李莉玲 | H126: 4 | I126: 0 | J126: 9 | K126: 11 | L126: 15 | M126: 39 | N126: 0 | O126: 39 | P126: 3874.8053 | Q126: 3874.8053 | R126: 2 | S126: 4 | T126: 5 | U126: 2 | V126: 0 | W126: 0 | X126: 0 | Y126: 24 | Z126: 99.353982 | AA126: 496.76991 | AB126: 7.8 | AC126: 7.8 | AD126: 4.8 | AE126: 0.8 | AF126: 1.8 | AG126: 2.2 | AH126: 4.5 | AI126: 9 | AJ126: 6 | AK126: 894.18584 | AL126: KAC | AM126: 0 | AN126: 5 | AO126: 46303 | AP126: 46203 | AQ126: N | AR126: 水泵
A127: KC2EWP13100 | B127: 配件 | C127: 水泵 | F127: 推新 | G127: 李莉玲 | H127: 0 | I127: 0 | J127: 8 | K127: 8 | L127: 23 | M127: 39 | N127: 0 | O127: 39 | P127: 1656.6372 | Q127: 1656.6372 | R127: 0 | S127: 0 | T127: 1 | U127: 1 | V127: 0 | W127: 20 | X127: 20 | Y127: 20 | Z127: 42.477876 | AA127: 42.477876 | AB127: 39 | AC127: 39 | AD127: 16 | AE127: 0 | AF127: 8 | AG127: 8 | AH127: 4.5 | AI127: 33 | AJ127: 6 | AK127: 1401.7699 | AL127: KAC | AM127: 0 | AN127: 1 | AP127: 46233 | AQ127: N | AR127: 水泵
A128: OO2EWP01800 | B128: 配件 | C128: 水泵 | F128: D | G128: 李莉玲 | H128: 4 | I128: 0 | J128: 8 | K128: 11 | L128: 16 | M128: 39 | N128: 18 | O128: 57 | P128: 4910.4221 | Q128: 7176.7708 | R128: 1 | S128: 4 | T128: 10 | U128: 9 | V128: 7 | W128: 0 | X128: 0 | Y128: 0 | Z128: 125.90826 | AA128: 1259.0826 | AB128: 5.7 | AC128: 3.9 | AD128: 2.3 | AE128: 0.4 | AF128: 0.8 | AG128: 1.1 | AH128: 4.5 | AI128: 0 | AJ128: 6 | AK128: 0 | AL128: Others | AM128: 7 | AN128: 3 | AO128: 45368 | AP128: 45351 | AQ128: N | AR128: 水泵
A129: OO2EWP12100 | B129: 配件 | C129: 水泵 | F129: C | G129: 李莉玲 | H129: 4 | I129: 0 | J129: 14 | K129: 0 | L129: 20 | M129: 38 | N129: 20 | O129: 58 | P129: 2458.4888 | Q129: 3752.4302 | R129: 1 | S129: 1 | T129: 3 | U129: 0 | V129: 8 | W129: 0 | X129: 0 | Y129: 20 | Z129: 64.697073 | AA129: 194.09122 | AB129: 19.333333 | AC129: 12.666667 | AD129: 6 | AE129: 1.3333333 | AF129: 4.6666667 | AG129: 0 | AH129: 4.5 | AI129: 20 | AJ129: 6 | AK129: 1293.9415 | AL129: Others | AM129: 2 | AN129: 0 | AO129: 46208 | AP129: 45717 | AQ129: N | AR129: 水泵
A130: ZC2CLK04700 | B130: 配件 | C130: 水泵 | F130: A | G130: 李莉玲 | H130: 5 | I130: 0 | J130: 13 | K130: 0 | L130: 20 | M130: 38 | N130: 80 | O130: 118 | P130: 1513.2743 | Q130: 4699.1151 | R130: 3 | S130: 8 | T130: 17 | U130: 16 | V130: 9 | W130: 0 | X130: 0 | Y130: 0 | Z130: 39.823009 | AA130: 676.99115 | AB130: 6.9411765 | AC130: 2.2352941 | AD130: 1.0588235 | AE130: 0.29411765 | AF130: 0.76470588 | AG130: 0 | AH130: 4.5 | AI130: 0 | AJ130: 6 | AK130: 0 | AL130: ZonCar | AM130: 11 | AN130: 6 | AO130: 46139 | AP130: 44804 | AQ130: N | AR130: 水泵
A131: KC2EWP25200 | B131: 配件 | C131: 水泵 | F131: D | G131: 李莉玲 | H131: 0 | I131: 0 | J131: 11 | K131: 6 | L131: 21 | M131: 38 | N131: 20 | O131: 58 | P131: 1546.9027 | Q131: 2361.062 | R131: 1 | S131: 1 | T131: 1 | U131: 1 | V131: 0 | W131: 0 | X131: 20 | Y131: 20 | Z131: 40.707965 | AA131: 40.707965 | AB131: 58 | AC131: 38 | AD131: 17 | AE131: 0 | AF131: 11 | AG131: 6 | AH131: 4.5 | AI131: 32 | AJ131: 6 | AK131: 1302.6549 | AL131: KAC | AM131: 0 | AN131: 1 | AP131: 46226 | AQ131: N | AR131: 水泵
A132: KC2EWP22300 | B132: 配件 | C132: 水泵 | F132: 推新 | G132: 李莉玲 | H132: 0 | I132: 0 | J132: 5 | K132: 14 | L132: 18 | M132: 37 | N132: 0 | O132: 37 | P132: 1686.2832 | Q132: 1686.2832 | R132: 0 | S132: 3 | T132: 4 | U132: 0 | V132: 0 | W132: 0 | X132: 0 | Y132: 0 | Z132: 45.575221 | AA132: 182.30088 | AB132: 9.25 | AC132: 9.25 | AD132: 4.75 | AE132: 0 | AF132: 1.25 | AG132: 3.5 | AH132: 4.5 | AI132: 13 | AJ132: 6 | AK132: 592.47787 | AL132: KAC | AM132: 0 | AN132: 4 | AP132: 46257 | AQ132: N | AR132: 水泵
A133: KC2EWP25000 | B133: 配件 | C133: 水泵 | F133: 推新 | G133: 李莉玲 | H133: 6 | I133: 6 | J133: 0 | K133: 24 | L133: 1 | M133: 37 | N133: 42 | O133: 79 | P133: 4518.5841 | Q133: 9647.7876 | R133: 3 | S133: 6 | T133: 13 | U133: 5 | V133: 0 | W133: 0 | X133: 0 | Y133: 0 | Z133: 122.12389 | AA133: 1587.6106 | AB133: 6.0769231 | AC133: 2.8461538 | AD133: 2.7692308 | AE133: 0.46153846 | AF133: 0 | AG133: 1.8461538 | AH133: 4.5 | AI133: 0 | AJ133: 6 | AK133: 0 | AL133: KAC | AM133: 0 | AN133: 13 | AO133: 46298 | AP133: 46233 | AQ133: N | AR133: 水泵
